Workbook

Sheet Lienzos y espejos
A1: Basar Ojos Color Sol | Y1: Entradas totales de la semana | Z1: Importe de las Entradas Semanal | AO1: Importe en $
AA2: Basar Ojos Color Sol | AH2: Basar Ojos Color Sol
A5: INVENTARIO | F5: 46152 | G5: Semana del 11 al 16 de Mayo | U5: Venta Total | V5: Deuda | W5: Baja sem. | X5: F. 16/5 /26 | AO5: No | AP5: Total al costo | AQ5: Total a la Venta | AR5: Utilidad Total | AS5: $ en Mercancia
G6: D-10 | I6: L-11 | K6: M-12 | M6: Mi-13 | O6: J-14 | Q6: V-15 | S6: S-16 | AA6: =G5 -> Semana del 11 al 16 de Mayo | AH6: =AA6 -> Semana del 11 al 16 de Mayo
A7: No | B7: Costo | C7: Venta | D7: Gan. | E7: Producto | G7: Entra. | H7: Venta | I7: Entra. | J7: Venta | K7: Entra. | L7: Venta | M7: Entra. | N7: Venta | O7: Entra. | P7: Venta | Q7: Entra. | R7: Venta | S7: Entra. | T7: Venta | AA7: Domingo | AB7: Lunes | AC7: Martes | AD7: Miercoles | AE7: Jueves | AF7: Viernes | AG7: Sabado | AH7: Cuadre en efectivo de la Semana
E8: Lienzoz y Espejos | Z8: =Z9+Z10+Z11+Z12+Z13+Z14+Z15+Z16+Z17+Z19+Z20+Z21+Z22+Z23+Z24+Z25+Z26+Z27+Z30+Z31+Z32+Z33+Z34+Z35+Z36+Z37+Z38+Z39+Z40+Z41+Z42+Z43+Z44+Z45+Z47+Z48+Z49+Z50+Z51+Z52+Z53+Z54+Z55+Z56+Z57+Z58+Z59+Z60+Z61+Z62+Z63+Z64+Z65+Z66+Z67+Z68+Z69+Z70+Z71 -> 0 | AH8: Domingo | AI8: Lunes | AJ8: Martes | AK8: Miercoles | AL8: Jueves | AM8: Viernes | AN8: Sabado | AP8: =AP9+AP10+AP11+AP12+AP13+AP14+AP15+AP16+AP17+AP18+AP19+AP20+AP21+AP22+AP23+AP24+AP25+AP26+AP27+AP28+AP29+AP30+AP31+AP32+AP33+AP34+AP35+AP36+AP37+AP38+AP39+AP40+AP41+AP42+AP43+AP44+AP45+AP46+AP47+AP48+AP49+AP50+AP51+AP52+AP53+AP54+AP55+AP56+AP57+AP58+AP59+AP60+AP61+AP62+AP63+AP64+AP65+AP66+AP67+AP68+AP69+AP70+AP71+AP72+AP73+AP74+AP75+AP76+AP77+AP78+AP79+AP80+AP81+AP82+AP83+AP84+AP85+AP86+AP87+AP88+AP89+AP90+AP91+AP92+AP93+AP94+AP95+AP96+AP97+AP98+AP99+AP100+AP101+AP102+AP103+AP104+AP105+AP106+AP107+AP108+AP109+AP110+AP111+AP112+AP113+AP114+AP115+AP116+AP117+AP118+AP119+AP120+AP121+AP122+AP123+AP124+AP125+AP126+AP127+AP128+AP129+AP130+AP131+AP132+AP134+AP135+AP136+AP137+AP138+AP139+AP140+AP141+AP142+AP143+AP144+AP145+AP146+AP147+AP148+AP149+AP150+AP151+AP152+AP153+AP154+AP155+AP156+AP157+AP158+AP159+AP160+AP161+AP162+AP163+AP164+AP165+AP166+AP167+AP168+AP169+AP170+AP171+AP172+AP173+AP174+AP175+AP176+AP177+AP178+AP179+AP180+AP181+AP182+AP183+AP184+AP185+AP186+AP187+AP188+AP189+AP190+AP191+AP192+AP193+AP194+AP195+AP196+AP197+AP198+AP199+AP200+AP201+AP202+AP203+AP204+AP205+AP207+AP208+AP209+AP210+AP211+AP212+AP213+AP214+AP215+AP216+AP217+AP218+AP220+AP221+AP222+AP223+AP224+AP225+AP226+AP227+AP228+AP229+AP230+AP231+AP232+AP233+AP234+AP235+AP236+AP237+AP238+AP239+AP240+AP241+AP243+AP244+AP245+AP246+AP247+AP248+AP249+AP250+AP251+AP252+AP253+AP254+AP255+AP256+AP257+AP258+AP259+AP260+AP261+AP262+AP263+AP264+AP265+AP266+AP267+AP269+AP270+AP271+AP272+AP273+AP274+AP275+AP276+AP279+AP280+AP281+AP282+AP283+AP284+AP286+AP287+AP288+AP289+AP290+AP291+AP292+AP293+AP294+AP295+AP296+AP297+AP298+AP299+AP300+AP301+AP302+AP303+AP304+AP305+AP306+AP307+AP308+AP309+AP310+AP311+AP312+AP313+AP314+AP315+AP316+AP317+AP318+AP319+AP320+AP321+AP322+AP323+AP324+AP325+AP326+AP327+AP328+AP329+AP330+AP331+AP332+AP333+AP334+AP335+AP336+AP337+AP338+AP339+AP340+AP341+AP342+AP343+AP344+AP345+AP346+AP347+AP348+AP349+AP350+AP351+AP352+AP353+AP354+AP355+AP356+AP357+AP358+AP359+AP360+AP361+AP362+AP363+AP364+AP365+AP366+AP367+AP369+AP370+AP371+AP372+AP373+AP374+AP375+AP376+AP377+AP378+AP379+AP380+AP381+AP382+AP383+AP384+AP385+AP386+AP387+AP388+AP389+AP390+AP391+AP392+AP393+AP394+AP395+AP396+AP397+AP398+AP399+AP400+AP401+AP402+AP403+AP404+AP405+AP406+AP407+AP408+AP409+AP410+AP411+AP412+AP413+AP414+AP415+AP416+AP417+AP418+AP419+AP420+AP422+AP423+AP424+AP425+AP426+AP427+AP428+AP429+AP430+AP431+AP432+AP433+AP434+AP435+AP436+AP437+AP438+AP439+AP440+AP441+AP442+AP443+AP444+AP445+AP446+AP447+AP448+AP449+AP450+AP451+AP452+AP453+AP454+AP455+AP456+AP457+AP458+AP459+AP460+AP461+AP462+AP463+AP464+AP465+AP466+AP467+AP468+AP469+AP470+AP471+AP472+AP473+AP474 -> 0 | AQ8: =AQ9+AQ10+AQ11+AQ12+AQ13+AQ14+AQ15+AQ16+AQ17+AQ18+AQ19+AQ20+AQ21+AQ22+AQ23+AQ24+AQ25+AQ26+AQ27+AQ28+AQ29+AQ30+AQ31+AQ32+AQ33+AQ34+AQ35+AQ36+AQ37+AQ38+AQ39+AQ40+AQ41+AQ42+AQ43+AQ44+AQ45+AQ46+AQ47+AQ48+AQ49+AQ50+AQ51+AQ52+AQ53+AQ54+AQ55+AQ56+AQ57+AQ58+AQ59+AQ60+AQ61+AQ62+AQ63+AQ64+AQ65+AQ66+AQ67+AQ68+AQ69+AQ70+AQ71+AQ72+AQ73+AQ74+AQ75+AQ76+AQ77+AQ78+AQ79+AQ80+AQ81+AQ82+AQ83+AQ84+AQ85+AQ86+AQ87+AQ88+AQ89+AQ90+AQ91+AQ92+AQ93+AQ94+AQ95+AQ96+AQ97+AQ98+AQ99+AQ100+AQ101+AQ102+AQ103+AQ104+AQ105+AQ106+AQ107+AQ108+AQ109+AQ110+AQ111+AQ112+AQ113+AQ114+AQ115+AQ116+AQ117+AQ118+AQ119+AQ120+AQ121+AQ122+AQ123+AQ124+AQ125+AQ126+AQ127+AQ128+AQ129+AQ130+AQ131+AQ132+AQ133+AQ134+AQ135+AQ136+AQ137+AQ138+AQ139+AQ140+AQ141+AQ142+AQ143+AQ144+AQ145+AQ146+AQ147+AQ148+AQ149+AQ150+AQ151+AQ152+AQ153+AQ154+AQ155+AQ156+AQ157+AQ158+AQ159+AQ160+AQ161+AQ162+AQ163+AQ164+AQ165+AQ166+AQ167+AQ168+AQ169+AQ170+AQ171+AQ172+AQ173+AQ174+AQ175+AQ176+AQ177+AQ178+AQ179+AQ180+AQ181+AQ182+AQ183+AQ184+AQ185+AQ186+AQ187+AQ188+AQ189+AQ190+AQ191+AQ192+AQ193+AQ194+AQ195+AQ196+AQ197+AQ198+AQ199+AQ200+AQ201+AQ202+AQ203+AQ204+AQ205+AQ206+AQ207+AQ208+AQ209+AQ210+AQ211+AQ212+AQ213+AQ214+AQ215+AQ216+AQ217+AQ218+AQ219+AQ220+AQ221+AQ222+AQ223+AQ224+AQ225+AQ226+AQ227+AQ228+AQ229+AQ230+AQ231+AQ232+AQ233+AQ234+AQ235+AQ236+AQ237+AQ238+AQ239+AQ240+AQ241+AQ242+AQ243+AQ244+AQ245+AQ246+AQ247+AQ248+AQ249+AQ250+AQ251+AQ252+AQ253+AQ254+AQ255+AQ256+AQ257+AQ258+AQ259+AQ260+AQ261+AQ262+AQ263+AQ264+AQ265+AQ266+AQ267+AQ268+AQ269+AQ270+AQ271+AQ272+AQ273+AQ274+AQ275+AQ276+AQ277+AQ278+AQ279+AQ280+AQ281+AQ282+AQ283+AQ284+AQ285+AQ286+AQ287+AQ288+AQ289+AQ290+AQ291+AQ292+AQ293+AQ294+AQ295+AQ296+AQ297+AQ298+AQ299+AQ300+AQ301+AQ302+AQ303+AQ304+AQ305+AQ306+AQ307+AQ308+AQ309+AQ310+AQ311+AQ312+AQ313+AQ314+AQ315+AQ316+AQ317+AQ318+AQ319+AQ320+AQ321+AQ322+AQ323+AQ324+AQ325+AQ326+AQ327+AQ328+AQ329+AQ330+AQ331+AQ332+AQ333+AQ334+AQ335+AQ336+AQ337+AQ338+AQ339+AQ340+AQ341+AQ342+AQ343+AQ344+AQ345+AQ346+AQ347+AQ348+AQ349+AQ350+AQ351+AQ352+AQ353+AQ354+AQ355+AQ356+AQ357+AQ358+AQ359+AQ360+AQ361+AQ362+AQ363+AQ364+AQ365+AQ366+AQ367+AQ368+AQ369+AQ370+AQ371+AQ372+AQ373+AQ374+AQ375+AQ376+AQ377+AQ378+AQ379+AQ380+AQ381+AQ382+AQ383+AQ384+AQ385+AQ386+AQ387+AQ388+AQ389+AQ390+AQ391+AQ392+AQ393+AQ394+AQ395+AQ396+AQ397+AQ398+AQ399+AQ400+AQ401+AQ402+AQ403+AQ404+AQ405+AQ406+AQ407+AQ408+AQ409+AQ410+AQ411+AQ412+AQ413+AQ414+AQ415+AQ416+AQ417+AQ418+AQ419+AQ420+AQ421+AQ422+AQ423+AQ424+AQ425+AQ426+AQ427+AQ428+AQ429+AQ430+AQ431+AQ432+AQ433+AQ434+AQ435+AQ436+AQ437+AQ438+AQ439+AQ440+AQ441+AQ442+AQ443+AQ444+AQ445+AQ446+AQ447+AQ448+AQ449+AQ450+AQ451+AQ452+AQ453+AQ454+AQ455+AQ456+AQ457+AQ458+AQ459+AQ460+AQ461+AQ462+AQ463+AQ464+AQ465+AQ466+AQ467+AQ468+AQ469+AQ470+AQ471+AQ472+AQ473+AQ474+AQ475+AQ476+AQ477+AQ478+AQ479+AQ480+AQ481+AQ482+AQ483+AQ484+AQ485+AQ486+AQ487+AQ488+AQ489+AQ490+AQ491+AQ492+AQ493+AQ494+AQ495+AQ496+AQ497+AQ498+AQ499+AQ500+AQ501+AQ502+AQ503+AQ504+AQ505+AQ506+AQ507+AQ508+AQ509+AQ510+AQ511+AQ512+AQ513+AQ514+AQ515+AQ516+AQ517+AQ518+AQ519+AQ520+AQ521+AQ522+AQ523+AQ524+AQ525+AQ526+AQ527+AQ528+AQ529+AQ530+AQ531+AQ532+AQ533+AQ534+AQ535+AQ536+AQ537+AQ538+AQ539+AQ540+AQ541+AQ542+AQ543+AQ544+AQ545+AQ546+AQ547+AQ548+AQ549+AQ550+AQ551+AQ552+AQ553+AQ554+AQ555+AQ556 -> 0 | AR8: =AQ8-AP8 -> 0 | AS8: =AS9+AS10+AS11+AS12+AS13+AS14+AS15+AS16+AS17+AS18+AS19+AS20+AS21+AS22+AS23+AS24+AS25+AS26+AS27+AS28+AS29+AS30+AS31+AS32+AS33+AS34+AS35+AS36+AS37+AS38+AS39+AS40+AS41+AS42+AS43+AS44+AS45+AS46+AS47+AS48+AS49+AS50+AS51+AS52+AS53+AS54+AS55+AS56+AS57+AS58+AS59+AS60+AS61+AS62+AS63+AS64+AS65+AS66+AS67+AS68+AS69+AS70+AS71+AS72+AS73+AS74+AS75+AS76+AS77+AS78+AS79+AS80+AS81+AS82+AS83+AS84+AS85+AS86+AS87+AS88+AS89+AS90+AS91+AS92+AS93+AS94+AS95+AS96+AS97+AS98+AS99+AS100+AS101+AS102+AS103+AS104+AS105+AS106+AS107+AS108+AS109+AS110+AS111+AS112+AS113+AS114+AS115+AS116+AS117+AS118+AS119+AS120+AS121+AS122+AS123+AS124+AS125+AS126+AS127+AS128+AS129+AS130+AS131+AS132+AS133+AS134+AS135+AS136+AS137+AS138+AS139+AS140+AS141+AS142+AS143+AS144+AS145+AS146+AS147+AS148+AS149+AS150+AS151+AS152+AS153+AS154+AS155+AS156+AS157+AS158+AS159+AS160+AS161+AS162+AS163+AS164+AS165+AS166+AS167+AS168+AS169+AS170+AS171+AS172+AS173+AS174+AS175+AS176+AS177+AS178+AS179+AS180+AS181+AS182+AS183+AS184+AS185+AS186+AS187+AS188+AS189+AS190+AS191+AS192+AS193+AS194+AS195+AS196+AS197+AS198+AS199+AS200+AS201+AS202+AS203+AS204+AS205+AS207+AS208+AS209+AS210+AS211+AS212+AS213+AS214+AS215+AS216+AS217+AS218+AS220+AS221+AS222+AS223+AS224+AS225+AS226+AS227+AS228+AS229+AS230+AS231+AS232+AS233+AS234+AS235+AS236+AS237+AS238+AS239+AS240+AS241+AS243+AS244+AS245+AS246+AS247+AS248+AS249+AS250+AS251+AS252+AS253+AS254+AS255+AS256+AS257+AS258+AS259+AS260+AS261+AS262+AS263+AS264+AS265+AS266+AS267+AS269+AS270+AS271+AS272+AS273+AS274+AS275+AS276+AS279+AS280+AS281+AS282+AS283+AS284+AS286+AS287+AS288+AS289+AS290+AS291+AS292+AS293+AS294+AS295+AS296+AS297+AS298+AS299+AS300+AS301+AS302+AS303+AS304+AS305+AS306+AS307+AS308+AS309+AS310+AS311+AS312+AS313+AS314+AS315+AS316+AS317+AS318+AS319+AS320+AS321+AS322+AS323+AS324+AS325+AS326+AS327+AS328+AS329+AS330+AS331+AS332+AS333+AS334+AS335+AS336+AS337+AS338+AS339+AS340+AS341+AS342+AS343+AS344+AS345+AS346+AS347+AS348+AS349+AS350+AS351+AS352+AS353+AS354+AS355+AS356+AS357+AS358+AS359+AS360+AS361+AS362+AS363+AS364+AS365+AS366+AS367+AS369+AS370+AS371+AS372+AS373+AS374+AS375+AS376+AS377+AS378+AS379+AS380+AS381+AS382+AS383+AS384+AS385+AS386+AS387+AS388+AS389+AS390+AS391+AS392+AS393+AS394+AS395+AS396+AS397+AS398+AS399+AS400+AS401+AS402+AS403+AS404+AS405+AS406+AS407+AS408+AS409+AS410+AS411+AS412+AS413+AS414+AS415+AS416+AS417+AS418+AS419+AS420+AS422+AS423+AS424+AS425+AS426+AS427+AS428+AS429+AS430+AS431+AS432+AS433+AS434+AS435+AS436+AS437+AS438+AS439+AS440+AS441+AS442+AS443+AS444+AS445+AS446+AS447+AS448+AS449+AS450+AS451+AS452+AS453+AS454+AS455+AS456+AS457+AS458+AS459+AS460+AS461+AS462+AS463+AS464+AS465+AS466+AS467+AS468+AS469+AS470+AS471+AS472+AS473+AS474 -> 15000
A9: 1 | B9: 1300 | C9: 2000 | D9: 700 | E9: Lona Chicas | F9: 3 | U9: =H9+J9+L9+N9+P9+R9+T9 -> 0 | X9: =F9+G9+I9+K9+M9+O9+Q9+S9-H9-J9-L9-N9-P9-R9-T9-V9-W9 -> 3 | Y9: =G9+I9+K9+M9+O9+Q9+S9 -> 0 | Z9: =Y9*B9 -> 0 | AA9: =H9*C9 -> 0 | AB9: =J9*C9 -> 0 | AC9: =L9*C9 -> 0 | AD9: =N9*C9 -> 0 | AE9: =P9*C9 -> 0 | AF9: =R9*C9 -> 0 | AG9: =T9*C9 -> 0 | AH9: =AA9+AA10+AA11+AA12+AA13+AA14+AA15+AA16+AA17+AA18+AA19+AA20+AA21+AA22+AA23+AA24+AA25+AA26+AA27+AA28+AA30+AA31+AA32+AA33+AA34+AA35+AA36+AA37+AA38+AA39+AA40+AA41+AA42+AA43+AA44+AA45+AA47+AA48+AA49+AA50+AA51+AA52+AA53+AA54+AA55+AA56+AA57+AA58+AA59+AA60+AA61+AA62+AA63+AA64+AA65+AA66+AA67+AA68+AA69+AA70+AA71+AA72+AA73+AA74+AA75+AA76+AA77+AA78+AA79+AA80+AA81+AA82+AA83+AA84+AA85+AA86+AA87+AA88+AA89+AA90+AA91+AA92+AA93+AA94+AA95+AA96+AA97+AA98+AA99+AA100+AA101+AA102+AA103+AA104+AA105+AA106+AA107+AA108+AA109+AA110+AA111+AA112+AA113+AA114+AA115+AA116+AA117+AA118+AA119+AA120+AA121+AA122+AA123+AA124+AA125+AA126+AA127+AA128+AA129+AA130+AA131+AA132+AA133+AA134+AA135+AA136+AA137+AA138+AA139+AA140+AA141+AA142+AA143+AA144+AA145+AA146+AA147+AA148+AA149+AA150+AA151+AA152+AA153+AA154+AA155+AA156+AA157+AA158+AA159+AA160+AA161+AA162+AA163+AA164+AA165+AA166+AA167+AA168+AA169+AA170+AA171+AA172+AA173+AA174+AA175+AA176+AA177+AA178+AA179+AA180+AA181+AA182+AA183+AA184+AA185+AA186+AA187+AA188+AA189+AA190+AA191+AA192+AA193+AA194+AA195+AA196+AA197+AA198+AA199+AA200+AA201+AA202+AA203+AA204+AA205+AA206+AA207+AA208+AA209+AA210+AA211+AA212+AA213+AA214+AA215+AA216+AA217+AA218+AA219+AA220+AA221+AA222+AA223+AA224+AA225+AA226+AA227+AA228+AA229+AA230+AA231+AA232+AA233+AA234+AA235+AA236+AA237+AA238+AA239+AA240+AA241+AA242+AA243+AA244+AA245+AA246+AA247+AA248+AA249+AA250+AA251+AA252+AA253+AA254+AA255+AA256+AA257+AA258+AA259+AA260+AA261+AA262+AA263+AA264+AA265+AA266+AA267+AA268+AA269+AA270+AA271+AA272+AA273+AA274+AA275+AA276+AA277+AA278+AA279+AA280+AA281+AA282+AA283+AA284+AA285+AA286+AA287+AA288+AA289+AA290+AA291+AA292+AA293+AA294+AA295+AA296+AA297+AA298+AA299+AA300+AA301+AA302+AA303+AA304+AA305+AA306+AA307+AA308+AA309+AA310+AA311+AA312+AA313+AA314+AA315+AA316+AA317+AA318+AA319+AA320+AA321+AA322+AA323+AA324+AA325+AA326+AA327+AA328+AA329+AA330+AA331+AA332+AA333+AA334+AA335+AA336+AA337+AA338+AA339+AA340+AA341+AA342+AA343+AA344+AA345+AA346+AA347+AA348+AA349+AA350+AA351+AA352+AA353+AA354+AA355+AA356+AA357+AA358+AA359+AA360+AA361+AA362+AA363+AA364+AA365+AA366+AA367+AA368+AA369+AA370+AA371+AA372+AA373+AA374+AA375+AA376+AA377+AA378+AA379+AA380+AA381+AA382+AA383+AA384+AA385+AA386+AA387+AA388+AA389+AA390+AA391+AA392+AA393+AA394+AA395+AA396+AA397+AA398+AA399+AA400+AA401+AA402+AA403+AA404+AA405+AA406+AA407+AA408+AA409+AA410+AA411+AA412+AA413+AA414+AA415+AA416+AA417+AA418+AA419+AA420+AA421+AA422+AA423+AA424+AA425+AA426+AA427+AA428+AA429+AA430+AA431+AA432+AA433+AA434+AA435+AA436+AA437+AA438+AA439+AA440+AA441+AA442+AA443+AA444+AA445+AA446+AA447+AA448+AA449+AA450+AA451+AA452+AA453+AA454+AA455+AA456+AA457+AA458+AA459+AA460+AA461+AA462+AA463+AA464+AA465+AA466+AA467+AA468+AA469+AA470+AA471+AA472+AA473+AA474+AA475+AA476+AA477+AA478+AA479+AA480+AA481+AA482+AA483+AA484+AA485+AA486+AA487+AA488+AA489+AA490+AA491+AA492+AA493+AA494+AA495+AA496+AA497+AA498+AA499+AA500+AA501+AA502+AA503+AA504+AA505+AA506+AA507+AA508+AA509+AA510+AA511+AA512+AA513+AA514+AA515+AA516+AA517+AA518+AA519+AA520+AA521+AA522+AA523+AA524+AA525+AA526+AA527+AA528+AA529+AA530+AA531+AA532+AA533+AA534+AA535+AA536+AA537+AA538+AA539+AA540+AA541+AA542+AA543+AA544+AA545+AA546+AA547+AA548+AA549+AA550+AA551+AA552+AA553+AA554+AA555+AA556+AA557+AA558+AA559+AA560+AA561+AA562+AA563 -> 0 | AI9: =AB9+AB10+AB11+AB12+AB13+AB14+AB15+AB16+AB17+AB18+AB19+AB20+AB21+AB22+AB23+AB24+AB25+AB26+AB27+AB28+AB29+AB30+AB31+AB32+AB33+AB34+AB35+AB36+AB37+AB38+AB39+AB40+AB41+AB42+AB43+AB44+AB45+AB46+AB47+AB48+AB49+AB50+AB51+AB52+AB53+AB54+AB55+AB56+AB57+AB58+AB59+AB60+AB61+AB62+AB63+AB64+AB65+AB66+AB67+AB68+AB69+AB70+AB71+AB72+AB73+AB74+AB75+AB76+AB77+AB78+AB79+AB80+AB81+AB82+AB83+AB84+AB85+AB86+AB87+AB88+AB89+AB90+AB91+AB92+AB93+AB94+AB95+AB96+AB97+AB98+AB99+AB100+AB101+AB102+AB103+AB104+AB105+AB106+AB107+AB108+AB109+AB110+AB111+AB112+AB113+AB114+AB115+AB116+AB117+AB118+AB119+AB120+AB121+AB122+AB123+AB124+AB125+AB126+AB127+AB128+AB129+AB130+AB131+AB132+AB133+AB134+AB135+AB136+AB137+AB138+AB139+AB140+AB141+AB142+AB143+AB144+AB145+AB146+AB147+AB148+AB149+AB150+AB151+AB152+AB153+AB154+AB155+AB156+AB157+AB158+AB159+AB160+AB161+AB162+AB163+AB164+AB165+AB166+AB167+AB168+AB169+AB170+AB171+AB172+AB173+AB174+AB175+AB176+AB177+AB178+AB179+AB180+AB181+AB182+AB183+AB184+AB185+AB186+AB187+AB188+AB189+AB190+AB191+AB192+AB193+AB194+AB195+AB196+AB197+AB198+AB199+AB200+AB201+AB202+AB203+AB204+AB205+AB206+AB207+AB208+AB209+AB210+AB211+AB212+AB213+AB214+AB215+AB216+AB217+AB218+AB219+AB220+AB221+AB222+AB223+AB224+AB225+AB226+AB227+AB228+AB229+AB230+AB231+AB232+AB233+AB234+AB235+AB236+AB237+AB238+AB239+AB240+AB241+AB242+AB243+AB244+AB245+AB246+AB247+AB248+AB249+AB250+AB251+AB252+AB253+AB254+AB255+AB256+AB257+AB258+AB259+AB260+AB261+AB262+AB263+AB264+AB265+AB266+AB267+AB268+AB269+AB270+AB271+AB272+AB273+AB274+AB275+AB276+AB277+AB278+AB279+AB280+AB281+AB282+AB283+AB284+AB285+AB286+AB287+AB288+AB289+AB290+AB291+AB292+AB293+AB294+AB295+AB296+AB297+AB298+AB299+AB300+AB301+AB302+AB303+AB304+AB305+AB306+AB307+AB308+AB309+AB310+AB311+AB312+AB313+AB314+AB315+AB316+AB317+AB318+AB319+AB320+AB321+AB322+AB323+AB324+AB325+AB326+AB327+AB328+AB329+AB330+AB331+AB332+AB333+AB334+AB335+AB336+AB337+AB338+AB339+AB340+AB341+AB342+AB343+AB344+AB345+AB346+AB347+AB348+AB349+AB350+AB351+AB352+AB353+AB354+AB355+AB356+AB357+AB358+AB359+AB360+AB361+AB362+AB363+AB364+AB365+AB366+AB367+AB368+AB369+AB370+AB371+AB372+AB373+AB374+AB375+AB376+AB377+AB378+AB379+AB380+AB381+AB382+AB383+AB384+AB385+AB386+AB387+AB388+AB389+AB390+AB391+AB392+AB393+AB394+AB395+AB396+AB397+AB398+AB399+AB400+AB401+AB402+AB403+AB404+AB405+AB406+AB407+AB408+AB409+AB410+AB411+AB412+AB413+AB414+AB415+AB416+AB417+AB418+AB419+AB420+AB421+AB422+AB423+AB424+AB425+AB426+AB427+AB428+AB429+AB430+AB431+AB432+AB433+AB434+AB435+AB436+AB437+AB438+AB439+AB440+AB441+AB442+AB443+AB444+AB445+AB446+AB447+AB448+AB449+AB450+AB451+AB452+AB453+AB454+AB455+AB456+AB457+AB458+AB459+AB460+AB461+AB462+AB463+AB464+AB465+AB466+AB467+AB468+AB469+AB470+AB471+AB472+AB473+AB474+AB475+AB476+AB477+AB478+AB479+AB480+AB481+AB482+AB483+AB484+AB485+AB486+AB487+AB488+AB489+AB490+AB491+AB492+AB493+AB494+AB495+AB496+AB497+AB498+AB499+AB500+AB501+AB502+AB503+AB504+AB505+AB506+AB507+AB508+AB509+AB510+AB511+AB512+AB513+AB514+AB515+AB516+AB517+AB518+AB519+AB520+AB521+AB522+AB523+AB524+AB525+AB526+AB527+AB528+AB529+AB530+AB531+AB532+AB533+AB534+AB535+AB536+AB537+AB538+AB539+AB540+AB541+AB542+AB543+AB544+AB545+AB546+AB547+AB548+AB549+AB550+AB551+AB552+AB553+AB554+AB555+AB556+AB557+AB558+AB559+AB560+AB561+AB562+AB563 -> 0 | AJ9: =AC9+AC10+AC11+AC12+AC13+AC14+AC15+AC16+AC17+AC18+AC19+AC20+AC21+AC22+AC23+AC24+AC25+AC26+AC27+AC28+AC29+AC30+AC31+AC32+AC33+AC34+AC35+AC36+AC37+AC38+AC39+AC40+AC41+AC42+AC43+AC44+AC45+AC46+AC47+AC48+AC49+AC50+AC51+AC52+AC53+AC54+AC55+AC56+AC57+AC58+AC59+AC60+AC61+AC62+AC63+AC64+AC65+AC66+AC67+AC68+AC69+AC70+AC71+AC72+AC73+AC74+AC75+AC76+AC77+AC78+AC79+AC80+AC81+AC82+AC83+AC84+AC85+AC86+AC87+AC88+AC89+AC90+AC91+AC92+AC93+AC94+AC95+AC96+AC97+AC98+AC99+AC100+AC101+AC102+AC103+AC104+AC105+AC106+AC107+AC108+AC109+AC110+AC111+AC112+AC113+AC114+AC115+AC116+AC117+AC118+AC119+AC120+AC121+AC122+AC123+AC124+AC125+AC126+AC127+AC128+AC129+AC130+AC131+AC132+AC133+AC134+AC135+AC136+AC137+AC138+AC139+AC140+AC141+AC142+AC143+AC144+AC145+AC146+AC147+AC148+AC149+AC150+AC151+AC152+AC153+AC154+AC155+AC156+AC157+AC158+AC159+AC160+AC161+AC162+AC163+AC164+AC165+AC166+AC167+AC168+AC169+AC170+AC171+AC172+AC173+AC174+AC175+AC176+AC177+AC178+AC179+AC180+AC181+AC182+AC183+AC184+AC185+AC186+AC187+AC188+AC189+AC190+AC191+AC192+AC193+AC194+AC195+AC196+AC197+AC198+AC199+AC200+AC201+AC202+AC203+AC204+AC205+AC206+AC207+AC208+AC209+AC210+AC211+AC212+AC213+AC214+AC215+AC216+AC217+AC218+AC219+AC220+AC221+AC222+AC223+AC224+AC225+AC226+AC227+AC228+AC229+AC230+AC231+AC232+AC233+AC234+AC235+AC236+AC237+AC238+AC239+AC240+AC241+AC242+AC243+AC244+AC245+AC246+AC247+AC248+AC249+AC250+AC251+AC252+AC253+AC254+AC255+AC256+AC257+AC258+AC259+AC260+AC261+AC262+AC263+AC264+AC265+AC266+AC267+AC268+AC269+AC270+AC271+AC272+AC273+AC274+AC275+AC276+AC277+AC278+AC279+AC280+AC281+AC282+AC283+AC284+AC285+AC286+AC287+AC288+AC289+AC290+AC291+AC292+AC293+AC294+AC295+AC296+AC297+AC298+AC299+AC300+AC301+AC302+AC303+AC304+AC305+AC306+AC307+AC308+AC309+AC310+AC311+AC312+AC313+AC314+AC315+AC316+AC317+AC318+AC319+AC320+AC321+AC322+AC323+AC324+AC325+AC326+AC327+AC328+AC329+AC330+AC331+AC332+AC333+AC334+AC335+AC336+AC337+AC338+AC339+AC340+AC341+AC342+AC343+AC344+AC345+AC346+AC347+AC348+AC349+AC350+AC351+AC352+AC353+AC354+AC355+AC356+AC357+AC358+AC359+AC360+AC361+AC362+AC363+AC364+AC365+AC366+AC367+AC368+AC369+AC370+AC371+AC372+AC373+AC374+AC375+AC376+AC377+AC378+AC379+AC380+AC381+AC382+AC383+AC384+AC385+AC386+AC387+AC388+AC389+AC390+AC391+AC392+AC393+AC394+AC395+AC396+AC397+AC398+AC399+AC400+AC401+AC402+AC403+AC404+AC405+AC406+AC407+AC408+AC409+AC410+AC411+AC412+AC413+AC414+AC415+AC416+AC417+AC418+AC419+AC420+AC421+AC422+AC423+AC424+AC425+AC426+AC427+AC428+AC429+AC430+AC431+AC432+AC433+AC434+AC435+AC436+AC437+AC438+AC439+AC440+AC441+AC442+AC443+AC444+AC445+AC446+AC447+AC448+AC449+AC450+AC451+AC452+AC453+AC454+AC455+AC456+AC457+AC458+AC459+AC460+AC461+AC462+AC463+AC464+AC465+AC466+AC467+AC468+AC469+AC470+AC471+AC472+AC473+AC474+AC475+AC476+AC477+AC478+AC479+AC480+AC481+AC482+AC483+AC484+AC485+AC486+AC487+AC488+AC489+AC490+AC491+AC492+AC493+AC494+AC495+AC496+AC497+AC498+AC499+AC500+AC501+AC502+AC503+AC504+AC505+AC506+AC507+AC508+AC509+AC510+AC511+AC512+AC513+AC514+AC515+AC516+AC517+AC518+AC519+AC520+AC521+AC522+AC523+AC524+AC525+AC526+AC527+AC528+AC529+AC530+AC531+AC532+AC533+AC534+AC535+AC536+AC537+AC538+AC539+AC540+AC541+AC542+AC543+AC544+AC545+AC546+AC547+AC548+AC549+AC550+AC551+AC552+AC553+AC554+AC555+AC556+AC557+AC558+AC559+AC560+AC561+AC562+AC563 -> 0 | AK9: =AD9+AD10+AD11+AD12+AD13+AD14+AD15+AD16+AD17+AD18+AD19+AD20+AD21+AD22+AD23+AD24+AD25+AD26+AD27+AD28+AD29+AD30+AD31+AD32+AD33+AD34+AD35+AD36+AD37+AD38+AD39+AD40+AD41+AD42+AD43+AD44+AD45+AD47+AD48+AD49+AD50+AD51+AD52+AD53+AD54+AD55+AD56+AD57+AD58+AD59+AD60+AD61+AD62+AD63+AD64+AD65+AD66+AD67+AD68+AD69+AD70+AD71+AD72+AD73+AD74+AD75+AD76+AD77+AD78+AD79+AD80+AD81+AD82+AD83+AD84+AD85+AD86+AD87+AD88+AD89+AD90+AD91+AD92+AD93+AD94+AD95+AD96+AD97+AD98+AD99+AD100+AD101+AD102+AD103+AD104+AD105+AD106+AD107+AD108+AD109+AD110+AD111+AD112+AD113+AD114+AD115+AD116+AD117+AD118+AD119+AD120+AD121+AD122+AD123+AD124+AD125+AD126+AD127+AD128+AD129+AD130+AD131+AD132+AD133+AD134+AD135+AD136+AD137+AD138+AD139+AD140+AD141+AD142+AD143+AD144+AD145+AD146+AD147+AD148+AD149+AD150+AD151+AD152+AD153+AD154+AD155+AD156+AD157+AD158+AD159+AD160+AD161+AD162+AD163+AD164+AD165+AD166+AD167+AD168+AD169+AD170+AD171+AD172+AD173+AD174+AD175+AD176+AD177+AD178+AD179+AD180+AD181+AD182+AD183+AD184+AD185+AD186+AD187+AD188+AD189+AD190+AD191+AD192+AD193+AD194+AD195+AD196+AD197+AD198+AD199+AD200+AD201+AD202+AD203+AD204+AD205+AD206+AD207+AD208+AD209+AD210+AD211+AD212+AD213+AD214+AD215+AD216+AD217+AD218+AD219+AD220+AD221+AD222+AD223+AD224+AD225+AD226+AD227+AD228+AD229+AD230+AD231+AD232+AD233+AD234+AD235+AD236+AD237+AD238+AD239+AD240+AD241+AD242+AD243+AD244+AD245+AD246+AD247+AD248+AD249+AD250+AD251+AD252+AD253+AD254+AD255+AD256+AD257+AD258+AD259+AD260+AD261+AD262+AD263+AD264+AD265+AD266+AD267+AD268+AD269+AD270+AD271+AD272+AD273+AD274+AD275+AD276+AD277+AD278+AD279+AD280+AD281+AD282+AD283+AD284+AD285+AD286+AD287+AD288+AD289+AD290+AD291+AD292+AD293+AD294+AD295+AD296+AD297+AD298+AD299+AD300+AD301+AD302+AD303+AD304+AD305+AD306+AD307+AD308+AD309+AD310+AD311+AD312+AD313+AD314+AD315+AD316+AD317+AD318+AD319+AD320+AD321+AD322+AD323+AD324+AD325+AD326+AD327+AD328+AD329+AD330+AD331+AD332+AD333+AD334+AD335+AD336+AD337+AD338+AD339+AD340+AD341+AD342+AD343+AD344+AD345+AD346+AD347+AD348+AD349+AD350+AD351+AD352+AD353+AD354+AD355+AD356+AD357+AD358+AD359+AD360+AD361+AD362+AD363+AD364+AD365+AD366+AD367+AD368+AD369+AD370+AD371+AD372+AD373+AD374+AD375+AD376+AD377+AD378+AD379+AD380+AD381+AD382+AD383+AD384+AD385+AD386+AD387+AD388+AD389+AD390+AD391+AD392+AD393+AD394+AD395+AD396+AD397+AD398+AD399+AD400+AD401+AD402+AD403+AD404+AD405+AD406+AD407+AD408+AD409+AD410+AD411+AD412+AD413+AD414+AD415+AD416+AD417+AD418+AD419+AD420+AD421+AD422+AD423+AD424+AD425+AD426+AD427+AD428+AD429+AD430+AD431+AD432+AD433+AD434+AD435+AD436+AD437+AD438+AD439+AD440+AD441+AD442+AD443+AD444+AD445+AD446+AD447+AD448+AD449+AD450+AD451+AD452+AD453+AD454+AD455+AD456+AD457+AD458+AD459+AD460+AD461+AD462+AD463+AD464+AD465+AD466+AD467+AD468+AD469+AD470+AD471+AD472+AD473+AD474+AD475+AD476+AD477+AD478+AD479+AD480+AD481+AD482+AD483+AD484+AD485+AD486+AD487+AD488+AD489+AD490+AD491+AD492+AD493+AD494+AD495+AD496+AD497+AD498+AD499+AD500+AD501+AD502+AD503+AD504+AD505+AD506+AD507+AD508+AD509+AD510+AD511+AD512+AD513+AD514+AD515+AD516+AD517+AD518+AD519+AD520+AD521+AD522+AD523+AD524+AD525+AD526+AD527+AD528+AD529+AD530+AD531+AD532+AD533+AD534+AD535+AD536+AD537+AD538+AD539+AD540+AD541+AD542+AD543+AD544+AD545+AD546+AD547+AD548+AD549+AD550+AD551+AD552+AD553+AD554+AD555+AD556+AD557+AD558+AD559+AD560+AD561+AD562+AD563 -> 0 | AL9: =AE9+AE10+AE11+AE12+AE13+AE14+AE15+AE16+AE17+AE18+AE19+AE20+AE21+AE22+AE23+AE24+AE25+AE26+AE27+AE28+AE29+AE30+AE31+AE32+AE33+AE34+AE35+AE36+AE37+AE38+AE39+AE40+AE41+AE42+AE43+AE44+AE45+AE46+AE47+AE48+AE49+AE50+AE51+AE52+AE53+AE54+AE55+AE56+AE57+AE58+AE59+AE60+AE61+AE62+AE63+AE64+AE65+AE66+AE67+AE68+AE69+AE70+AE71+AE72+AE73+AE74+AE75+AE76+AE77+AE78+AE79+AE80+AE81+AE82+AE83+AE84+AE85+AE86+AE87+AE88+AE89+AE90+AE91+AE92+AE93+AE94+AE95+AE96+AE97+AE98+AE99+AE100+AE101+AE102+AE103+AE104+AE105+AE106+AE107+AE108+AE109+AE110+AE111+AE112+AE113+AE114+AE115+AE116+AE117+AE118+AE119+AE120+AE121+AE122+AE123+AE124+AE125+AE126+AE127+AE128+AE129+AE130+AE131+AE132+AE133+AE134+AE135+AE136+AE137+AE138+AE139+AE140+AE141+AE142+AE143+AE144+AE145+AE146+AE147+AE148+AE149+AE150+AE151+AE152+AE153+AE154+AE155+AE156+AE157+AE158+AE159+AE160+AE161+AE162+AE163+AE164+AE165+AE166+AE167+AE168+AE169+AE170+AE171+AE172+AE173+AE174+AE175+AE176+AE177+AE178+AE179+AE180+AE181+AE182+AE183+AE184+AE185+AE186+AE187+AE188+AE189+AE190+AE191+AE192+AE193+AE194+AE195+AE196+AE197+AE198+AE199+AE200+AE201+AE202+AE203+AE204+AE205+AE206+AE207+AE208+AE209+AE210+AE211+AE212+AE213+AE214+AE215+AE216+AE217+AE218+AE219+AE220+AE221+AE222+AE223+AE224+AE225+AE226+AE227+AE228+AE229+AE230+AE231+AE232+AE233+AE234+AE235+AE236+AE237+AE238+AE239+AE240+AE241+AE242+AE243+AE244+AE245+AE246+AE247+AE248+AE249+AE250+AE251+AE252+AE253+AE254+AE255+AE256+AE257+AE258+AE259+AE260+AE261+AE262+AE263+AE264+AE265+AE266+AE267+AE268+AE269+AE270+AE271+AE272+AE273+AE274+AE275+AE276+AE277+AE278+AE279+AE280+AE281+AE282+AE283+AE284+AE285+AE286+AE287+AE288+AE289+AE290+AE291+AE292+AE293+AE294+AE295+AE296+AE297+AE298+AE299+AE300+AE301+AE302+AE303+AE304+AE305+AE306+AE307+AE308+AE309+AE310+AE311+AE312+AE313+AE314+AE315+AE316+AE317+AE318+AE319+AE320+AE321+AE322+AE323+AE324+AE325+AE326+AE327+AE328+AE329+AE330+AE331+AE332+AE333+AE334+AE335+AE336+AE337+AE338+AE339+AE340+AE341+AE342+AE343+AE344+AE345+AE346+AE347+AE348+AE349+AE350+AE351+AE352+AE353+AE354+AE355+AE356+AE357+AE358+AE359+AE360+AE361+AE362+AE363+AE364+AE365+AE366+AE367+AE368+AE369+AE370+AE371+AE372+AE373+AE374+AE375+AE376+AE377+AE378+AE379+AE380+AE381+AE382+AE383+AE384+AE385+AE386+AE387+AE388+AE389+AE390+AE391+AE392+AE393+AE394+AE395+AE396+AE397+AE398+AE399+AE400+AE401+AE402+AE403+AE404+AE405+AE406+AE407+AE408+AE409+AE410+AE411+AE412+AE413+AE414+AE415+AE416+AE417+AE418+AE419+AE420+AE421+AE422+AE423+AE424+AE425+AE426+AE427+AE428+AE429+AE430+AE431+AE432+AE433+AE434+AE435+AE436+AE437+AE438+AE439+AE440+AE441+AE442+AE443+AE444+AE445+AE446+AE447+AE448+AE449+AE450+AE451+AE452+AE453+AE454+AE455+AE456+AE457+AE458+AE459+AE460+AE461+AE462+AE463+AE464+AE465+AE466+AE467+AE468+AE469+AE470+AE471+AE472+AE473+AE474+AE475+AE476+AE477+AE478+AE479+AE480+AE481+AE482+AE483+AE484+AE485+AE486+AE487+AE488+AE489+AE490+AE491+AE492+AE493+AE494+AE495+AE496+AE497+AE498+AE499+AE500+AE501+AE502+AE503+AE504+AE505+AE506+AE507+AE508+AE509+AE510+AE511+AE512+AE513+AE514+AE515+AE516+AE517+AE518+AE519+AE520+AE521+AE522+AE523+AE524+AE525+AE526+AE527+AE528+AE529+AE530+AE531+AE532+AE533+AE534+AE535+AE536+AE537+AE538+AE539+AE540+AE541+AE542+AE543+AE544+AE545+AE546+AE547+AE548+AE549+AE550+AE551+AE552+AE553+AE554+AE555+AE556+AE557+AE558+AE559+AE560+AE561+AE562+AE563 -> 0 | AM9: =AF9+AF10+AF11+AF12+AF13+AF14+AF15+AF16+AF17+AF18+AF19+AF20+AF21+AF22+AF23+AF24+AF25+AF26+AF27+AF28+AF29+AF30+AF31+AF32+AF33+AF34+AF35+AF36+AF37+AF38+AF39+AF40+AF41+AF42+AF43+AF44+AF45+AF46+AF47+AF48+AF49+AF50+AF51+AF52+AF53+AF54+AF55+AF56+AF57+AF58+AF59+AF60+AF61+AF62+AF63+AF64+AF65+AF66+AF67+AF68+AF69+AF70+AF71+AF72+AF73+AF74+AF75+AF76+AF77+AF78+AF79+AF80+AF81+AF82+AF83+AF84+AF85+AF86+AF87+AF88+AF89+AF90+AF91+AF92+AF93+AF94+AF95+AF96+AF97+AF98+AF99+AF100+AF101+AF102+AF103+AF104+AF105+AF106+AF107+AF108+AF109+AF110+AF111+AF112+AF113+AF114+AF115+AF116+AF117+AF118+AF119+AF120+AF121+AF122+AF123+AF124+AF125+AF126+AF127+AF128+AF129+AF130+AF131+AF132+AF133+AF134+AF135+AF136+AF137+AF138+AF139+AF140+AF141+AF142+AF143+AF144+AF145+AF146+AF147+AF148+AF149+AF150+AF151+AF152+AF153+AF154+AF155+AF156+AF157+AF158+AF159+AF160+AF161+AF162+AF163+AF164+AF165+AF166+AF167+AF168+AF169+AF170+AF171+AF172+AF173+AF174+AF175+AF176+AF177+AF178+AF179+AF180+AF181+AF182+AF183+AF184+AF185+AF186+AF187+AF188+AF189+AF190+AF191+AF192+AF193+AF194+AF195+AF196+AF197+AF198+AF199+AF200+AF201+AF202+AF203+AF204+AF205+AF206+AF207+AF208+AF209+AF210+AF211+AF212+AF213+AF214+AF215+AF216+AF217+AF218+AF219+AF220+AF221+AF222+AF223+AF224+AF225+AF226+AF227+AF228+AF229+AF230+AF231+AF232+AF233+AF234+AF235+AF236+AF237+AF238+AF239+AF240+AF241+AF242+AF243+AF244+AF245+AF246+AF247+AF248+AF249+AF250+AF251+AF252+AF253+AF254+AF255+AF256+AF257+AF258+AF259+AF260+AF261+AF262+AF263+AF264+AF265+AF266+AF267+AF268+AF269+AF270+AF271+AF272+AF273+AF274+AF275+AF276+AF277+AF278+AF279+AF280+AF281+AF282+AF283+AF284+AF285+AF286+AF287+AF288+AF289+AF290+AF291+AF292+AF293+AF294+AF295+AF296+AF297+AF298+AF299+AF300+AF301+AF302+AF303+AF304+AF305+AF306+AF307+AF308+AF309+AF310+AF311+AF312+AF313+AF314+AF315+AF316+AF317+AF318+AF319+AF320+AF321+AF322+AF323+AF324+AF325+AF326+AF327+AF328+AF329+AF330+AF331+AF332+AF333+AF334+AF335+AF336+AF337+AF338+AF339+AF340+AF341+AF342+AF343+AF344+AF345+AF346+AF347+AF348+AF349+AF350+AF351+AF352+AF353+AF354+AF355+AF356+AF357+AF358+AF359+AF360+AF361+AF362+AF363+AF364+AF365+AF366+AF367+AF368+AF369+AF370+AF371+AF372+AF373+AF374+AF375+AF376+AF377+AF378+AF379+AF380+AF381+AF382+AF383+AF384+AF385+AF386+AF387+AF388+AF389+AF390+AF391+AF392+AF393+AF394+AF395+AF396+AF397+AF398+AF399+AF400+AF401+AF402+AF403+AF404+AF405+AF406+AF407+AF408+AF409+AF410+AF411+AF412+AF413+AF414+AF415+AF416+AF417+AF418+AF419+AF420+AF421+AF422+AF423+AF424+AF425+AF426+AF427+AF428+AF429+AF430+AF431+AF432+AF433+AF434+AF435+AF436+AF437+AF438+AF439+AF440+AF441+AF442+AF443+AF444+AF445+AF446+AF447+AF448+AF449+AF450+AF451+AF452+AF453+AF454+AF455+AF456+AF457+AF458+AF459+AF460+AF461+AF462+AF463+AF464+AF465+AF466+AF467+AF468+AF469+AF470+AF471+AF472+AF473+AF474+AF475+AF476+AF477+AF478+AF479+AF480+AF481+AF482+AF483+AF484+AF485+AF486+AF487+AF488+AF489+AF490+AF491+AF492+AF493+AF494+AF495+AF496+AF497+AF498+AF499+AF500+AF501+AF502+AF503+AF504+AF505+AF506+AF507+AF508+AF509+AF510+AF511+AF512+AF513+AF514+AF515+AF516+AF517+AF518+AF519+AF520+AF521+AF522+AF523+AF524+AF525+AF526+AF527+AF528+AF529+AF530+AF531+AF532+AF533+AF534+AF535+AF536+AF537+AF538+AF539+AF540+AF541+AF542+AF543+AF544+AF545+AF546+AF547+AF548+AF549+AF550+AF551+AF552+AF553+AF554+AF555+AF556+AF557+AF558+AF559+AF560+AF561+AF562+AF563 -> 0 | AN9: =AG9+AG10+AG11+AG12+AG13+AG14+AG15+AG16+AG17+AG18+AG19+AG20+AG21+AG22+AG23+AG24+AG25+AG26+AG27+AG28+AG29+AG30+AG31+AG32+AG33+AG34+AG35+AG36+AG37+AG38+AG39+AG40+AG41+AG42+AG43+AG44+AG45+AG46+AG47+AG48+AG49+AG50+AG51+AG52+AG53+AG54+AG55+AG56+AG57+AG58+AG59+AG60+AG61+AG62+AG63+AG64+AG65+AG66+AG67+AG68+AG69+AG70+AG71+AG72+AG73+AG74+AG75+AG76+AG77+AG78+AG79+AG80+AG81+AG82+AG83+AG84+AG85+AG86+AG87+AG88+AG89+AG90+AG91+AG92+AG93+AG94+AG95+AG96+AG97+AG98+AG99+AG100+AG101+AG102+AG103+AG104+AG105+AG106+AG107+AG108+AG109+AG110+AG111+AG112+AG113+AG114+AG115+AG116+AG117+AG118+AG119+AG120+AG121+AG122+AG123+AG124+AG125+AG126+AG127+AG128+AG129+AG130+AG131+AG132+AG133+AG134+AG135+AG136+AG137+AG138+AG139+AG140+AG141+AG142+AG143+AG144+AG145+AG146+AG147+AG148+AG149+AG150+AG151+AG152+AG153+AG154+AG155+AG156+AG157+AG158+AG159+AG160+AG161+AG162+AG163+AG164+AG165+AG166+AG167+AG168+AG169+AG170+AG171+AG172+AG173+AG174+AG175+AG176+AG177+AG178+AG179+AG180+AG181+AG182+AG183+AG184+AG185+AG186+AG187+AG188+AG189+AG190+AG191+AG192+AG193+AG194+AG195+AG196+AG197+AG198+AG199+AG200+AG201+AG202+AG203+AG204+AG205+AG206+AG207+AG208+AG209+AG210+AG211+AG212+AG213+AG214+AG215+AG216+AG217+AG218+AG219+AG220+AG221+AG222+AG223+AG224+AG225+AG226+AG227+AG228+AG229+AG230+AG231+AG232+AG233+AG234+AG235+AG236+AG237+AG238+AG239+AG240+AG241+AG242+AG243+AG244+AG245+AG246+AG247+AG248+AG249+AG250+AG251+AG252+AG253+AG254+AG255+AG256+AG257+AG258+AG259+AG260+AG261+AG262+AG263+AG264+AG265+AG266+AG267+AG268+AG269+AG270+AG271+AG272+AG273+AG274+AG275+AG276+AG277+AG278+AG279+AG280+AG281+AG282+AG283+AG284+AG285+AG286+AG287+AG288+AG289+AG290+AG291+AG292+AG293+AG294+AG295+AG296+AG297+AG298+AG299+AG300+AG301+AG302+AG303+AG304+AG305+AG306+AG307+AG308+AG309+AG310+AG311+AG312+AG313+AG314+AG315+AG316+AG317+AG318+AG319+AG320+AG321+AG322+AG323+AG324+AG325+AG326+AG327+AG328+AG329+AG330+AG331+AG332+AG333+AG334+AG335+AG336+AG337+AG338+AG339+AG340+AG341+AG342+AG343+AG344+AG345+AG346+AG347+AG348+AG349+AG350+AG351+AG352+AG353+AG354+AG355+AG356+AG357+AG358+AG359+AG360+AG361+AG362+AG363+AG364+AG365+AG366+AG367+AG368+AG369+AG370+AG371+AG372+AG373+AG374+AG375+AG376+AG377+AG378+AG379+AG380+AG381+AG382+AG383+AG384+AG385+AG386+AG387+AG388+AG389+AG390+AG391+AG392+AG393+AG394+AG395+AG396+AG397+AG398+AG399+AG400+AG401+AG402+AG403+AG404+AG405+AG406+AG407+AG408+AG409+AG410+AG411+AG412+AG413+AG414+AG415+AG416+AG417+AG418+AG419+AG420+AG421+AG422+AG423+AG424+AG425+AG426+AG427+AG428+AG429+AG430+AG431+AG432+AG433+AG434+AG435+AG436+AG437+AG438+AG439+AG440+AG441+AG442+AG443+AG444+AG445+AG446+AG447+AG448+AG449+AG450+AG451+AG452+AG453+AG454+AG455+AG456+AG457+AG458+AG459+AG460+AG461+AG462+AG463+AG464+AG465+AG466+AG467+AG468+AG469+AG470+AG471+AG472+AG473+AG474+AG475+AG476+AG477+AG478+AG479+AG480+AG481+AG482+AG483+AG484+AG485+AG486+AG487+AG488+AG489+AG490+AG491+AG492+AG493+AG494+AG495+AG496+AG497+AG498+AG499+AG500+AG501+AG502+AG503+AG504+AG505+AG506+AG507+AG508+AG509+AG510+AG511+AG512+AG513+AG514+AG515+AG516+AG517+AG518+AG519+AG520+AG521+AG522+AG523+AG524+AG525+AG526+AG527+AG528+AG529+AG530+AG531+AG532+AG533+AG534+AG535+AG536+AG537+AG538+AG539+AG540+AG541+AG542+AG543+AG544+AG545+AG546+AG547+AG548+AG549+AG550+AG551+AG552+AG553+AG554+AG555+AG556+AG557+AG558+AG559+AG560+AG561+AG562+AG563 -> 0 | AO9: 1 | AP9: =U9*B9 -> 0 | AQ9: =U9*C9 -> 0 | AR9: =AQ9-AP9 -> 0 | AS9: =X9*B9 -> 3900
A10: 2 | B10: 1900 | C10: 3000 | D10: 1100 | E10: Lonas Medianas | F10: 3 | U10: =H10+J10+L10+N10+P10+R10+T10 -> 0 | X10: =F10+G10+I10+K10+M10+O10+Q10+S10-H10-J10-L10-N10-P10-R10-T10-V10-W10 -> 3 | Y10: =G10+I10+K10+M10+O10+Q10+S10 -> 0 | Z10: =Y10*B10 -> 0 | AA10: =H10*C10 -> 0 | AB10: =J10*C10 -> 0 | AC10: =L10*C10 -> 0 | AD10: =N10*C10 -> 0 | AE10: =P10*C10 -> 0 | AF10: =R10*C10 -> 0 | AG10: =T10*C10 -> 0 | AO10: 2 | AP10: =U10*B10 -> 0 | AQ10: =U10*C10 -> 0 | AR10: =AQ10-AP10 -> 0 | AS10: =X10*B10 -> 5700
A11: 3 | B11: 2100 | C11: 3500 | D11: 1400 | E11: Lonas Grandes | F11: 2 | U11: =H11+J11+L11+N11+P11+R11+T11 -> 0 | X11: =F11+G11+I11+K11+M11+O11+Q11+S11-H11-J11-L11-N11-P11-R11-T11-V11-W11 -> 2 | Y11: =G11+I11+K11+M11+O11+Q11+S11 -> 0 | Z11: =Y11*B11 -> 0 | AA11: =H11*C11 -> 0 | AB11: =J11*C11 -> 0 | AC11: =L11*C11 -> 0 | AD11: =N11*C11 -> 0 | AE11: =P11*C11 -> 0 | AF11: =R11*C11 -> 0 | AG11: =T11*C11 -> 0 | AO11: 3 | AP11: =U11*B11 -> 0 | AQ11: =U11*C11 -> 0 | AR11: =AQ11-AP11 -> 0 | AS11: =X11*B11 -> 4200
A12: 4 | U12: =H12+J12+L12+N12+P12+R12+T12 -> 0 | X12: =F12+G12+I12+K12+M12+O12+Q12+S12-H12-J12-L12-N12-P12-R12-T12-V12-W12 -> 0 | Y12: =G12+I12+K12+M12+O12+Q12+S12 -> 0 | Z12: =Y12*B12 -> 0 | AA12: =H12*C12 -> 0 | AB12: =J12*C12 -> 0 | AC12: =L12*C12 -> 0 | AD12: =N12*C12 -> 0 | AE12: =P12*C12 -> 0 | AF12: =R12*C12 -> 0 | AG12: =T12*C12 -> 0 | AH12: Total de la semana | AI12: =AH9+AI9+AJ9+AK9+AL9+AM9+AN9 -> 0 | AO12: 4 | AP12: =U12*B12 -> 0 | AQ12: =U12*C12 -> 0 | AR12: =AQ12-AP12 -> 0 | AS12: =X12*B12 -> 0
A13: 5 | U13: =H13+J13+L13+N13+P13+R13+T13 -> 0 | X13: =F13+G13+I13+K13+M13+O13+Q13+S13-H13-J13-L13-N13-P13-R13-T13-V13-W13 -> 0 | Y13: =G13+I13+K13+M13+O13+Q13+S13 -> 0 | Z13: =Y13*B13 -> 0 | AA13: =H13*C13 -> 0 | AB13: =J13*C13 -> 0 | AC13: =L13*C13 -> 0 | AD13: =N13*C13 -> 0 | AE13: =P13*C13 -> 0 | AF13: =R13*C13 -> 0 | AG13: =T13*C13 -> 0 | AO13: 5 | AP13: =U13*B13 -> 0 | AQ13: =U13*C13 -> 0 | AR13: =AQ13-AP13 -> 0 | AS13: =X13*B13 -> 0
A14: 6 | U14: =H14+J14+L14+N14+P14+R14+T14 -> 0 | X14: =F14+G14+I14+K14+M14+O14+Q14+S14-H14-J14-L14-N14-P14-R14-T14-V14-W14 -> 0 | Y14: =G14+I14+K14+M14+O14+Q14+S14 -> 0 | Z14: =Y14*B14 -> 0 | AA14: =H14*C14 -> 0 | AB14: =J14*C14 -> 0 | AC14: =L14*C14 -> 0 | AD14: =N14*C14 -> 0 | AE14: =P14*C14 -> 0 | AF14: =R14*C14 -> 0 | AG14: =T14*C14 -> 0 | AO14: 6 | AP14: =U14*B14 -> 0 | AQ14: =U14*C14 -> 0 | AR14: =AQ14-AP14 -> 0 | AS14: =X14*B14 -> 0
A15: 7 | U15: =H15+J15+L15+N15+P15+R15+T15 -> 0 | X15: =F15+G15+I15+K15+M15+O15+Q15+S15-H15-J15-L15-N15-P15-R15-T15-V15-W15 -> 0 | Y15: =G15+I15+K15+M15+O15+Q15+S15 -> 0 | Z15: =Y15*B15 -> 0 | AA15: =H15*C15 -> 0 | AB15: =J15*C15 -> 0 | AC15: =L15*C15 -> 0 | AD15: =N15*C15 -> 0 | AE15: =P15*C15 -> 0 | AF15: =R15*C15 -> 0 | AG15: =T15*C15 -> 0 | AO15: 7 | AP15: =U15*B15 -> 0 | AQ15: =U15*C15 -> 0 | AR15: =AQ15-AP15 -> 0 | AS15: =X15*B15 -> 0
A16: 8 | B16: 200 | C16: 300 | D16: =C16-B16 -> 100 | E16: Plato Chico | F16: 6 | U16: =H16+J16+L16+N16+P16+R16+T16 -> 0 | X16: =F16+G16+I16+K16+M16+O16+Q16+S16-H16-J16-L16-N16-P16-R16-T16-V16-W16 -> 6 | Y16: =G16+I16+K16+M16+O16+Q16+S16 -> 0 | Z16: =Y16*B16 -> 0 | AA16: =H16*C16 -> 0 | AB16: =J16*C16 -> 0 | AC16: =L16*C16 -> 0 | AD16: =N16*C16 -> 0 | AE16: =P16*C16 -> 0 | AF16: =R16*C16 -> 0 | AG16: =T16*C16 -> 0 | AO16: 9 | AP16: =U16*B16 -> 0 | AQ16: =U16*C16 -> 0 | AR16: =AQ16-AP16 -> 0 | AS16: =X16*B16 -> 1200
A17: 9 | B17: 300 | C17: 400 | D17: =C17-B17 -> 100 | E17: Plato Mediano | F17: 0 | U17: =H17+J17+L17+N17+P17+R17+T17 -> 0 | X17: =F17+G17+I17+K17+M17+O17+Q17+S17-H17-J17-L17-N17-P17-R17-T17-V17-W17 -> 0 | Y17: =G17+I17+K17+M17+O17+Q17+S17 -> 0 | Z17: =Y17*B17 -> 0 | AA17: =H17*C17 -> 0 | AB17: =J17*C17 -> 0 | AC17: =L17*C17 -> 0 | AD17: =N17*C17 -> 0 | AE17: =P17*C17 -> 0 | AF17: =R17*C17 -> 0 | AG17: =T17*C17 -> 0 | AO17: 10 | AP17: =U17*B17 -> 0 | AQ17: =U17*C17 -> 0 | AR17: =AQ17-AP17 -> 0 | AS17: =X17*B17 -> 0
A18: 10 | B18: 400 | C18: 600 | D18: =C18-B18 -> 200 | E18: Platos Grandes | F18: 0 | U18: =H18+J18+L18+N18+P18+R18+T18 -> 0 | X18: =F18+G18+I18+K18+M18+O18+Q18+S18-H18-J18-L18-N18-P18-R18-T18-V18-W18 -> 0 | Y18: =G18+I18+K18+M18+O18+Q18+S18 -> 0 | Z18: =Y18*B18 -> 0 | AA18: =H18*C18 -> 0 | AB18: =J18*C18 -> 0 | AC18: =L18*C18 -> 0 | AD18: =N18*C18 -> 0 | AE18: =P18*C18 -> 0 | AF18: =R18*C18 -> 0 | AG18: =T18*C18 -> 0 | AO18: 11 | AP18: =U18*B18 -> 0 | AQ18: =U18*C18 -> 0 | AR18: =AQ18-AP18 -> 0 | AS18: =X18*B18 -> 0
A19: 11 | U19: =H19+J19+L19+N19+P19+R19+T19 -> 0 | X19: =F19+G19+I19+K19+M19+O19+Q19+S19-H19-J19-L19-N19-P19-R19-T19-V19-W19 -> 0 | Y19: =G19+I19+K19+M19+O19+Q19+S19 -> 0 | Z19: =Y19*B19 -> 0 | AA19: =H19*C19 -> 0 | AB19: =J19*C19 -> 0 | AC19: =L19*C19 -> 0 | AD19: =N19*C19 -> 0 | AE19: =P19*C19 -> 0 | AF19: =R19*C19 -> 0 | AG19: =T19*C19 -> 0 | AO19: 12 | AP19: =U19*B19 -> 0 | AQ19: =U19*C19 -> 0 | AR19: =AQ19-AP19 -> 0 | AS19: =X19*B19 -> 0
A20: 12 | U20: =H20+J20+L20+N20+P20+R20+T20 -> 0 | X20: =F20+G20+I20+K20+M20+O20+Q20+S20-H20-J20-L20-N20-P20-R20-T20-V20-W20 -> 0 | Y20: =G20+I20+K20+M20+O20+Q20+S20 -> 0 | Z20: =Y20*B20 -> 0 | AA20: =H20*C20 -> 0 | AB20: =J20*C20 -> 0 | AC20: =L20*C20 -> 0 | AD20: =N20*C20 -> 0 | AE20: =P20*C20 -> 0 | AF20: =R20*C20 -> 0 | AG20: =T20*C20 -> 0 | AO20: 13 | AP20: =U20*B20 -> 0 | AQ20: =U20*C20 -> 0 | AR20: =AQ20-AP20 -> 0 | AS20: =X20*B20 -> 0
A21: 13 | U21: =H21+J21+L21+N21+P21+R21+T21 -> 0 | X21: =F21+G21+I21+K21+M21+O21+Q21+S21-H21-J21-L21-N21-P21-R21-T21-V21-W21 -> 0 | Y21: =G21+I21+K21+M21+O21+Q21+S21 -> 0 | Z21: =Y21*B21 -> 0 | AA21: =H21*C21 -> 0 | AB21: =J21*C21 -> 0 | AC21: =L21*C21 -> 0 | AD21: =N21*C21 -> 0 | AE21: =P21*C21 -> 0 | AF21: =R21*C21 -> 0 | AG21: =T21*C21 -> 0 | AO21: 14 | AP21: =U21*B21 -> 0 | AQ21: =U21*C21 -> 0 | AR21: =AQ21-AP21 -> 0 | AS21: =X21*B21 -> 0
A22: 14 | U22: =H22+J22+L22+N22+P22+R22+T22 -> 0 | X22: =F22+G22+I22+K22+M22+O22+Q22+S22-H22-J22-L22-N22-P22-R22-T22-V22-W22 -> 0 | Y22: =G22+I22+K22+M22+O22+Q22+S22 -> 0 | Z22: =Y22*B22 -> 0 | AA22: =H22*C22 -> 0 | AB22: =J22*C22 -> 0 | AC22: =L22*C22 -> 0 | AD22: =N22*C22 -> 0 | AE22: =P22*C22 -> 0 | AF22: =R22*C22 -> 0 | AG22: =T22*C22 -> 0 | AO22: 15 | AP22: =U22*B22 -> 0 | AQ22: =U22*C22 -> 0 | AR22: =AQ22-AP22 -> 0 | AS22: =X22*B22 -> 0
A23: 15 | U23: =H23+J23+L23+N23+P23+R23+T23 -> 0 | X23: =F23+G23+I23+K23+M23+O23+Q23+S23-H23-J23-L23-N23-P23-R23-T23-V23-W23 -> 0 | Y23: =G23+I23+K23+M23+O23+Q23+S23 -> 0 | Z23: =Y23*B23 -> 0 | AA23: =H23*C23 -> 0 | AB23: =J23*C23 -> 0 | AC23: =L23*C23 -> 0 | AD23: =N23*C23 -> 0 | AE23: =P23*C23 -> 0 | AF23: =R23*C23 -> 0 | AG23: =T23*C23 -> 0 | AO23: 16 | AP23: =U23*B23 -> 0 | AQ23: =U23*C23 -> 0 | AR23: =AQ23-AP23 -> 0 | AS23: =X23*B23 -> 0
A24: 16 | U24: =H24+J24+L24+N24+P24+R24+T24 -> 0 | X24: =F24+G24+I24+K24+M24+O24+Q24+S24-H24-J24-L24-N24-P24-R24-T24-V24-W24 -> 0 | Y24: =G24+I24+K24+M24+O24+Q24+S24 -> 0 | Z24: =Y24*B24 -> 0 | AA24: =H24*C24 -> 0 | AB24: =J24*C24 -> 0 | AC24: =L24*C24 -> 0 | AD24: =N24*C24 -> 0 | AE24: =P24*C24 -> 0 | AF24: =R24*C24 -> 0 | AG24: =T24*C24 -> 0 | AO24: 17 | AP24: =U24*B24 -> 0 | AQ24: =U24*C24 -> 0 | AR24: =AQ24-AP24 -> 0 | AS24: =X24*B24 -> 0
A25: 17 | U25: =H25+J25+L25+N25+P25+R25+T25 -> 0 | X25: =F25+G25+I25+K25+M25+O25+Q25+S25-H25-J25-L25-N25-P25-R25-T25-V25-W25 -> 0 | Y25: =G25+I25+K25+M25+O25+Q25+S25 -> 0 | Z25: =Y25*B25 -> 0 | AA25: =H25*C25 -> 0 | AB25: =J25*C25 -> 0 | AC25: =L25*C25 -> 0 | AD25: =N25*C25 -> 0 | AE25: =P25*C25 -> 0 | AF25: =R25*C25 -> 0 | AG25: =T25*C25 -> 0 | AO25: 18 | AP25: =U25*B25 -> 0 | AQ25: =U25*C25 -> 0 | AR25: =AQ25-AP25 -> 0 | AS25: =X25*B25 -> 0
A26: 18 | U26: =H26+J26+L26+N26+P26+R26+T26 -> 0 | X26: =F26+G26+I26+K26+M26+O26+Q26+S26-H26-J26-L26-N26-P26-R26-T26-V26-W26 -> 0 | Y26: =G26+I26+K26+M26+O26+Q26+S26 -> 0 | Z26: =Y26*B26 -> 0 | AA26: =H26*C26 -> 0 | AB26: =J26*C26 -> 0 | AC26: =L26*C26 -> 0 | AD26: =N26*C26 -> 0 | AE26: =P26*C26 -> 0 | AF26: =R26*C26 -> 0 | AG26: =T26*C26 -> 0 | AO26: 19 | AP26: =U26*B26 -> 0 | AQ26: =U26*C26 -> 0 | AR26: =AQ26-AP26 -> 0 | AS26: =X26*B26 -> 0
A27: 19 | U27: =H27+J27+L27+N27+P27+R27+T27 -> 0 | X27: =F27+G27+I27+K27+M27+O27+Q27+S27-H27-J27-L27-N27-P27-R27-T27-V27-W27 -> 0 | Y27: =G27+I27+K27+M27+O27+Q27+S27 -> 0 | Z27: =Y27*B27 -> 0 | AA27: =H27*C27 -> 0 | AB27: =J27*C27 -> 0 | AC27: =L27*C27 -> 0 | AD27: =N27*C27 -> 0 | AE27: =P27*C27 -> 0 | AF27: =R27*C27 -> 0 | AG27: =T27*C27 -> 0 | AO27: 20 | AP27: =U27*B27 -> 0 | AQ27: =U27*C27 -> 0 | AR27: =AQ27-AP27 -> 0 | AS27: =X27*B27 -> 0
A28: 20 | U28: =H28+J28+L28+N28+P28+R28+T28 -> 0 | X28: =F28+G28+I28+K28+M28+O28+Q28+S28-H28-J28-L28-N28-P28-R28-T28-V28-W28 -> 0 | Y28: =G28+I28+K28+M28+O28+Q28+S28 -> 0 | Z28: =Y28*B28 -> 0 | AA28: =H28*C28 -> 0 | AB28: =J28*C28 -> 0 | AC28: =L28*C28 -> 0 | AD28: =N28*C28 -> 0 | AE28: =P28*C28 -> 0 | AF28: =R28*C28 -> 0 | AG28: =T28*C28 -> 0 | AO28: 21 | AP28: =U28*B28 -> 0 | AQ28: =U28*C28 -> 0 | AR28: =AQ28-AP28 -> 0 | AS28: =X28*B28 -> 0
A29: 21 | U29: =H29+J29+L29+N29+P29+R29+T29 -> 0 | X29: =F29+G29+I29+K29+M29+O29+Q29+S29-H29-J29-L29-N29-P29-R29-T29-V29-W29 -> 0 | Y29: =G29+I29+K29+M29+O29+Q29+S29 -> 0 | Z29: =Y29*B29 -> 0 | AA29: =H29*C29 -> 0 | AB29: =J29*C29 -> 0 | AC29: =L29*C29 -> 0 | AD29: =N29*C29 -> 0 | AE29: =P29*C29 -> 0 | AF29: =R29*C29 -> 0 | AG29: =T29*C29 -> 0 | AO29: 22 | AP29: =U29*B29 -> 0 | AQ29: =U29*C29 -> 0 | AR29: =AQ29-AP29 -> 0 | AS29: =X29*B29 -> 0
A30: 22 | U30: =H30+J30+L30+N30+P30+R30+T30 -> 0 | X30: =F30+G30+I30+K30+M30+O30+Q30+S30-H30-J30-L30-N30-P30-R30-T30-V30-W30 -> 0 | Y30: =G30+I30+K30+M30+O30+Q30+S30 -> 0 | Z30: =Y30*B30 -> 0 | AA30: =H30*C30 -> 0 | AB30: =J30*C30 -> 0 | AC30: =L30*C30 -> 0 | AD30: =N30*C30 -> 0 | AE30: =P30*C30 -> 0 | AF30: =R30*C30 -> 0 | AG30: =T30*C30 -> 0 | AO30: 23 | AP30: =U30*B30 -> 0 | AQ30: =U30*C30 -> 0 | AR30: =AQ30-AP30 -> 0 | AS30: =X30*B30 -> 0
... A45: 37 | U45: =H45+J45+L45+N45+P45+R45+T45 -> 0 | X45: =F45+G45+I45+K45+M45+O45+Q45+S45-H45-J45-L45-N45-P45-R45-T45-V45-W45 -> 0 | Y45: =G45+I45+K45+M45+O45+Q45+S45 -> 0 | Z45: =Y45*B45 -> 0 | AA45: =H45*C45 -> 0 | AB45: =J45*C45 -> 0 | AC45: =L45*C45 -> 0 | AD45: =N45*C45 -> 0 | AE45: =P45*C45 -> 0 | AF45: =R45*C45 -> 0 | AG45: =T45*C45 -> 0 | AO45: 38 | AP45: =U45*B45 -> 0 | AQ45: =U45*C45 -> 0 | AR45: =AQ45-AP45 -> 0 | AS45: =X45*B45 -> 0
A46: 38 | U46: =H46+J46+L46+N46+P46+R46+T46 -> 0 | X46: =F46+G46+I46+K46+M46+O46+Q46+S46-H46-J46-L46-N46-P46-R46-T46-V46-W46 -> 0 | Y46: =G46+I46+K46+M46+O46+Q46+S46 -> 0 | Z46: =Y46*B46 -> 0 | AA46: =H46*C46 -> 0 | AB46: =J46*C46 -> 0 | AC46: =L46*C46 -> 0 | AD46: =N46*C46 -> 0 | AE46: =P46*C46 -> 0 | AF46: =R46*C46 -> 0 | AG46: =T46*C46 -> 0 | AO46: 39 | AP46: =U46*B46 -> 0 | AQ46: =U46*C46 -> 0 | AS46: =X46*B46 -> 0
A47: 39 | U47: =H47+J47+L47+N47+P47+R47+T47 -> 0 | X47: =F47+G47+I47+K47+M47+O47+Q47+S47-H47-J47-L47-N47-P47-R47-T47-V47-W47 -> 0 | Y47: =G47+I47+K47+M47+O47+Q47+S47 -> 0 | Z47: =Y47*B47 -> 0 | AA47: =H47*C47 -> 0 | AB47: =J47*C47 -> 0 | AC47: =L47*C47 -> 0 | AD47: =N47*C47 -> 0 | AE47: =P47*C47 -> 0 | AF47: =R47*C47 -> 0 | AG47: =T47*C47 -> 0 | AO47: 40 | AP47: =U47*B47 -> 0 | AQ47: =U47*C47 -> 0 | AR47: =AQ47-AP47 -> 0 | AS47: =X47*B47 -> 0
A48: 40 | U48: =H48+J48+L48+N48+P48+R48+T48 -> 0 | X48: =F48+G48+I48+K48+M48+O48+Q48+S48-H48-J48-L48-N48-P48-R48-T48-V48-W48 -> 0 | Y48: =G48+I48+K48+M48+O48+Q48+S48 -> 0 | Z48: =Y48*B48 -> 0 | AA48: =H48*C48 -> 0 | AB48: =J48*C48 -> 0 | AC48: =L48*C48 -> 0 | AD48: =N48*C48 -> 0 | AE48: =P48*C48 -> 0 | AF48: =R48*C48 -> 0 | AG48: =T48*C48 -> 0 | AO48: 41 | AP48: =U48*B48 -> 0 | AQ48: =U48*C48 -> 0 | AR48: =AQ48-AP48 -> 0 | AS48: =X48*B48 -> 0
A49: 41 | U49: =H49+J49+L49+N49+P49+R49+T49 -> 0 | X49: =F49+G49+I49+K49+M49+O49+Q49+S49-H49-J49-L49-N49-P49-R49-T49-V49-W49 -> 0 | Y49: =G49+I49+K49+M49+O49+Q49+S49 -> 0 | Z49: =Y49*B49 -> 0 | AA49: =H49*C49 -> 0 | AB49: =J49*C49 -> 0 | AC49: =L49*C49 -> 0 | AD49: =N49*C49 -> 0 | AE49: =P49*C49 -> 0 | AF49: =R49*C49 -> 0 | AG49: =T49*C49 -> 0 | AO49: 42 | AP49: =U49*B49 -> 0 | AQ49: =U49*C49 -> 0 | AR49: =AQ49-AP49 -> 0 | AS49: =X49*B49 -> 0
A50: 42 | U50: =H50+J50+L50+N50+P50+R50+T50 -> 0 | X50: =F50+G50+I50+K50+M50+O50+Q50+S50-H50-J50-L50-N50-P50-R50-T50-V50-W50 -> 0 | Y50: =G50+I50+K50+M50+O50+Q50+S50 -> 0 | Z50: =Y50*B50 -> 0 | AA50: =H50*C50 -> 0 | AB50: =J50*C50 -> 0 | AC50: =L50*C50 -> 0 | AD50: =N50*C50 -> 0 | AE50: =P50*C50 -> 0 | AF50: =R50*C50 -> 0 | AG50: =T50*C50 -> 0 | AO50: 43 | AP50: =U50*B50 -> 0 | AQ50: =U50*C50 -> 0 | AR50: =AQ50-AP50 -> 0 | AS50: =X50*B50 -> 0
A51: 43 | U51: =H51+J51+L51+N51+P51+R51+T51 -> 0 | X51: =F51+G51+I51+K51+M51+O51+Q51+S51-H51-J51-L51-N51-P51-R51-T51-V51-W51 -> 0 | Y51: =G51+I51+K51+M51+O51+Q51+S51 -> 0 | Z51: =Y51*B51 -> 0 | AA51: =H51*C51 -> 0 | AB51: =J51*C51 -> 0 | AC51: =L51*C51 -> 0 | AD51: =N51*C51 -> 0 | AE51: =P51*C51 -> 0 | AF51: =R51*C51 -> 0 | AG51: =T51*C51 -> 0 | AO51: 44 | AP51: =U51*B51 -> 0 | AQ51: =U51*C51 -> 0 | AR51: =AQ51-AP51 -> 0 | AS51: =X51*B51 -> 0
A52: 44 | U52: =H52+J52+L52+N52+P52+R52+T52 -> 0 | X52: =F52+G52+I52+K52+M52+O52+Q52+S52-H52-J52-L52-N52-P52-R52-T52-V52-W52 -> 0 | Y52: =G52+I52+K52+M52+O52+Q52+S52 -> 0 | Z52: =Y52*B52 -> 0 | AA52: =H52*C52 -> 0 | AB52: =J52*C52 -> 0 | AC52: =L52*C52 -> 0 | AD52: =N52*C52 -> 0 | AE52: =P52*C52 -> 0 | AF52: =R52*C52 -> 0 | AG52: =T52*C52 -> 0 | AO52: 45 | AP52: =U52*B52 -> 0 | AQ52: =U52*C52 -> 0 | AR52: =AQ52-AP52 -> 0 | AS52: =X52*B52 -> 0
A53: 45 | U53: =H53+J53+L53+N53+P53+R53+T53 -> 0 | X53: =F53+G53+I53+K53+M53+O53+Q53+S53-H53-J53-L53-N53-P53-R53-T53-V53-W53 -> 0 | Y53: =G53+I53+K53+M53+O53+Q53+S53 -> 0 | Z53: =Y53*B53 -> 0 | AA53: =H53*C53 -> 0 | AB53: =J53*C53 -> 0 | AC53: =L53*C53 -> 0 | AD53: =N53*C53 -> 0 | AE53: =P53*C53 -> 0 | AF53: =R53*C53 -> 0 | AG53: =T53*C53 -> 0 | AO53: 46 | AP53: =U53*B53 -> 0 | AQ53: =U53*C53 -> 0 | AR53: =AQ53-AP53 -> 0 | AS53: =X53*B53 -> 0
A54: 46 | U54: =H54+J54+L54+N54+P54+R54+T54 -> 0 | X54: =F54+G54+I54+K54+M54+O54+Q54+S54-H54-J54-L54-N54-P54-R54-T54-V54-W54 -> 0 | Y54: =G54+I54+K54+M54+O54+Q54+S54 -> 0 | Z54: =Y54*B54 -> 0 | AA54: =H54*C54 -> 0 | AB54: =J54*C54 -> 0 | AC54: =L54*C54 -> 0 | AD54: =N54*C54 -> 0 | AE54: =P54*C54 -> 0 | AF54: =R54*C54 -> 0 | AG54: =T54*C54 -> 0 | AO54: 47 | AP54: =U54*B54 -> 0 | AQ54: =U54*C54 -> 0 | AR54: =AQ54-AP54 -> 0 | AS54: =X54*B54 -> 0
A55: 47 | U55: =H55+J55+L55+N55+P55+R55+T55 -> 0 | X55: =F55+G55+I55+K55+M55+O55+Q55+S55-H55-J55-L55-N55-P55-R55-T55-V55-W55 -> 0 | Y55: =G55+I55+K55+M55+O55+Q55+S55 -> 0 | Z55: =Y55*B55 -> 0 | AA55: =H55*C55 -> 0 | AB55: =J55*C55 -> 0 | AC55: =L55*C55 -> 0 | AD55: =N55*C55 -> 0 | AE55: =P55*C55 -> 0 | AF55: =R55*C55 -> 0 | AG55: =T55*C55 -> 0 | AO55: 48 | AP55: =U55*B55 -> 0 | AQ55: =U55*C55 -> 0 | AR55: =AQ55-AP55 -> 0 | AS55: =X55*B55 -> 0
A56: 48 | U56: =H56+J56+L56+N56+P56+R56+T56 -> 0 | X56: =F56+G56+I56+K56+M56+O56+Q56+S56-H56-J56-L56-N56-P56-R56-T56-V56-W56 -> 0 | Y56: =G56+I56+K56+M56+O56+Q56+S56 -> 0 | Z56: =Y56*B56 -> 0 | AA56: =H56*C56 -> 0 | AB56: =J56*C56 -> 0 | AC56: =L56*C56 -> 0 | AD56: =N56*C56 -> 0 | AE56: =P56*C56 -> 0 | AF56: =R56*C56 -> 0 | AG56: =T56*C56 -> 0 | AO56: 49 | AP56: =U56*B56 -> 0 | AQ56: =U56*C56 -> 0 | AR56: =AQ56-AP56 -> 0 | AS56: =X56*B56 -> 0
A57: 49 | U57: =H57+J57+L57+N57+P57+R57+T57 -> 0 | X57: =F57+G57+I57+K57+M57+O57+Q57+S57-H57-J57-L57-N57-P57-R57-T57-V57-W57 -> 0 | Y57: =G57+I57+K57+M57+O57+Q57+S57 -> 0 | Z57: =Y57*B57 -> 0 | AA57: =H57*C57 -> 0 | AB57: =J57*C57 -> 0 | AC57: =L57*C57 -> 0 | AD57: =N57*C57 -> 0 | AE57: =P57*C57 -> 0 | AF57: =R57*C57 -> 0 | AG57: =T57*C57 -> 0 | AO57: 50 | AP57: =U57*B57 -> 0 | AQ57: =U57*C57 -> 0 | AR57: =AQ57-AP57 -> 0 | AS57: =X57*B57 -> 0
A58: 50 | U58: =H58+J58+L58+N58+P58+R58+T58 -> 0 | X58: =F58+G58+I58+K58+M58+O58+Q58+S58-H58-J58-L58-N58-P58-R58-T58-V58-W58 -> 0 | Y58: =G58+I58+K58+M58+O58+Q58+S58 -> 0 | Z58: =Y58*B58 -> 0 | AA58: =H58*C58 -> 0 | AB58: =J58*C58 -> 0 | AC58: =L58*C58 -> 0 | AD58: =N58*C58 -> 0 | AE58: =P58*C58 -> 0 | AF58: =R58*C58 -> 0 | AG58: =T58*C58 -> 0 | AO58: 51 | AP58: =U58*B58 -> 0 | AQ58: =U58*C58 -> 0 | AR58: =AQ58-AP58 -> 0 | AS58: =X58*B58 -> 0
... A85: 77 | U85: =H85+J85+L85+N85+P85+R85+T85 -> 0 | X85: =F85+G85+I85+K85+M85+O85+Q85+S85-H85-J85-L85-N85-P85-R85-T85-V85-W85 -> 0 | Y85: =G85+I85+K85+M85+O85+Q85+S85 -> 0 | Z85: =Y85*B85 -> 0 | AA85: =H85*C85 -> 0 | AB85: =J85*C85 -> 0 | AC85: =L85*C85 -> 0 | AD85: =N85*C85 -> 0 | AE85: =P85*C85 -> 0 | AF85: =R85*C85 -> 0 | AG85: =T85*C85 -> 0 | AO85: 78 | AP85: =U85*B85 -> 0 | AQ85: =U85*C85 -> 0 | AR85: =AQ85-AP85 -> 0 | AS85: =X85*B85 -> 0
A86: 78 | D86: =C86-B86 -> 0 | U86: =H86+J86+L86+N86+P86+R86+T86 -> 0 | X86: =F86+G86+I86+K86+M86+O86+Q86+S86-H86-J86-L86-N86-P86-R86-T86-V86-W86 -> 0 | Y86: =G86+I86+K86+M86+O86+Q86+S86 -> 0 | Z86: =Y86*B86 -> 0 | AA86: =H86*C86 -> 0 | AB86: =J86*C86 -> 0 | AC86: =L86*C86 -> 0 | AD86: =N86*C86 -> 0 | AE86: =P86*C86 -> 0 | AF86: =R86*C86 -> 0 | AG86: =T86*C86 -> 0 | AO86: 79 | AP86: =U86*B86 -> 0 | AQ86: =U86*C86 -> 0 | AR86: =AQ86-AP86 -> 0 | AS86: =X86*B86 -> 0
A87: 79 | D87: =C87-B87 -> 0 | U87: =H87+J87+L87+N87+P87+R87+T87 -> 0 | X87: =F87+G87+I87+K87+M87+O87+Q87+S87-H87-J87-L87-N87-P87-R87-T87-V87-W87 -> 0 | Y87: =G87+I87+K87+M87+O87+Q87+S87 -> 0 | Z87: =Y87*B87 -> 0 | AA87: =H87*C87 -> 0 | AB87: =J87*C87 -> 0 | AC87: =L87*C87 -> 0 | AD87: =N87*C87 -> 0 | AE87: =P87*C87 -> 0 | AF87: =R87*C87 -> 0 | AG87: =T87*C87 -> 0 | AO87: 80 | AP87: =U87*B87 -> 0 | AQ87: =U87*C87 -> 0 | AR87: =AQ87-AP87 -> 0 | AS87: =X87*B87 -> 0
A88: 80 | D88: =C88-B88 -> 0 | U88: =H88+J88+L88+N88+P88+R88+T88 -> 0 | X88: =F88+G88+I88+K88+M88+O88+Q88+S88-H88-J88-L88-N88-P88-R88-T88-V88-W88 -> 0 | Y88: =G88+I88+K88+M88+O88+Q88+S88 -> 0 | Z88: =Y88*B88 -> 0 | AA88: =H88*C88 -> 0 | AB88: =J88*C88 -> 0 | AC88: =L88*C88 -> 0 | AD88: =N88*C88 -> 0 | AE88: =P88*C88 -> 0 | AF88: =R88*C88 -> 0 | AG88: =T88*C88 -> 0 | AO88: 81 | AP88: =U88*B88 -> 0 | AQ88: =U88*C88 -> 0 | AR88: =AQ88-AP88 -> 0 | AS88: =X88*B88 -> 0
A89: 81 | U89: =H89+J89+L89+N89+P89+R89+T89 -> 0 | X89: =F89+G89+I89+K89+M89+O89+Q89+S89-H89-J89-L89-N89-P89-R89-T89-V89-W89 -> 0 | Y89: =G89+I89+K89+M89+O89+Q89+S89 -> 0 | Z89: =Y89*B89 -> 0 | AA89: =H89*C89 -> 0 | AB89: =J89*C89 -> 0 | AC89: =L89*C89 -> 0 | AD89: =N89*C89 -> 0 | AE89: =P89*C89 -> 0 | AF89: =R89*C89 -> 0 | AG89: =T89*C89 -> 0 | AO89: 82 | AP89: =U89*B89 -> 0 | AQ89: =U89*C89 -> 0 | AR89: =AQ89-AP89 -> 0 | AS89: =X89*B89 -> 0
A90: 82 | U90: =H90+J90+L90+N90+P90+R90+T90 -> 0 | X90: =F90+G90+I90+K90+M90+O90+Q90+S90-H90-J90-L90-N90-P90-R90-T90-V90-W90 -> 0 | Y90: =G90+I90+K90+M90+O90+Q90+S90 -> 0 | Z90: =Y90*B90 -> 0 | AA90: =H90*C90 -> 0 | AB90: =J90*C90 -> 0 | AC90: =L90*C90 -> 0 | AD90: =N90*C90 -> 0 | AE90: =P90*C90 -> 0 | AF90: =R90*C90 -> 0 | AG90: =T90*C90 -> 0 | AO90: 83 | AP90: =U90*B90 -> 0 | AQ90: =U90*C90 -> 0 | AR90: =AQ90-AP90 -> 0 | AS90: =X90*B90 -> 0
A91: 83 | U91: =H91+J91+L91+N91+P91+R91+T91 -> 0 | X91: =F91+G91+I91+K91+M91+O91+Q91+S91-H91-J91-L91-N91-P91-R91-T91-V91-W91 -> 0 | Y91: =G91+I91+K91+M91+O91+Q91+S91 -> 0 | Z91: =Y91*B91 -> 0 | AA91: =H91*C91 -> 0 | AB91: =J91*C91 -> 0 | AC91: =L91*C91 -> 0 | AD91: =N91*C91 -> 0 | AE91: =P91*C91 -> 0 | AF91: =R91*C91 -> 0 | AG91: =T91*C91 -> 0 | AO91: 84 | AP91: =U91*B91 -> 0 | AQ91: =U91*C91 -> 0 | AR91: =AQ91-AP91 -> 0 | AS91: =X91*B91 -> 0
A92: 84 | U92: =H92+J92+L92+N92+P92+R92+T92 -> 0 | X92: =F92+G92+I92+K92+M92+O92+Q92+S92-H92-J92-L92-N92-P92-R92-T92-V92-W92 -> 0 | Y92: =G92+I92+K92+M92+O92+Q92+S92 -> 0 | Z92: =Y92*B92 -> 0 | AA92: =H92*C92 -> 0 | AB92: =J92*C92 -> 0 | AC92: =L92*C92 -> 0 | AD92: =N92*C92 -> 0 | AE92: =P92*C92 -> 0 | AF92: =R92*C92 -> 0 | AG92: =T92*C92 -> 0 | AO92: 85 | AP92: =U92*B92 -> 0 | AQ92: =U92*C92 -> 0 | AR92: =AQ92-AP92 -> 0 | AS92: =X92*B92 -> 0
A93: 85 | U93: =H93+J93+L93+N93+P93+R93+T93 -> 0 | X93: =F93+G93+I93+K93+M93+O93+Q93+S93-H93-J93-L93-N93-P93-R93-T93-V93-W93 -> 0 | Y93: =G93+I93+K93+M93+O93+Q93+S93 -> 0 | Z93: =Y93*B93 -> 0 | AA93: =H93*C93 -> 0 | AB93: =J93*C93 -> 0 | AC93: =L93*C93 -> 0 | AD93: =N93*C93 -> 0 | AE93: =P93*C93 -> 0 | AF93: =R93*C93 -> 0 | AG93: =T93*C93 -> 0 | AO93: 86 | AP93: =U93*B93 -> 0 | AQ93: =U93*C93 -> 0 | AR93: =AQ93-AP93 -> 0 | AS93: =X93*B93 -> 0
A94: 86 | U94: =H94+J94+L94+N94+P94+R94+T94 -> 0 | X94: =F94+G94+I94+K94+M94+O94+Q94+S94-H94-J94-L94-N94-P94-R94-T94-V94-W94 -> 0 | Y94: =G94+I94+K94+M94+O94+Q94+S94 -> 0 | Z94: =Y94*B94 -> 0 | AA94: =H94*C94 -> 0 | AB94: =J94*C94 -> 0 | AC94: =L94*C94 -> 0 | AD94: =N94*C94 -> 0 | AE94: =P94*C94 -> 0 | AF94: =R94*C94 -> 0 | AG94: =T94*C94 -> 0 | AQ94: =U94*C94 -> 0
A95: 87 | U95: =H95+J95+L95+N95+P95+R95+T95 -> 0 | X95: =F95+G95+I95+K95+M95+O95+Q95+S95-H95-J95-L95-N95-P95-R95-T95-V95-W95 -> 0 | Y95: =G95+I95+K95+M95+O95+Q95+S95 -> 0 | Z95: =Y95*B95 -> 0 | AA95: =H95*C95 -> 0 | AB95: =J95*C95 -> 0 | AC95: =L95*C95 -> 0 | AD95: =N95*C95 -> 0 | AE95: =P95*C95 -> 0 | AF95: =R95*C95 -> 0 | AG95: =T95*C95 -> 0 | AQ95: =U95*C95 -> 0
A96: 88 | U96: =H96+J96+L96+N96+P96+R96+T96 -> 0 | X96: =F96+G96+I96+K96+M96+O96+Q96+S96-H96-J96-L96-N96-P96-R96-T96-V96-W96 -> 0 | Y96: =G96+I96+K96+M96+O96+Q96+S96 -> 0 | Z96: =Y96*B96 -> 0 | AA96: =H96*C96 -> 0 | AB96: =J96*C96 -> 0 | AC96: =L96*C96 -> 0 | AD96: =N96*C96 -> 0 | AE96: =P96*C96 -> 0 | AF96: =R96*C96 -> 0 | AG96: =T96*C96 -> 0 | AQ96: =U96*C96 -> 0
A97: 89 | U97: =H97+J97+L97+N97+P97+R97+T97 -> 0 | X97: =F97+G97+I97+K97+M97+O97+Q97+S97-H97-J97-L97-N97-P97-R97-T97-V97-W97 -> 0 | Y97: =G97+I97+K97+M97+O97+Q97+S97 -> 0 | Z97: =Y97*B97 -> 0 | AA97: =H97*C97 -> 0 | AB97: =J97*C97 -> 0 | AC97: =L97*C97 -> 0 | AD97: =N97*C97 -> 0 | AE97: =P97*C97 -> 0 | AF97: =R97*C97 -> 0 | AG97: =T97*C97 -> 0 | AQ97: =U97*C97 -> 0
A98: 90 | U98: =H98+J98+L98+N98+P98+R98+T98 -> 0 | X98: =F98+G98+I98+K98+M98+O98+Q98+S98-H98-J98-L98-N98-P98-R98-T98-V98-W98 -> 0 | Y98: =G98+I98+K98+M98+O98+Q98+S98 -> 0 | Z98: =Y98*B98 -> 0 | AA98: =H98*C98 -> 0 | AB98: =J98*C98 -> 0 | AC98: =L98*C98 -> 0 | AD98: =N98*C98 -> 0 | AE98: =P98*C98 -> 0 | AF98: =R98*C98 -> 0 | AG98: =T98*C98 -> 0 | AQ98: =U98*C98 -> 0
A99: 91 | U99: =H99+J99+L99+N99+P99+R99+T99 -> 0 | X99: =F99+G99+I99+K99+M99+O99+Q99+S99-H99-J99-L99-N99-P99-R99-T99-V99-W99 -> 0 | Y99: =G99+I99+K99+M99+O99+Q99+S99 -> 0 | Z99: =Y99*B99 -> 0 | AA99: =H99*C99 -> 0 | AB99: =J99*C99 -> 0 | AC99: =L99*C99 -> 0 | AD99: =N99*C99 -> 0 | AE99: =P99*C99 -> 0 | AF99: =R99*C99 -> 0 | AG99: =T99*C99 -> 0 | AQ99: =U99*C99 -> 0
A100: 92 | U100: =H100+J100+L100+N100+P100+R100+T100 -> 0 | X100: =F100+G100+I100+K100+M100+O100+Q100+S100-H100-J100-L100-N100-P100-R100-T100-V100-W100 -> 0 | Y100: =G100+I100+K100+M100+O100+Q100+S100 -> 0 | Z100: =Y100*B100 -> 0 | AA100: =H100*C100 -> 0 | AB100: =J100*C100 -> 0 | AC100: =L100*C100 -> 0 | AD100: =N100*C100 -> 0 | AE100: =P100*C100 -> 0 | AF100: =R100*C100 -> 0 | AG100: =T100*C100 -> 0 | AQ100: =U100*C100 -> 0
A101: 93 | U101: =H101+J101+L101+N101+P101+R101+T101 -> 0 | X101: =F101+G101+I101+K101+M101+O101+Q101+S101-H101-J101-L101-N101-P101-R101-T101-V101-W101 -> 0 | Y101: =G101+I101+K101+M101+O101+Q101+S101 -> 0 | Z101: =Y101*B101 -> 0 | AA101: =H101*C101 -> 0 | AB101: =J101*C101 -> 0 | AC101: =L101*C101 -> 0 | AD101: =N101*C101 -> 0 | AE101: =P101*C101 -> 0 | AF101: =R101*C101 -> 0 | AG101: =T101*C101 -> 0 | AQ101: =U101*C101 -> 0
A102: 94 | U102: =H102+J102+L102+N102+P102+R102+T102 -> 0 | X102: =F102+G102+I102+K102+M102+O102+Q102+S102-H102-J102-L102-N102-P102-R102-T102-V102-W102 -> 0 | Y102: =G102+I102+K102+M102+O102+Q102+S102 -> 0 | Z102: =Y102*B102 -> 0 | AA102: =H102*C102 -> 0 | AB102: =J102*C102 -> 0 | AC102: =L102*C102 -> 0 | AD102: =N102*C102 -> 0 | AE102: =P102*C102 -> 0 | AF102: =R102*C102 -> 0 | AG102: =T102*C102 -> 0 | AQ102: =U102*C102 -> 0
A103: 95 | U103: =H103+J103+L103+N103+P103+R103+T103 -> 0 | X103: =F103+G103+I103+K103+M103+O103+Q103+S103-H103-J103-L103-N103-P103-R103-T103-V103-W103 -> 0 | Y103: =G103+I103+K103+M103+O103+Q103+S103 -> 0 | Z103: =Y103*B103 -> 0 | AA103: =H103*C103 -> 0 | AB103: =J103*C103 -> 0 | AC103: =L103*C103 -> 0 | AD103: =N103*C103 -> 0 | AE103: =P103*C103 -> 0 | AF103: =R103*C103 -> 0 | AG103: =T103*C103 -> 0 | AQ103: =U103*C103 -> 0
A104: 96 | U104: =H104+J104+L104+N104+P104+R104+T104 -> 0 | X104: =F104+G104+I104+K104+M104+O104+Q104+S104-H104-J104-L104-N104-P104-R104-T104-V104-W104 -> 0 | Y104: =G104+I104+K104+M104+O104+Q104+S104 -> 0 | Z104: =Y104*B104 -> 0 | AA104: =H104*C104 -> 0 | AB104: =J104*C104 -> 0 | AC104: =L104*C104 -> 0 | AD104: =N104*C104 -> 0 | AE104: =P104*C104 -> 0 | AF104: =R104*C104 -> 0 | AG104: =T104*C104 -> 0 | AQ104: =U104*C104 -> 0
A105: 97 | U105: =H105+J105+L105+N105+P105+R105+T105 -> 0 | X105: =F105+G105+I105+K105+M105+O105+Q105+S105-H105-J105-L105-N105-P105-R105-T105-V105-W105 -> 0 | Y105: =G105+I105+K105+M105+O105+Q105+S105 -> 0 | Z105: =Y105*B105 -> 0 | AA105: =H105*C105 -> 0 | AB105: =J105*C105 -> 0 | AC105: =L105*C105 -> 0 | AD105: =N105*C105 -> 0 | AE105: =P105*C105 -> 0 | AF105: =R105*C105 -> 0 | AG105: =T105*C105 -> 0 | AQ105: =U105*C105 -> 0
... A141: 133 | U141: =H141+J141+L141+N141+P141+R141+T141 -> 0 | X141: =F141+G141+I141+K141+M141+O141+Q141+S141-H141-J141-L141-N141-P141-R141-T141-V141-W141 -> 0 | Y141: =G141+I141+K141+M141+O141+Q141+S141 -> 0 | Z141: =Y141*B141 -> 0 | AA141: =H141*C141 -> 0 | AB141: =J141*C141 -> 0 | AC141: =L141*C141 -> 0 | AD141: =N141*C141 -> 0 | AE141: =P141*C141 -> 0 | AF141: =R141*C141 -> 0 | AG141: =T141*C141 -> 0 | AQ141: =U141*C141 -> 0
A142: 134 | U142: =H142+J142+L142+N142+P142+R142+T142 -> 0 | X142: =F142+G142+I142+K142+M142+O142+Q142+S142-H142-J142-L142-N142-P142-R142-T142-W142 -> 0 | Y142: =G142+I142+K142+M142+O142+Q142+S142 -> 0 | Z142: =Y142*B142 -> 0 | AA142: =H142*C142 -> 0 | AB142: =J142*C142 -> 0 | AC142: =L142*C142 -> 0 | AD142: =N142*C142 -> 0 | AE142: =P142*C142 -> 0 | AF142: =R142*C142 -> 0 | AG142: =T142*C142 -> 0 | AQ142: =U142*C142 -> 0
A143: 135 | U143: =H143+J143+L143+N143+P143+R143+T143 -> 0 | X143: =F143+G143+I143+K143+M143+O143+Q143+S143-H143-J143-L143-N143-P143-R143-T143-W143 -> 0 | Y143: =G143+I143+K143+M143+O143+Q143+S143 -> 0 | Z143: =Y143*B143 -> 0 | AA143: =H143*C143 -> 0 | AB143: =J143*C143 -> 0 | AC143: =L143*C143 -> 0 | AD143: =N143*C143 -> 0 | AE143: =P143*C143 -> 0 | AF143: =R143*C143 -> 0 | AG143: =T143*C143 -> 0 | AQ143: =U143*C143 -> 0
A144: 136 | U144: =H144+J144+L144+N144+P144+R144+T144 -> 0 | X144: =F144+G144+I144+K144+M144+O144+Q144+S144-H144-J144-L144-N144-P144-R144-T144-W144 -> 0 | Y144: =G144+I144+K144+M144+O144+Q144+S144 -> 0 | Z144: =Y144*B144 -> 0 | AA144: =H144*C144 -> 0 | AB144: =J144*C144 -> 0 | AC144: =L144*C144 -> 0 | AD144: =N144*C144 -> 0 | AE144: =P144*C144 -> 0 | AF144: =R144*C144 -> 0 | AG144: =T144*C144 -> 0 | AQ144: =U144*C144 -> 0
A145: 137 | U145: =H145+J145+L145+N145+P145+R145+T145 -> 0 | X145: =F145+G145+I145+K145+M145+O145+Q145+S145-H145-J145-L145-N145-P145-R145-T145-W145 -> 0 | Y145: =G145+I145+K145+M145+O145+Q145+S145 -> 0 | Z145: =Y145*B145 -> 0 | AA145: =H145*C145 -> 0 | AB145: =J145*C145 -> 0 | AC145: =L145*C145 -> 0 | AD145: =N145*C145 -> 0 | AE145: =P145*C145 -> 0 | AF145: =R145*C145 -> 0 | AG145: =T145*C145 -> 0 | AQ145: =U145*C145 -> 0
A146: 138 | U146: =H146+J146+L146+N146+P146+R146+T146 -> 0 | X146: =F146+G146+I146+K146+M146+O146+Q146+S146-H146-J146-L146-N146-P146-R146-T146-W146 -> 0 | Y146: =G146+I146+K146+M146+O146+Q146+S146 -> 0 | Z146: =Y146*B146 -> 0 | AA146: =H146*C146 -> 0 | AB146: =J146*C146 -> 0 | AC146: =L146*C146 -> 0 | AD146: =N146*C146 -> 0 | AE146: =P146*C146 -> 0 | AF146: =R146*C146 -> 0 | AG146: =T146*C146 -> 0 | AQ146: =U146*C146 -> 0
A147: 139 | U147: =H147+J147+L147+N147+P147+R147+T147 -> 0 | X147: =F147+G147+I147+K147+M147+O147+Q147+S147-H147-J147-L147-N147-P147-R147-T147-W147 -> 0 | Y147: =G147+I147+K147+M147+O147+Q147+S147 -> 0 | Z147: =Y147*B147 -> 0 | AA147: =H147*C147 -> 0 | AB147: =J147*C147 -> 0 | AC147: =L147*C147 -> 0 | AD147: =N147*C147 -> 0 | AE147: =P147*C147 -> 0 | AF147: =R147*C147 -> 0 | AG147: =T147*C147 -> 0 | AQ147: =U147*C147 -> 0
A148: 140 | U148: =H148+J148+L148+N148+P148+R148+T148 -> 0 | X148: =F148+G148+I148+K148+M148+O148+Q148+S148-H148-J148-L148-N148-P148-R148-T148-W148 -> 0 | Y148: =G148+I148+K148+M148+O148+Q148+S148 -> 0 | Z148: =Y148*B148 -> 0 | AA148: =H148*C148 -> 0 | AB148: =J148*C148 -> 0 | AC148: =L148*C148 -> 0 | AD148: =N148*C148 -> 0 | AE148: =P148*C148 -> 0 | AF148: =R148*C148 -> 0 | AG148: =T148*C148 -> 0 | AQ148: =U148*C148 -> 0
A149: 141 | U149: =H149+J149+L149+N149+P149+R149+T149 -> 0 | X149: =F149+G149+I149+K149+M149+O149+Q149+S149-H149-J149-L149-N149-P149-R149-T149-W149 -> 0 | Y149: =G149+I149+K149+M149+O149+Q149+S149 -> 0 | Z149: =Y149*B149 -> 0 | AA149: =H149*C149 -> 0 | AB149: =J149*C149 -> 0 | AC149: =L149*C149 -> 0 | AD149: =N149*C149 -> 0 | AE149: =P149*C149 -> 0 | AF149: =R149*C149 -> 0 | AG149: =T149*C149 -> 0 | AQ149: =U149*C149 -> 0
A150: 142 | U150: =H150+J150+L150+N150+P150+R150+T150 -> 0 | X150: =F150+G150+I150+K150+M150+O150+Q150+S150-H150-J150-L150-N150-P150-R150-T150-W150 -> 0 | Y150: =G150+I150+K150+M150+O150+Q150+S150 -> 0 | AA150: =H150*C150 -> 0 | AB150: =J150*C150 -> 0 | AC150: =L150*C150 -> 0 | AD150: =N150*C150 -> 0 | AE150: =P150*C150 -> 0 | AF150: =R150*C150 -> 0 | AG150: =T150*C150 -> 0 | AQ150: =U150*C150 -> 0
A151: 143 | U151: =H151+J151+L151+N151+P151+R151+T151 -> 0 | X151: =F151+G151+I151+K151+M151+O151+Q151+S151-H151-J151-L151-N151-P151-R151-T151-W151 -> 0 | Y151: =G151+I151+K151+M151+O151+Q151+S151 -> 0 | AA151: =H151*C151 -> 0 | AB151: =J151*C151 -> 0 | AC151: =L151*C151 -> 0 | AD151: =N151*C151 -> 0 | AE151: =P151*C151 -> 0 | AF151: =R151*C151 -> 0 | AG151: =T151*C151 -> 0 | AQ151: =U151*C151 -> 0
A152: 144 | U152: =H152+J152+L152+N152+P152+R152+T152 -> 0 | X152: =F152+G152+I152+K152+M152+O152+Q152+S152-H152-J152-L152-N152-P152-R152-T152-W152 -> 0 | Y152: =G152+I152+K152+M152+O152+Q152+S152 -> 0 | AA152: =H152*C152 -> 0 | AB152: =J152*C152 -> 0 | AC152: =L152*C152 -> 0 | AD152: =N152*C152 -> 0 | AE152: =P152*C152 -> 0 | AF152: =R152*C152 -> 0 | AG152: =T152*C152 -> 0 | AQ152: =U152*C152 -> 0
A153: 145 | U153: =H153+J153+L153+N153+P153+R153+T153 -> 0 | X153: =F153+G153+I153+K153+M153+O153+Q153+S153-H153-J153-L153-N153-P153-R153-T153-W153 -> 0 | Y153: =G153+I153+K153+M153+O153+Q153+S153 -> 0 | AA153: =H153*C153 -> 0 | AB153: =J153*C153 -> 0 | AC153: =L153*C153 -> 0 | AD153: =N153*C153 -> 0 | AE153: =P153*C153 -> 0 | AF153: =R153*C153 -> 0 | AG153: =T153*C153 -> 0 | AQ153: =U153*C153 -> 0
A154: 146 | U154: =H154+J154+L154+N154+P154+R154+T154 -> 0 | X154: =F154+G154+I154+K154+M154+O154+Q154+S154-H154-J154-L154-N154-P154-R154-T154-W154 -> 0 | Y154: =G154+I154+K154+M154+O154+Q154+S154 -> 0 | AA154: =H154*C154 -> 0 | AB154: =J154*C154 -> 0 | AC154: =L154*C154 -> 0 | AD154: =N154*C154 -> 0 | AE154: =P154*C154 -> 0 | AF154: =R154*C154 -> 0 | AG154: =T154*C154 -> 0 | AQ154: =U154*C154 -> 0
A155: 147 | U155: =H155+J155+L155+N155+P155+R155+T155 -> 0 | X155: =F155+G155+I155+K155+M155+O155+Q155+S155-H155-J155-L155-N155-P155-R155-T155-W155 -> 0 | Y155: =G155+I155+K155+M155+O155+Q155+S155 -> 0 | AA155: =H155*C155 -> 0 | AB155: =J155*C155 -> 0 | AC155: =L155*C155 -> 0 | AD155: =N155*C155 -> 0 | AE155: =P155*C155 -> 0 | AF155: =R155*C155 -> 0 | AG155: =T155*C155 -> 0 | AQ155: =U155*C155 -> 0
A156: 148 | U156: =H156+J156+L156+N156+P156+R156+T156 -> 0 | X156: =F156+G156+I156+K156+M156+O156+Q156+S156-H156-J156-L156-N156-P156-R156-T156-W156 -> 0 | Y156: =G156+I156+K156+M156+O156+Q156+S156 -> 0 | AA156: =H156*C156 -> 0 | AB156: =J156*C156 -> 0 | AC156: =L156*C156 -> 0 | AD156: =N156*C156 -> 0 | AE156: =P156*C156 -> 0 | AF156: =R156*C156 -> 0 | AG156: =T156*C156 -> 0 | AQ156: =U156*C156 -> 0
A157: 149 | U157: =H157+J157+L157+N157+P157+R157+T157 -> 0 | X157: =F157+G157+I157+K157+M157+O157+Q157+S157-H157-J157-L157-N157-P157-R157-T157-W157 -> 0 | Y157: =G157+I157+K157+M157+O157+Q157+S157 -> 0 | AA157: =H157*C157 -> 0 | AB157: =J157*C157 -> 0 | AC157: =L157*C157 -> 0 | AD157: =N157*C157 -> 0 | AE157: =P157*C157 -> 0 | AF157: =R157*C157 -> 0 | AG157: =T157*C157 -> 0 | AQ157: =U157*C157 -> 0
A158: 150 | U158: =H158+J158+L158+N158+P158+R158+T158 -> 0 | X158: =F158+G158+I158+K158+M158+O158+Q158+S158-H158-J158-L158-N158-P158-R158-T158-W158 -> 0 | Y158: =G158+I158+K158+M158+O158+Q158+S158 -> 0 | AA158: =H158*C158 -> 0 | AB158: =J158*C158 -> 0 | AC158: =L158*C158 -> 0 | AD158: =N158*C158 -> 0 | AE158: =P158*C158 -> 0 | AF158: =R158*C158 -> 0 | AG158: =T158*C158 -> 0 | AQ158: =U158*C158 -> 0
A159: 151 | U159: =H159+J159+L159+N159+P159+R159+T159 -> 0 | X159: =F159+G159+I159+K159+M159+O159+Q159+S159-H159-J159-L159-N159-P159-R159-T159-W159 -> 0 | Y159: =G159+I159+K159+M159+O159+Q159+S159 -> 0 | AA159: =H159*C159 -> 0 | AB159: =J159*C159 -> 0 | AC159: =L159*C159 -> 0 | AD159: =N159*C159 -> 0 | AE159: =P159*C159 -> 0 | AF159: =R159*C159 -> 0 | AG159: =T159*C159 -> 0 | AQ159: =U159*C159 -> 0
A160: 152 | U160: =H160+J160+L160+N160+P160+R160+T160 -> 0 | X160: =F160+G160+I160+K160+M160+O160+Q160+S160-H160-J160-L160-N160-P160-R160-T160-W160 -> 0 | Y160: =G160+I160+K160+M160+O160+Q160+S160 -> 0 | AA160: =H160*C160 -> 0 | AB160: =J160*C160 -> 0 | AC160: =L160*C160 -> 0 | AD160: =N160*C160 -> 0 | AE160: =P160*C160 -> 0 | AF160: =R160*C160 -> 0 | AG160: =T160*C160 -> 0 | AQ160: =U160*C160 -> 0
A161: 153 | U161: =H161+J161+L161+N161+P161+R161+T161 -> 0 | X161: =F161+G161+I161+K161+M161+O161+Q161+S161-H161-J161-L161-N161-P161-R161-T161-W161 -> 0 | Y161: =G161+I161+K161+M161+O161+Q161+S161 -> 0 | AA161: =H161*C161 -> 0 | AB161: =J161*C161 -> 0 | AC161: =L161*C161 -> 0 | AD161: =N161*C161 -> 0 | AE161: =P161*C161 -> 0 | AF161: =R161*C161 -> 0 | AG161: =T161*C161 -> 0 | AQ161: =U161*C161 -> 0
... A198: 187 | U198: =H198+J198+L198+N198+P198+R198+T198 -> 0 | X198: =F198+G198+I198+K198+M198+O198+Q198+S198-H198-J198-L198-N198-P198-R198-T198-W198 -> 0 | Y198: =G198+I198+K198+M198+O198+Q198+S198 -> 0 | AA198: =H198*C198 -> 0 | AB198: =J198*C198 -> 0 | AC198: =L198*C198 -> 0 | AD198: =N198*C198 -> 0 | AE198: =P198*C198 -> 0 | AF198: =R198*C198 -> 0 | AG198: =T198*C198 -> 0 | AQ198: =U198*C198 -> 0
A199: 188 | U199: =H199+J199+L199+N199+P199+R199+T199 -> 0 | X199: =F199+G199+I199+K199+M199+O199+Q199+S199-H199-J199-L199-N199-P199-R199-T199-W199 -> 0 | Y199: =G199+I199+K199+M199+O199+Q199+S199 -> 0 | AA199: =H199*C199 -> 0 | AB199: =J199*C199 -> 0 | AC199: =L199*C199 -> 0 | AD199: =N199*C199 -> 0 | AE199: =P199*C199 -> 0 | AF199: =R199*C199 -> 0 | AG199: =T199*C199 -> 0
A200: 189 | U200: =T200+R200+P200+N200+L200+J200+H200 -> 0 | X200: =F200+G200+I200+K200+M200+O200+Q200+S200-H200-J200-L200-N200-P200-R200-T200-W200 -> 0 | Y200: =G200+I200+K200+M200+O200+Q200+S200 -> 0 | AA200: =H200*C200 -> 0 | AB200: =J200*C200 -> 0 | AC200: =L200*C200 -> 0 | AD200: =N200*C200 -> 0 | AE200: =P200*C200 -> 0 | AF200: =R200*C200 -> 0 | AG200: =T200*C200 -> 0
A201: 190 | U201: =T201+R201+P201+N201+L201+J201+H201 -> 0 | X201: =F201+G201+I201+K201+M201+O201+Q201+S201-H201-J201-L201-N201-P201-R201-T201-W201 -> 0 | Y201: =G201+I201+K201+M201+O201+Q201+S201 -> 0 | AA201: =H201*C201 -> 0 | AB201: =J201*C201 -> 0 | AC201: =L201*C201 -> 0 | AD201: =N201*C201 -> 0 | AE201: =P201*C201 -> 0 | AF201: =R201*C201 -> 0 | AG201: =T201*C201 -> 0
A202: 191 | U202: =T202+R202+P202+N202+L202+J202+H202 -> 0 | X202: =F202+G202+I202+K202+M202+O202+Q202+S202-H202-J202-L202-N202-P202-R202-T202-W202 -> 0 | Y202: =G202+I202+K202+M202+O202+Q202+S202 -> 0 | AA202: =H202*C202 -> 0 | AB202: =J202*C202 -> 0 | AC202: =L202*C202 -> 0 | AD202: =N202*C202 -> 0 | AE202: =P202*C202 -> 0 | AF202: =R202*C202 -> 0 | AG202: =T202*C202 -> 0
A203: 192 | U203: =T203+R203+P203+N203+L203+J203+H203 -> 0 | X203: =F203+G203+I203+K203+M203+O203+Q203+S203-H203-J203-L203-N203-P203-R203-T203-W203 -> 0 | Y203: =G203+I203+K203+M203+O203+Q203+S203 -> 0 | AA203: =H203*C203 -> 0 | AB203: =J203*C203 -> 0 | AC203: =L203*C203 -> 0 | AD203: =N203*C203 -> 0 | AE203: =P203*C203 -> 0 | AF203: =R203*C203 -> 0 | AG203: =T203*C203 -> 0
A204: 193 | U204: =T204+R204+P204+N204+L204+J204+H204 -> 0 | X204: =F204+G204+I204+K204+M204+O204+Q204+S204-H204-J204-L204-N204-P204-R204-T204-W204 -> 0 | Y204: =G204+I204+K204+M204+O204+Q204+S204 -> 0 | AA204: =H204*C204 -> 0 | AB204: =J204*C204 -> 0 | AC204: =L204*C204 -> 0 | AD204: =N204*C204 -> 0 | AE204: =P204*C204 -> 0 | AF204: =R204*C204 -> 0 | AG204: =T204*C204 -> 0
A205: 194 | U205: =T205+R205+P205+N205+L205+J205+H205 -> 0 | X205: =F205+G205+I205+K205+M205+O205+Q205+S205-H205-J205-L205-N205-P205-R205-T205-W205 -> 0 | Y205: =G205+I205+K205+M205+O205+Q205+S205 -> 0 | AA205: =H205*C205 -> 0 | AB205: =J205*C205 -> 0 | AC205: =L205*C205 -> 0 | AD205: =N205*C205 -> 0 | AE205: =P205*C205 -> 0 | AF205: =R205*C205 -> 0 | AG205: =T205*C205 -> 0
A206: 195 | U206: =T206+R206+P206+N206+L206+J206+H206 -> 0 | X206: =F206+G206+I206+K206+M206+O206+Q206+S206-H206-J206-L206-N206-P206-R206-T206-W206 -> 0 | Y206: =G206+I206+K206+M206+O206+Q206+S206 -> 0 | AA206: =H206*C206 -> 0 | AB206: =J206*C206 -> 0 | AC206: =L206*C206 -> 0 | AD206: =N206*C206 -> 0 | AE206: =P206*C206 -> 0 | AF206: =R206*C206 -> 0 | AG206: =T206*C206 -> 0
A207: 196 | U207: =T207+R207+P207+N207+L207+J207+H207 -> 0 | X207: =F207+G207+I207+K207+M207+O207+Q207+S207-H207-J207-L207-N207-P207-R207-T207-W207 -> 0 | Y207: =G207+I207+K207+M207+O207+Q207+S207 -> 0 | AA207: =H207*C207 -> 0 | AB207: =J207*C207 -> 0 | AC207: =L207*C207 -> 0 | AD207: =N207*C207 -> 0 | AE207: =P207*C207 -> 0 | AF207: =R207*C207 -> 0 | AG207: =T207*C207 -> 0
A208: 197 | U208: =T208+R208+P208+N208+L208+J208+H208 -> 0 | X208: =F208+G208+I208+K208+M208+O208+Q208+S208-H208-J208-L208-N208-P208-R208-T208-W208 -> 0 | Y208: =G208+I208+K208+M208+O208+Q208+S208 -> 0 | AA208: =H208*C208 -> 0 | AB208: =J208*C208 -> 0 | AC208: =L208*C208 -> 0 | AD208: =N208*C208 -> 0 | AE208: =P208*C208 -> 0 | AF208: =R208*C208 -> 0 | AG208: =T208*C208 -> 0
A209: 198 | U209: =T209+R209+P209+N209+L209+J209+H209 -> 0 | X209: =F209+G209+I209+K209+M209+O209+Q209+S209-H209-J209-L209-N209-P209-R209-T209-W209 -> 0 | Y209: =G209+I209+K209+M209+O209+Q209+S209 -> 0 | AA209: =H209*C209 -> 0 | AB209: =J209*C209 -> 0 | AC209: =L209*C209 -> 0 | AD209: =N209*C209 -> 0 | AE209: =P209*C209 -> 0 | AF209: =R209*C209 -> 0 | AG209: =T209*C209 -> 0
A210: 199 | U210: =T210+R210+P210+N210+L210+J210+H210 -> 0 | X210: =F210+G210+I210+K210+M210+O210+Q210+S210-H210-J210-L210-N210-P210-R210-T210-W210 -> 0 | Y210: =G210+I210+K210+M210+O210+Q210+S210 -> 0 | AA210: =H210*C210 -> 0 | AB210: =J210*C210 -> 0 | AC210: =L210*C210 -> 0 | AD210: =N210*C210 -> 0 | AE210: =P210*C210 -> 0 | AF210: =R210*C210 -> 0 | AG210: =T210*C210 -> 0
A211: 200 | U211: =T211+R211+P211+N211+L211+J211+H211 -> 0 | X211: =F211+G211+I211+K211+M211+O211+Q211+S211-H211-J211-L211-N211-P211-R211-T211-W211 -> 0 | Y211: =G211+I211+K211+M211+O211+Q211+S211 -> 0 | AA211: =H211*C211 -> 0 | AB211: =J211*C211 -> 0 | AC211: =L211*C211 -> 0 | AD211: =N211*C211 -> 0 | AE211: =P211*C211 -> 0 | AF211: =R211*C211 -> 0 | AG211: =T211*C211 -> 0
A212: 201 | U212: =T212+R212+P212+N212+L212+J212+H212 -> 0 | W212: 1 | X212: =F212+G212+I212+K212+M212+O212+Q212+S212-H212-J212-L212-N212-P212-R212-T212-W212 -> -1 | Y212: =G212+I212+K212+M212+O212+Q212+S212 -> 0 | AA212: =H212*C212 -> 0 | AB212: =J212*C212 -> 0 | AC212: =L212*C212 -> 0 | AD212: =N212*C212 -> 0 | AE212: =P212*C212 -> 0 | AF212: =R212*C212 -> 0 | AG212: =T212*C212 -> 0
A213: 202 | U213: =T213+R213+P213+N213+L213+J213+H213 -> 0 | X213: =F213+G213+I213+K213+M213+O213+Q213+S213-H213-J213-L213-N213-P213-R213-T213-W213 -> 0 | Y213: =G213+I213+K213+M213+O213+Q213+S213 -> 0 | AA213: =H213*C213 -> 0 | AB213: =J213*C213 -> 0 | AC213: =L213*C213 -> 0 | AD213: =N213*C213 -> 0 | AE213: =P213*C213 -> 0 | AF213: =R213*C213 -> 0 | AG213: =T213*C213 -> 0
...

Sheet Ceramica y Reloj
A1: Basar Ojos Color Sol | Y1: Entradas totales de la semana | Z1: Importe de las Entradas Semanal | AO1: Importe en $
AA2: Basar Ojos Color Sol | AH2: Basar Ojos Color Sol
A5: INVENTARIO | F5: ='Lienzos y espejos'!F5:F7 -> 46152 | G5: ='Lienzos y espejos'!G5:T5 -> Semana del 11 al 16 de Mayo | U5: Venta Total | V5: Deuda | W5: Baja sem. | X5: ='Lienzos y espejos'!X5:X7 -> F. 16/5 /26 | AO5: No | AP5: Total al costo | AQ5: Total a la Venta | AR5: Utilidad Total | AS5: $ en Mercancia
G6: ='Lienzos y espejos'!G6:H6 -> D-10 | I6: ='Lienzos y espejos'!I6:J6 -> L-11 | K6: ='Lienzos y espejos'!K6:L6 -> M-12 | M6: ='Lienzos y espejos'!M6:N6 -> Mi-13 | O6: ='Lienzos y espejos'!O6:P6 -> J-14 | Q6: ='Lienzos y espejos'!Q6:R6 -> V-15 | S6: ='Lienzos y espejos'!S6:T6 -> S-16 | AA6: =G5 -> Semana del 11 al 16 de Mayo | AH6: =AA6 -> Semana del 11 al 16 de Mayo
A7: No | B7: Costo | C7: Venta | D7: Gan. | E7: Producto | G7: Entra. | H7: Venta | I7: Entra. | J7: Venta | K7: Entra. | L7: Venta | M7: Entra. | N7: Venta | O7: Entra. | P7: Venta | Q7: Entra. | R7: Venta | S7: Entra. | T7: Venta | AA7: Domingo | AB7: Lunes | AC7: martes | AD7: Miercoles | AE7: Jueves | AF7: Viernes | AG7: Sabado | AH7: Cuadre en efectivo de la Semana
E8: Relojes | Z8: =Z9+Z10+Z11+Z12+Z13+Z14+Z15+Z16+Z17+Z18+Z19+Z20+Z21+Z22+Z23+Z24+Z25+Z26+Z27+Z28+Z29+Z30+Z31+Z32+Z33+Z34+Z35+Z36+Z37+Z38+Z39+Z40+Z41+Z42+Z43+Z44+Z45+Z46+Z47+Z48+Z49+Z50+Z51+Z52+Z53+Z54+Z55+Z56+Z57+Z58+Z59+Z60+Z61+Z62+Z63+Z64+Z65+Z66+Z67+Z68 -> 33880 | AH8: ='Lienzos y espejos'!AH8 -> Domingo | AI8: ='Lienzos y espejos'!AI8 -> Lunes | AJ8: ='Lienzos y espejos'!AJ8 -> Martes | AK8: ='Lienzos y espejos'!AK8 -> Miercoles | AL8: ='Lienzos y espejos'!AL8 -> Jueves | AM8: ='Lienzos y espejos'!AM8 -> Viernes | AN8: ='Lienzos y espejos'!AN8 -> Sabado | AP8: =SUM(AP9:AP59) -> 16190 | AQ8: =AQ9+AQ10+AQ11+AQ12+AQ13+AQ14+AQ15+AQ16+AQ17+AQ18+AQ19+AQ20+AQ21+AQ22+AQ23+AQ24+AQ25+AQ26+AQ27+AQ28+AQ29+AQ30+AQ31+AQ32+AQ33+AQ34+AQ35+AQ36+AQ37+AQ38+AQ39+AQ40+AQ41+AQ42+AQ43+AQ44+AQ45+AQ46+AQ47+AQ48+AQ49+AQ50+AQ51+AQ52+AQ53+AQ54+AQ55+AQ56+AQ57+AQ58+AQ59+AQ60+AQ61+AQ62+AQ63+AQ64+AQ65+AQ66+AQ67+AQ68+AQ69+AQ70+AQ71+AQ72+AQ73+AQ74+AQ75+AQ76+AQ77+AQ78+AQ79+AQ80+AQ81+AQ82+AQ83+AQ84+AQ85+AQ86+AQ87+AQ88+AQ89+AQ90+AQ91+AQ92+AQ93+AQ94+AQ95+AQ96+AQ97+AQ98+AQ99+AQ100+AQ101+AQ102+AQ103+AQ104+AQ105+AQ106+AQ107+AQ108+AQ109+AQ110+AQ111+AQ112+AQ113+AQ114+AQ115+AQ116+AQ117+AQ118+AQ119+AQ120+AQ121+AQ122+AQ123+AQ124+AQ125+AQ126+AQ127+AQ128+AQ129+AQ130+AQ131+AQ132+AQ133+AQ134+AQ135+AQ136+AQ137+AQ138+AQ139+AQ140+AQ141+AQ142+AQ143+AQ144+AQ145+AQ146+AQ147+AQ148+AQ149+AQ150+AQ151+AQ152+AQ153+AQ154+AQ155+AQ156+AQ157+AQ158+AQ159+AQ160+AQ161+AQ162+AQ163+AQ164+AQ165+AQ166+AQ167+AQ168+AQ169+AQ170+AQ171+AQ172+AQ173+AQ174+AQ175+AQ176+AQ177+AQ178+AQ179+AQ180+AQ181+AQ182+AQ183+AQ184+AQ185+AQ186+AQ187+AQ188+AQ189+AQ190+AQ191+AQ192+AQ193+AQ194+AQ195+AQ196+AQ197+AQ198+AQ199+AQ200+AQ201+AQ202+AQ203+AQ204+AQ205+AQ206+AQ207+AQ208+AQ209+AQ210+AQ211+AQ212+AQ213+AQ214+AQ215+AQ216+AQ217+AQ218+AQ219+AQ220+AQ221+AQ222+AQ223+AQ224+AQ225+AQ226+AQ227+AQ228+AQ229+AQ230+AQ231+AQ232+AQ233+AQ234+AQ235+AQ236+AQ237+AQ238+AQ239+AQ240+AQ241+AQ242+AQ243+AQ244+AQ245+AQ246+AQ247+AQ248+AQ249+AQ250+AQ251+AQ252+AQ253+AQ254+AQ255+AQ256+AQ257+AQ258+AQ259+AQ260+AQ261+AQ262+AQ263+AQ264+AQ265+AQ266+AQ267+AQ268+AQ269+AQ270+AQ271+AQ272+AQ273+AQ274+AQ275+AQ276+AQ277+AQ278+AQ279+AQ280+AQ281+AQ282+AQ283+AQ284+AQ285+AQ286+AQ287+AQ288+AQ289+AQ290+AQ291+AQ292+AQ293+AQ294+AQ295+AQ296+AQ297+AQ298+AQ299+AQ300+AQ301+AQ302+AQ303+AQ304+AQ305+AQ306+AQ307+AQ308+AQ309+AQ310+AQ311+AQ312+AQ313+AQ314+AQ315+AQ316+AQ317+AQ318+AQ319+AQ320+AQ321+AQ322+AQ323+AQ324+AQ325+AQ326+AQ327+AQ328+AQ329+AQ330+AQ331+AQ332+AQ333+AQ334+AQ335+AQ336+AQ337+AQ338+AQ339+AQ340+AQ341+AQ342+AQ343+AQ344+AQ345+AQ346+AQ347+AQ348+AQ349+AQ350+AQ351+AQ352+AQ353+AQ354+AQ355+AQ356+AQ357+AQ358+AQ359+AQ360+AQ361+AQ362+AQ363+AQ364+AQ365+AQ366+AQ367+AQ368+AQ369+AQ370+AQ371+AQ372+AQ373+AQ374+AQ375+AQ376+AQ377+AQ378+AQ379+AQ380+AQ381+AQ382+AQ383+AQ384+AQ385+AQ386+AQ387+AQ388+AQ389+AQ390+AQ391+AQ392+AQ393+AQ394+AQ395+AQ396+AQ397+AQ398+AQ399+AQ400+AQ401+AQ402+AQ403+AQ404+AQ405+AQ406+AQ407+AQ408+AQ409+AQ410+AQ411+AQ412+AQ413+AQ414+AQ415+AQ416+AQ417+AQ418+AQ419+AQ420+AQ421+AQ422+AQ423+AQ424+AQ425+AQ426+AQ427+AQ428+AQ429+AQ430+AQ431+AQ432+AQ433+AQ434+AQ435+AQ436+AQ437+AQ438+AQ439+AQ440+AQ441+AQ442+AQ443+AQ444+AQ445+AQ446+AQ447+AQ448+AQ449+AQ450+AQ451+AQ452+AQ453+AQ454+AQ455+AQ456+AQ457+AQ458+AQ459+AQ460+AQ461+AQ462+AQ463+AQ464+AQ465+AQ466+AQ467+AQ468+AQ469+AQ470+AQ471+AQ472+AQ473+AQ474+AQ475+AQ476+AQ477+AQ478+AQ479+AQ480+AQ481+AQ482+AQ483+AQ484+AQ485+AQ486+AQ487+AQ488+AQ489+AQ490+AQ491+AQ492+AQ493+AQ494+AQ495+AQ496+AQ497+AQ498+AQ499+AQ500+AQ501+AQ502+AQ503+AQ504+AQ505+AQ506+AQ507+AQ508+AQ509+AQ510+AQ511+AQ512+AQ513+AQ514+AQ515+AQ516+AQ517+AQ518+AQ519+AQ520+AQ521+AQ522+AQ523+AQ524+AQ525+AQ526+AQ527+AQ528+AQ529+AQ530+AQ531+AQ532+AQ533+AQ534+AQ535+AQ536+AQ537+AQ538+AQ539+AQ540+AQ541+AQ542+AQ543+AQ544+AQ545+AQ546+AQ547+AQ548+AQ549+AQ550+AQ551+AQ552+AQ553 -> 22200 | AR8: =AQ8-AP8 -> 6010 | AS8: =AS9+AS10+AS11+AS12+AS13+AS14+AS15+AS16+AS17+AS18+AS19+AS20+AS21+AS22+AS23+AS24+AS25+AS26+AS27+AS28+AS29+AS30+AS31+AS32+AS33+AS34+AS35+AS36+AS37+AS38+AS39+AS40+AS41+AS42+AS43+AS44+AS45+AS46+AS47+AS48+AS49+AS50+AS51+AS52+AS53+AS54+AS55+AS56+AS57+AS58+AS59+AS60+AS61+AS62+AS63+AS64+AS65+AS66+AS67+AS68+AS69+AS70+AS71+AS72+AS73+AS74+AS75+AS76+AS77+AS78+AS79+AS80+AS81+AS82+AS83+AS84+AS85+AS86+AS87+AS88+AS89+AS90+AS91+AS92+AS93+AS94+AS95+AS96+AS97+AS98+AS99+AS100+AS102+AS103+AS104+AS105+AS106+AS107+AS108+AS109+AS110+AS111+AS112+AS113+AS114+AS115+AS116+AS117+AS118+AS119+AS120+AS121+AS122+AS123+AS124+AS125+AS126+AS127+AS128+AS129+AS131+AS132+AS133+AS134+AS135+AS136+AS137+AS138+AS139+AS140+AS141+AS142+AS143+AS144+AS145+AS146+AS147+AS148+AS149+AS150+AS151+AS152+AS153+AS154+AS155+AS156+AS157+AS158+AS159+AS160+AS161+AS162+AS163+AS164+AS165+AS166+AS167+AS168+AS169+AS170+AS171+AS172+AS173+AS174+AS175+AS176+AS177+AS178+AS179+AS180+AS181+AS182+AS183+AS184+AS185+AS186+AS187+AS188+AS189+AS190+AS191+AS192+AS193+AS194+AS195+AS196+AS197+AS198+AS199+AS200+AS201+AS202+AS204+AS205+AS206+AS207+AS208+AS209+AS210+AS211+AS212+AS213+AS214+AS215+AS217+AS218+AS219+AS220+AS221+AS222+AS223+AS224+AS225+AS226+AS227+AS228+AS229+AS230+AS231+AS232+AS233+AS234+AS235+AS236+AS237+AS238+AS240+AS241+AS242+AS243+AS244+AS245+AS246+AS247+AS248+AS249+AS250+AS251+AS252+AS253+AS254+AS255+AS256+AS257+AS258+AS259+AS260+AS261+AS262+AS263+AS264+AS266+AS267+AS268+AS269+AS270+AS271+AS272+AS273+AS276+AS277+AS278+AS279+AS280+AS281+AS283+AS284+AS285+AS286+AS287+AS288+AS289+AS290+AS291+AS292+AS293+AS294+AS295+AS296+AS297+AS298+AS299+AS300+AS301+AS302+AS303+AS304+AS305+AS306+AS307+AS308+AS309+AS310+AS311+AS312+AS313+AS314+AS315+AS316+AS317+AS318+AS319+AS320+AS321+AS322+AS323+AS324+AS325+AS326+AS327+AS328+AS329+AS330+AS331+AS332+AS333+AS334+AS335+AS336+AS337+AS338+AS339+AS340+AS341+AS342+AS343+AS344+AS345+AS346+AS347+AS348+AS349+AS350+AS351+AS352+AS353+AS354+AS355+AS356+AS357+AS358+AS359+AS360+AS361+AS362+AS363+AS364+AS366+AS367+AS368+AS369+AS370+AS371+AS372+AS373+AS374+AS375+AS376+AS377+AS378+AS379+AS380+AS381+AS382+AS383+AS384+AS385+AS386+AS387+AS388+AS389+AS390+AS391+AS392+AS393+AS394+AS395+AS396+AS397+AS398+AS399+AS400+AS401+AS402+AS403+AS404+AS405+AS406+AS407+AS408+AS409+AS410+AS411+AS412+AS413+AS414+AS415+AS416+AS417+AS419+AS420+AS421+AS422+AS423+AS424+AS425+AS426+AS427+AS428+AS429+AS430+AS431+AS432+AS433+AS434+AS435+AS436+AS437+AS438+AS439+AS440+AS441+AS442+AS443+AS444+AS445+AS446+AS447+AS448+AS449+AS450+AS451+AS452+AS453+AS454+AS455+AS456+AS457+AS458+AS459+AS460+AS461+AS462+AS463+AS464+AS465+AS466+AS467+AS468+AS469+AS470+AS471 -> 86240
A9: 1 | B9: 1600 | C9: 2000 | D9: =C9-B9 -> 400 | E9: Reloj Jesus | F9: 2 | N9: 1 | U9: =T9+R9+P9+N9+L9+J9+H9 -> 1 | X9: =F9+G9+I9+K9+M9+O9+Q9+S9-H9-J9-L9-N9-P9-R9-T9-V9-W9 -> 1 | Y9: =G9+I9+K9+M9+O9+Q9+S9 -> 0 | Z9: =Y9*B9 -> 0 | AA9: =H9*C9 -> 0 | AB9: =J9*C9 -> 0 | AC9: =L9*C9 -> 0 | AD9: =N9*C9 -> 2000 | AE9: =P9*C9 -> 0 | AF9: =R9*C9 -> 0 | AG9: =T9*C9 -> 0 | AH9: =AA9+AA10+AA11+AA12+AA13+AA14+AA15+AA16+AA17+AA18+AA19+AA20+AA21+AA22+AA23+AA24+AA25+AA26+AA27+AA28+AA29+AA30+AA31+AA32+AA33+AA34+AA35+AA36+AA37+AA38+AA39+AA40+AA41+AA42+AA43+AA44+AA45+AA46+AA47+AA48+AA49+AA50+AA51+AA52+AA53+AA54+AA55+AA56+AA57+AA58+AA59+AA60+AA61+AA62+AA63+AA64+AA65+AA66+AA67+AA68+AA69+AA70+AA71+AA72+AA73+AA74+AA75+AA76+AA77+AA78+AA79+AA80+AA81+AA82+AA83+AA84+AA85+AA86+AA87+AA88+AA89+AA90+AA91+AA92+AA93+AA94+AA95+AA96+AA97+AA98+AA99+AA100+AA101+AA102+AA103+AA104+AA105+AA106+AA107+AA108+AA109+AA110+AA111+AA112+AA113+AA114+AA115+AA116+AA117+AA118+AA119+AA120+AA121+AA122+AA123+AA124+AA125+AA126+AA127+AA128+AA129+AA130+AA131+AA132+AA133+AA134+AA135+AA136+AA137+AA138+AA139+AA140+AA141+AA142+AA143+AA144+AA145+AA146+AA147+AA148+AA149+AA150+AA151+AA152+AA153+AA154+AA155+AA156+AA157+AA158+AA159+AA160+AA161+AA162+AA163+AA164+AA165+AA166+AA167+AA168+AA169+AA170+AA171+AA172+AA173+AA174+AA175+AA176+AA177+AA178+AA179+AA180+AA181+AA182+AA183+AA184+AA185+AA186+AA187+AA188+AA189+AA190+AA191+AA192+AA193+AA194+AA195+AA196+AA197+AA198+AA199+AA200+AA201+AA202+AA203+AA204+AA205+AA206+AA207+AA208+AA209+AA210+AA211+AA212+AA213+AA214+AA215+AA216+AA217+AA218+AA219+AA220+AA221+AA222+AA223+AA224+AA225+AA226+AA227+AA228+AA229+AA230+AA231+AA232+AA233+AA234+AA235+AA236+AA237+AA238+AA239+AA240+AA241+AA242+AA243+AA244+AA245+AA246+AA247+AA248+AA249+AA250+AA251+AA252+AA253+AA254+AA255+AA256+AA257+AA258+AA259+AA260+AA261+AA262+AA263+AA264+AA265+AA266+AA267+AA268+AA269+AA270+AA271+AA272+AA273+AA274+AA275+AA276+AA277+AA278+AA279+AA280+AA281+AA282+AA283+AA284+AA285+AA286+AA287+AA288+AA289+AA290+AA291+AA292+AA293+AA294+AA295+AA296+AA297+AA298+AA299+AA300+AA301+AA302+AA303+AA304+AA305+AA306+AA307+AA308+AA309+AA310+AA311+AA312+AA313+AA314+AA315+AA316+AA317+AA318+AA319+AA320+AA321+AA322+AA323+AA324+AA325+AA326+AA327+AA328+AA329+AA330+AA331+AA332+AA333+AA334+AA335+AA336+AA337+AA338+AA339+AA340+AA341+AA342+AA343+AA344+AA345+AA346+AA347+AA348+AA349+AA350+AA351+AA352+AA353+AA354+AA355+AA356+AA357+AA358+AA359+AA360+AA361+AA362+AA363+AA364+AA365+AA366+AA367+AA368+AA369+AA370+AA371+AA372+AA373+AA374+AA375+AA376+AA377+AA378+AA379+AA380+AA381+AA382+AA383+AA384+AA385+AA386+AA387+AA388+AA389+AA390+AA391+AA392+AA393+AA394+AA395+AA396+AA397+AA398+AA399+AA400+AA401+AA402+AA403+AA404+AA405+AA406+AA407+AA408+AA409+AA410+AA411+AA412+AA413+AA414+AA415+AA416+AA417+AA418+AA419+AA420+AA421+AA422+AA423+AA424+AA425+AA426+AA427+AA428+AA429+AA430+AA431+AA432+AA433+AA434+AA435+AA436+AA437+AA438+AA439+AA440+AA441+AA442+AA443+AA444+AA445+AA446+AA447+AA448+AA449+AA450+AA451+AA452+AA453+AA454+AA455+AA456+AA457+AA458+AA459+AA460+AA461+AA462+AA463+AA464+AA465+AA466+AA467+AA468+AA469+AA470+AA471+AA472+AA473+AA474+AA475+AA476+AA477+AA478+AA479+AA480+AA481+AA482+AA483+AA484+AA485+AA486+AA487+AA488+AA489+AA490+AA491+AA492+AA493+AA494+AA495+AA496+AA497+AA498+AA499+AA500+AA501+AA502+AA503+AA504+AA505+AA506+AA507+AA508+AA509+AA510+AA511+AA512+AA513+AA514+AA515+AA516+AA517+AA518+AA519+AA520+AA521+AA522+AA523+AA524+AA525+AA526+AA527+AA528+AA529+AA530+AA531+AA532+AA533+AA534+AA535+AA536+AA537+AA538+AA539+AA540+AA541+AA542+AA543+AA544+AA545+AA546+AA547+AA548+AA549+AA550+AA551+AA552+AA553+AA554+AA555+AA556+AA557+AA558+AA559+AA560 -> 0 | AI9: =AB9+AB10+AB11+AB12+AB13+AB14+AB15+AB16+AB17+AB18+AB19+AB20+AB21+AB22+AB23+AB24+AB25+AB26+AB27+AB28+AB29+AB30+AB31+AB32+AB33+AB34+AB35+AB36+AB37+AB38+AB39+AB40+AB41+AB42+AB43+AB44+AB45+AB46+AB47+AB48+AB49+AB50+AB51+AB52+AB53+AB54+AB55+AB56+AB57+AB58+AB59+AB60+AB61+AB62+AB63+AB64+AB65+AB66+AB67+AB68+AB69+AB70+AB71+AB72+AB73+AB74+AB75+AB76+AB77+AB78+AB79+AB80+AB81+AB82+AB83+AB84+AB85+AB86+AB87+AB88+AB89+AB90+AB91+AB92+AB93+AB94+AB95+AB96+AB97+AB98+AB99+AB100+AB101+AB102+AB103+AB104+AB105+AB106+AB107+AB108+AB109+AB110+AB111+AB112+AB113+AB114+AB115+AB116+AB117+AB118+AB119+AB120+AB121+AB122+AB123+AB124+AB125+AB126+AB127+AB128+AB129+AB130+AB131+AB132+AB133+AB134+AB135+AB136+AB137+AB138+AB139+AB140+AB141+AB142+AB143+AB144+AB145+AB146+AB147+AB148+AB149+AB150+AB151+AB152+AB153+AB154+AB155+AB156+AB157+AB158+AB159+AB160+AB161+AB162+AB163+AB164+AB165+AB166+AB167+AB168+AB169+AB170+AB171+AB172+AB173+AB174+AB175+AB176+AB177+AB178+AB179+AB180+AB181+AB182+AB183+AB184+AB185+AB186+AB187+AB188+AB189+AB190+AB191+AB192+AB193+AB194+AB195+AB196+AB197+AB198+AB199+AB200+AB201+AB202+AB203+AB204+AB205+AB206+AB207+AB208+AB209+AB210+AB211+AB212+AB213+AB214+AB215+AB216+AB217+AB218+AB219+AB220+AB221+AB222+AB223+AB224+AB225+AB226+AB227+AB228+AB229+AB230+AB231+AB232+AB233+AB234+AB235+AB236+AB237+AB238+AB239+AB240+AB241+AB242+AB243+AB244+AB245+AB246+AB247+AB248+AB249+AB250+AB251+AB252+AB253+AB254+AB255+AB256+AB257+AB258+AB259+AB260+AB261+AB262+AB263+AB264+AB265+AB266+AB267+AB268+AB269+AB270+AB271+AB272+AB273+AB274+AB275+AB276+AB277+AB278+AB279+AB280+AB281+AB282+AB283+AB284+AB285+AB286+AB287+AB288+AB289+AB290+AB291+AB292+AB293+AB294+AB295+AB296+AB297+AB298+AB299+AB300+AB301+AB302+AB303+AB304+AB305+AB306+AB307+AB308+AB309+AB310+AB311+AB312+AB313+AB314+AB315+AB316+AB317+AB318+AB319+AB320+AB321+AB322+AB323+AB324+AB325+AB326+AB327+AB328+AB329+AB330+AB331+AB332+AB333+AB334+AB335+AB336+AB337+AB338+AB339+AB340+AB341+AB342+AB343+AB344+AB345+AB346+AB347+AB348+AB349+AB350+AB351+AB352+AB353+AB354+AB355+AB356+AB357+AB358+AB359+AB360+AB361+AB362+AB363+AB364+AB365+AB366+AB367+AB368+AB369+AB370+AB371+AB372+AB373+AB374+AB375+AB376+AB377+AB378+AB379+AB380+AB381+AB382+AB383+AB384+AB385+AB386+AB387+AB388+AB389+AB390+AB391+AB392+AB393+AB394+AB395+AB396+AB397+AB398+AB399+AB400+AB401+AB402+AB403+AB404+AB405+AB406+AB407+AB408+AB409+AB410+AB411+AB412+AB413+AB414+AB415+AB416+AB417+AB418+AB419+AB420+AB421+AB422+AB423+AB424+AB425+AB426+AB427+AB428+AB429+AB430+AB431+AB432+AB433+AB434+AB435+AB436+AB437+AB438+AB439+AB440+AB441+AB442+AB443+AB444+AB445+AB446+AB447+AB448+AB449+AB450+AB451+AB452+AB453+AB454+AB455+AB456+AB457+AB458+AB459+AB460+AB461+AB462+AB463+AB464+AB465+AB466+AB467+AB468+AB469+AB470+AB471+AB472+AB473+AB474+AB475+AB476+AB477+AB478+AB479+AB480+AB481+AB482+AB483+AB484+AB485+AB486+AB487+AB488+AB489+AB490+AB491+AB492+AB493+AB494+AB495+AB496+AB497+AB498+AB499+AB500+AB501+AB502+AB503+AB504+AB505+AB506+AB507+AB508+AB509+AB510+AB511+AB512+AB513+AB514+AB515+AB516+AB517+AB518+AB519+AB520+AB521+AB522+AB523+AB524+AB525+AB526+AB527+AB528+AB529+AB530+AB531+AB532+AB533+AB534+AB535+AB536+AB537+AB538+AB539+AB540+AB541+AB542+AB543+AB544+AB545+AB546+AB547+AB548+AB549+AB550+AB551+AB552+AB553+AB554+AB555+AB556+AB557+AB558+AB559+AB560 -> 2450 | AJ9: =AC9+AC10+AC11+AC12+AC13+AC14+AC15+AC16+AC17+AC18+AC19+AC20+AC21+AC22+AC23+AC24+AC25+AC26+AC27+AC28+AC29+AC30+AC31+AC32+AC33+AC34+AC35+AC36+AC37+AC38+AC39+AC40+AC41+AC42+AC43+AC44+AC45+AC46+AC47+AC48+AC49+AC50+AC51+AC52+AC53+AC54+AC55+AC56+AC57+AC58+AC59+AC60+AC61+AC62+AC63+AC64+AC65+AC66+AC67+AC68+AC69+AC70+AC71+AC72+AC73+AC74+AC75+AC76+AC77+AC78+AC79+AC80+AC81+AC82+AC83+AC84+AC85+AC86+AC87+AC88+AC89+AC90+AC91+AC92+AC93+AC94+AC95+AC96+AC97+AC98+AC99+AC100+AC101+AC102+AC103+AC104+AC105+AC106+AC107+AC108+AC109+AC110+AC111+AC112+AC113+AC114+AC115+AC116+AC117+AC118+AC119+AC120+AC121+AC122+AC123+AC124+AC125+AC126+AC127+AC128+AC129+AC130+AC131+AC132+AC133+AC134+AC135+AC136+AC137+AC138+AC139+AC140+AC141+AC142+AC143+AC144+AC145+AC146+AC147+AC148+AC149+AC150+AC151+AC152+AC153+AC154+AC155+AC156+AC157+AC158+AC159+AC160+AC161+AC162+AC163+AC164+AC165+AC166+AC167+AC168+AC169+AC170+AC171+AC172+AC173+AC174+AC175+AC176+AC177+AC178+AC179+AC180+AC181+AC182+AC183+AC184+AC185+AC186+AC187+AC188+AC189+AC190+AC191+AC192+AC193+AC194+AC195+AC196+AC197+AC198+AC199+AC200+AC201+AC202+AC203+AC204+AC205+AC206+AC207+AC208+AC209+AC210+AC211+AC212+AC213+AC214+AC215+AC216+AC217+AC218+AC219+AC220+AC221+AC222+AC223+AC224+AC225+AC226+AC227+AC228+AC229+AC230+AC231+AC232+AC233+AC234+AC235+AC236+AC237+AC238+AC239+AC240+AC241+AC242+AC243+AC244+AC245+AC246+AC247+AC248+AC249+AC250+AC251+AC252+AC253+AC254+AC255+AC256+AC257+AC258+AC259+AC260+AC261+AC262+AC263+AC264+AC265+AC266+AC267+AC268+AC269+AC270+AC271+AC272+AC273+AC274+AC275+AC276+AC277+AC278+AC279+AC280+AC281+AC282+AC283+AC284+AC285+AC286+AC287+AC288+AC289+AC290+AC291+AC292+AC293+AC294+AC295+AC296+AC297+AC298+AC299+AC300+AC301+AC302+AC303+AC304+AC305+AC306+AC307+AC308+AC309+AC310+AC311+AC312+AC313+AC314+AC315+AC316+AC317+AC318+AC319+AC320+AC321+AC322+AC323+AC324+AC325+AC326+AC327+AC328+AC329+AC330+AC331+AC332+AC333+AC334+AC335+AC336+AC337+AC338+AC339+AC340+AC341+AC342+AC343+AC344+AC345+AC346+AC347+AC348+AC349+AC350+AC351+AC352+AC353+AC354+AC355+AC356+AC357+AC358+AC359+AC360+AC361+AC362+AC363+AC364+AC365+AC366+AC367+AC368+AC369+AC370+AC371+AC372+AC373+AC374+AC375+AC376+AC377+AC378+AC379+AC380+AC381+AC382+AC383+AC384+AC385+AC386+AC387+AC388+AC389+AC390+AC391+AC392+AC393+AC394+AC395+AC396+AC397+AC398+AC399+AC400+AC401+AC402+AC403+AC404+AC405+AC406+AC407+AC408+AC409+AC410+AC411+AC412+AC413+AC414+AC415+AC416+AC417+AC418+AC419+AC420+AC421+AC422+AC423+AC424+AC425+AC426+AC427+AC428+AC429+AC430+AC431+AC432+AC433+AC434+AC435+AC436+AC437+AC438+AC439+AC440+AC441+AC442+AC443+AC444+AC445+AC446+AC447+AC448+AC449+AC450+AC451+AC452+AC453+AC454+AC455+AC456+AC457+AC458+AC459+AC460+AC461+AC462+AC463+AC464+AC465+AC466+AC467+AC468+AC469+AC470+AC471+AC472+AC473+AC474+AC475+AC476+AC477+AC478+AC479+AC480+AC481+AC482+AC483+AC484+AC485+AC486+AC487+AC488+AC489+AC490+AC491+AC492+AC493+AC494+AC495+AC496+AC497+AC498+AC499+AC500+AC501+AC502+AC503+AC504+AC505+AC506+AC507+AC508+AC509+AC510+AC511+AC512+AC513+AC514+AC515+AC516+AC517+AC518+AC519+AC520+AC521+AC522+AC523+AC524+AC525+AC526+AC527+AC528+AC529+AC530+AC531+AC532+AC533+AC534+AC535+AC536+AC537+AC538+AC539+AC540+AC541+AC542+AC543+AC544+AC545+AC546+AC547+AC548+AC549+AC550+AC551+AC552+AC553+AC554+AC555+AC556+AC557+AC558+AC559+AC560 -> 2000 | AK9: =AD9+AD10+AD11+AD12+AD13+AD14+AD15+AD16+AD17+AD18+AD19+AD20+AD21+AD22+AD23+AD24+AD25+AD26+AD27+AD28+AD29+AD30+AD31+AD32+AD33+AD34+AD35+AD36+AD37+AD38+AD39+AD40+AD41+AD42+AD43+AD44+AD45+AD46+AD47+AD48+AD49+AD50+AD51+AD52+AD53+AD54+AD55+AD56+AD57+AD58+AD59+AD60+AD61+AD62+AD63+AD64+AD65+AD66+AD67+AD68+AD69+AD70+AD71+AD72+AD73+AD74+AD75+AD76+AD77+AD78+AD79+AD80+AD81+AD82+AD83+AD84+AD85+AD86+AD87+AD88+AD89+AD90+AD91+AD92+AD93+AD94+AD95+AD96+AD97+AD98+AD99+AD100+AD101+AD102+AD103+AD104+AD105+AD106+AD107+AD108+AD109+AD110+AD111+AD112+AD113+AD114+AD115+AD116+AD117+AD118+AD119+AD120+AD121+AD122+AD123+AD124+AD125+AD126+AD127+AD128+AD129+AD130+AD131+AD132+AD133+AD134+AD135+AD136+AD137+AD138+AD139+AD140+AD141+AD142+AD143+AD144+AD145+AD146+AD147+AD148+AD149+AD150+AD151+AD152+AD153+AD154+AD155+AD156+AD157+AD158+AD159+AD160+AD161+AD162+AD163+AD164+AD165+AD166+AD167+AD168+AD169+AD170+AD171+AD172+AD173+AD174+AD175+AD176+AD177+AD178+AD179+AD180+AD181+AD182+AD183+AD184+AD185+AD186+AD187+AD188+AD189+AD190+AD191+AD192+AD193+AD194+AD195+AD196+AD197+AD198+AD199+AD200+AD201+AD202+AD203+AD204+AD205+AD206+AD207+AD208+AD209+AD210+AD211+AD212+AD213+AD214+AD215+AD216+AD217+AD218+AD219+AD220+AD221+AD222+AD223+AD224+AD225+AD226+AD227+AD228+AD229+AD230+AD231+AD232+AD233+AD234+AD235+AD236+AD237+AD238+AD239+AD240+AD241+AD242+AD243+AD244+AD245+AD246+AD247+AD248+AD249+AD250+AD251+AD252+AD253+AD254+AD255+AD256+AD257+AD258+AD259+AD260+AD261+AD262+AD263+AD264+AD265+AD266+AD267+AD268+AD269+AD270+AD271+AD272+AD273+AD274+AD275+AD276+AD277+AD278+AD279+AD280+AD281+AD282+AD283+AD284+AD285+AD286+AD287+AD288+AD289+AD290+AD291+AD292+AD293+AD294+AD295+AD296+AD297+AD298+AD299+AD300+AD301+AD302+AD303+AD304+AD305+AD306+AD307+AD308+AD309+AD310+AD311+AD312+AD313+AD314+AD315+AD316+AD317+AD318+AD319+AD320+AD321+AD322+AD323+AD324+AD325+AD326+AD327+AD328+AD329+AD330+AD331+AD332+AD333+AD334+AD335+AD336+AD337+AD338+AD339+AD340+AD341+AD342+AD343+AD344+AD345+AD346+AD347+AD348+AD349+AD350+AD351+AD352+AD353+AD354+AD355+AD356+AD357+AD358+AD359+AD360+AD361+AD362+AD363+AD364+AD365+AD366+AD367+AD368+AD369+AD370+AD371+AD372+AD373+AD374+AD375+AD376+AD377+AD378+AD379+AD380+AD381+AD382+AD383+AD384+AD385+AD386+AD387+AD388+AD389+AD390+AD391+AD392+AD393+AD394+AD395+AD396+AD397+AD398+AD399+AD400+AD401+AD402+AD403+AD404+AD405+AD406+AD407+AD408+AD409+AD410+AD411+AD412+AD413+AD414+AD415+AD416+AD417+AD418+AD419+AD420+AD421+AD422+AD423+AD424+AD425+AD426+AD427+AD428+AD429+AD430+AD431+AD432+AD433+AD434+AD435+AD436+AD437+AD438+AD439+AD440+AD441+AD442+AD443+AD444+AD445+AD446+AD447+AD448+AD449+AD450+AD451+AD452+AD453+AD454+AD455+AD456+AD457+AD458+AD459+AD460+AD461+AD462+AD463+AD464+AD465+AD466+AD467+AD468+AD469+AD470+AD471+AD472+AD473+AD474+AD475+AD476+AD477+AD478+AD479+AD480+AD481+AD482+AD483+AD484+AD485+AD486+AD487+AD488+AD489+AD490+AD491+AD492+AD493+AD494+AD495+AD496+AD497+AD498+AD499+AD500+AD501+AD502+AD503+AD504+AD505+AD506+AD507+AD508+AD509+AD510+AD511+AD512+AD513+AD514+AD515+AD516+AD517+AD518+AD519+AD520+AD521+AD522+AD523+AD524+AD525+AD526+AD527+AD528+AD529+AD530+AD531+AD532+AD533+AD534+AD535+AD536+AD537+AD538+AD539+AD540+AD541+AD542+AD543+AD544+AD545+AD546+AD547+AD548+AD549+AD550+AD551+AD552+AD553+AD554+AD555+AD556+AD557+AD558+AD559+AD560 -> 14350 | AL9: =AE9+AE10+AE11+AE12+AE13+AE14+AE15+AE16+AE17+AE18+AE19+AE20+AE21+AE22+AE23+AE24+AE25+AE26+AE27+AE28+AE29+AE30+AE31+AE32+AE33+AE34+AE35+AE36+AE37+AE38+AE39+AE40+AE41+AE42+AE43+AE44+AE45+AE46+AE47+AE48+AE49+AE50+AE51+AE52+AE53+AE54+AE55+AE56+AE57+AE58+AE59+AE60+AE61+AE62+AE63+AE64+AE65+AE66+AE67+AE68+AE69+AE70+AE71+AE72+AE73+AE74+AE75+AE76+AE77+AE78+AE79+AE80+AE81+AE82+AE83+AE84+AE85+AE86+AE87+AE88+AE89+AE90+AE91+AE92+AE93+AE94+AE95+AE96+AE97+AE98+AE99+AE100+AE101+AE102+AE103+AE104+AE105+AE106+AE107+AE108+AE109+AE110+AE111+AE112+AE113+AE114+AE115+AE116+AE117+AE118+AE119+AE120+AE121+AE122+AE123+AE124+AE125+AE126+AE127+AE128+AE129+AE130+AE131+AE132+AE133+AE134+AE135+AE136+AE137+AE138+AE139+AE140+AE141+AE142+AE143+AE144+AE145+AE146+AE147+AE148+AE149+AE150+AE151+AE152+AE153+AE154+AE155+AE156+AE157+AE158+AE159+AE160+AE161+AE162+AE163+AE164+AE165+AE166+AE167+AE168+AE169+AE170+AE171+AE172+AE173+AE174+AE175+AE176+AE177+AE178+AE179+AE180+AE181+AE182+AE183+AE184+AE185+AE186+AE187+AE188+AE189+AE190+AE191+AE192+AE193+AE194+AE195+AE196+AE197+AE198+AE199+AE200+AE201+AE202+AE203+AE204+AE205+AE206+AE207+AE208+AE209+AE210+AE211+AE212+AE213+AE214+AE215+AE216+AE217+AE218+AE219+AE220+AE221+AE222+AE223+AE224+AE225+AE226+AE227+AE228+AE229+AE230+AE231+AE232+AE233+AE234+AE235+AE236+AE237+AE238+AE239+AE240+AE241+AE242+AE243+AE244+AE245+AE246+AE247+AE248+AE249+AE250+AE251+AE252+AE253+AE254+AE255+AE256+AE257+AE258+AE259+AE260+AE261+AE262+AE263+AE264+AE265+AE266+AE267+AE268+AE269+AE270+AE271+AE272+AE273+AE274+AE275+AE276+AE277+AE278+AE279+AE280+AE281+AE282+AE283+AE284+AE285+AE286+AE287+AE288+AE289+AE290+AE291+AE292+AE293+AE294+AE295+AE296+AE297+AE298+AE299+AE300+AE301+AE302+AE303+AE304+AE305+AE306+AE307+AE308+AE309+AE310+AE311+AE312+AE313+AE314+AE315+AE316+AE317+AE318+AE319+AE320+AE321+AE322+AE323+AE324+AE325+AE326+AE327+AE328+AE329+AE330+AE331+AE332+AE333+AE334+AE335+AE336+AE337+AE338+AE339+AE340+AE341+AE342+AE343+AE344+AE345+AE346+AE347+AE348+AE349+AE350+AE351+AE352+AE353+AE354+AE355+AE356+AE357+AE358+AE359+AE360+AE361+AE362+AE363+AE364+AE365+AE366+AE367+AE368+AE369+AE370+AE371+AE372+AE373+AE374+AE375+AE376+AE377+AE378+AE379+AE380+AE381+AE382+AE383+AE384+AE385+AE386+AE387+AE388+AE389+AE390+AE391+AE392+AE393+AE394+AE395+AE396+AE397+AE398+AE399+AE400+AE401+AE402+AE403+AE404+AE405+AE406+AE407+AE408+AE409+AE410+AE411+AE412+AE413+AE414+AE415+AE416+AE417+AE418+AE419+AE420+AE421+AE422+AE423+AE424+AE425+AE426+AE427+AE428+AE429+AE430+AE431+AE432+AE433+AE434+AE435+AE436+AE437+AE438+AE439+AE440+AE441+AE442+AE443+AE444+AE445+AE446+AE447+AE448+AE449+AE450+AE451+AE452+AE453+AE454+AE455+AE456+AE457+AE458+AE459+AE460+AE461+AE462+AE463+AE464+AE465+AE466+AE467+AE468+AE469+AE470+AE471+AE472+AE473+AE474+AE475+AE476+AE477+AE478+AE479+AE480+AE481+AE482+AE483+AE484+AE485+AE486+AE487+AE488+AE489+AE490+AE491+AE492+AE493+AE494+AE495+AE496+AE497+AE498+AE499+AE500+AE501+AE502+AE503+AE504+AE505+AE506+AE507+AE508+AE509+AE510+AE511+AE512+AE513+AE514+AE515+AE516+AE517+AE518+AE519+AE520+AE521+AE522+AE523+AE524+AE525+AE526+AE527+AE528+AE529+AE530+AE531+AE532+AE533+AE534+AE535+AE536+AE537+AE538+AE539+AE540+AE541+AE542+AE543+AE544+AE545+AE546+AE547+AE548+AE549+AE550+AE551+AE552+AE553+AE554+AE555+AE556+AE557+AE558+AE559+AE560 -> 2400 | AM9: =AF9+AF10+AF11+AF12+AF13+AF14+AF15+AF16+AF17+AF18+AF19+AF20+AF21+AF22+AF23+AF24+AF25+AF26+AF27+AF28+AF29+AF30+AF31+AF32+AF33+AF34+AF35+AF36+AF37+AF38+AF39+AF40+AF41+AF42+AF43+AF44+AF45+AF46+AF47+AF48+AF49+AF50+AF51+AF52+AF53+AF54+AF55+AF56+AF57+AF58+AF59+AF60+AF61+AF62+AF63+AF64+AF65+AF66+AF67+AF68+AF69+AF70+AF71+AF72+AF73+AF74+AF75+AF76+AF77+AF78+AF79+AF80+AF81+AF82+AF83+AF84+AF85+AF86+AF87+AF88+AF89+AF90+AF91+AF92+AF93+AF94+AF95+AF96+AF97+AF98+AF99+AF100+AF101+AF102+AF103+AF104+AF105+AF106+AF107+AF108+AF109+AF110+AF111+AF112+AF113+AF114+AF115+AF116+AF117+AF118+AF119+AF120+AF121+AF122+AF123+AF124+AF125+AF126+AF127+AF128+AF129+AF130+AF131+AF132+AF133+AF134+AF135+AF136+AF137+AF138+AF139+AF140+AF141+AF142+AF143+AF144+AF145+AF146+AF147+AF148+AF149+AF150+AF151+AF152+AF153+AF154+AF155+AF156+AF157+AF158+AF159+AF160+AF161+AF162+AF163+AF164+AF165+AF166+AF167+AF168+AF169+AF170+AF171+AF172+AF173+AF174+AF175+AF176+AF177+AF178+AF179+AF180+AF181+AF182+AF183+AF184+AF185+AF186+AF187+AF188+AF189+AF190+AF191+AF192+AF193+AF194+AF195+AF196+AF197+AF198+AF199+AF200+AF201+AF202+AF203+AF204+AF205+AF206+AF207+AF208+AF209+AF210+AF211+AF212+AF213+AF214+AF215+AF216+AF217+AF218+AF219+AF220+AF221+AF222+AF223+AF224+AF225+AF226+AF227+AF228+AF229+AF230+AF231+AF232+AF233+AF234+AF235+AF236+AF237+AF238+AF239+AF240+AF241+AF242+AF243+AF244+AF245+AF246+AF247+AF248+AF249+AF250+AF251+AF252+AF253+AF254+AF255+AF256+AF257+AF258+AF259+AF260+AF261+AF262+AF263+AF264+AF265+AF266+AF267+AF268+AF269+AF270+AF271+AF272+AF273+AF274+AF275+AF276+AF277+AF278+AF279+AF280+AF281+AF282+AF283+AF284+AF285+AF286+AF287+AF288+AF289+AF290+AF291+AF292+AF293+AF294+AF295+AF296+AF297+AF298+AF299+AF300+AF301+AF302+AF303+AF304+AF305+AF306+AF307+AF308+AF309+AF310+AF311+AF312+AF313+AF314+AF315+AF316+AF317+AF318+AF319+AF320+AF321+AF322+AF323+AF324+AF325+AF326+AF327+AF328+AF329+AF330+AF331+AF332+AF333+AF334+AF335+AF336+AF337+AF338+AF339+AF340+AF341+AF342+AF343+AF344+AF345+AF346+AF347+AF348+AF349+AF350+AF351+AF352+AF353+AF354+AF355+AF356+AF357+AF358+AF359+AF360+AF361+AF362+AF363+AF364+AF365+AF366+AF367+AF368+AF369+AF370+AF371+AF372+AF373+AF374+AF375+AF376+AF377+AF378+AF379+AF380+AF381+AF382+AF383+AF384+AF385+AF386+AF387+AF388+AF389+AF390+AF391+AF392+AF393+AF394+AF395+AF396+AF397+AF398+AF399+AF400+AF401+AF402+AF403+AF404+AF405+AF406+AF407+AF408+AF409+AF410+AF411+AF412+AF413+AF414+AF415+AF416+AF417+AF418+AF419+AF420+AF421+AF422+AF423+AF424+AF425+AF426+AF427+AF428+AF429+AF430+AF431+AF432+AF433+AF434+AF435+AF436+AF437+AF438+AF439+AF440+AF441+AF442+AF443+AF444+AF445+AF446+AF447+AF448+AF449+AF450+AF451+AF452+AF453+AF454+AF455+AF456+AF457+AF458+AF459+AF460+AF461+AF462+AF463+AF464+AF465+AF466+AF467+AF468+AF469+AF470+AF471+AF472+AF473+AF474+AF475+AF476+AF477+AF478+AF479+AF480+AF481+AF482+AF483+AF484+AF485+AF486+AF487+AF488+AF489+AF490+AF491+AF492+AF493+AF494+AF495+AF496+AF497+AF498+AF499+AF500+AF501+AF502+AF503+AF504+AF505+AF506+AF507+AF508+AF509+AF510+AF511+AF512+AF513+AF514+AF515+AF516+AF517+AF518+AF519+AF520+AF521+AF522+AF523+AF524+AF525+AF526+AF527+AF528+AF529+AF530+AF531+AF532+AF533+AF534+AF535+AF536+AF537+AF538+AF539+AF540+AF541+AF542+AF543+AF544+AF545+AF546+AF547+AF548+AF549+AF550+AF551+AF552+AF553+AF554+AF555+AF556+AF557+AF558+AF559+AF560 -> 0 | AN9: =AG9+AG10+AG11+AG12+AG13+AG14+AG15+AG16+AG17+AG18+AG19+AG20+AG21+AG22+AG23+AG24+AG25+AG26+AG27+AG28+AG29+AG30+AG31+AG32+AG33+AG34+AG35+AG36+AG37+AG38+AG39+AG40+AG41+AG42+AG43+AG44+AG45+AG46+AG47+AG48+AG49+AG50+AG51+AG52+AG53+AG54+AG55+AG56+AG57+AG58+AG59+AG60+AG61+AG62+AG63+AG64+AG65+AG66+AG67+AG68+AG69+AG70+AG71+AG72+AG73+AG74+AG75+AG76+AG77+AG78+AG79+AG80+AG81+AG82+AG83+AG84+AG85+AG86+AG87+AG88+AG89+AG90+AG91+AG92+AG93+AG94+AG95+AG96+AG97+AG98+AG99+AG100+AG101+AG102+AG103+AG104+AG105+AG106+AG107+AG108+AG109+AG110+AG111+AG112+AG113+AG114+AG115+AG116+AG117+AG118+AG119+AG120+AG121+AG122+AG123+AG124+AG125+AG126+AG127+AG128+AG129+AG130+AG131+AG132+AG133+AG134+AG135+AG136+AG137+AG138+AG139+AG140+AG141+AG142+AG143+AG144+AG145+AG146+AG147+AG148+AG149+AG150+AG151+AG152+AG153+AG154+AG155+AG156+AG157+AG158+AG159+AG160+AG161+AG162+AG163+AG164+AG165+AG166+AG167+AG168+AG169+AG170+AG171+AG172+AG173+AG174+AG175+AG176+AG177+AG178+AG179+AG180+AG181+AG182+AG183+AG184+AG185+AG186+AG187+AG188+AG189+AG190+AG191+AG192+AG193+AG194+AG195+AG196+AG197+AG198+AG199+AG200+AG201+AG202+AG203+AG204+AG205+AG206+AG207+AG208+AG209+AG210+AG211+AG212+AG213+AG214+AG215+AG216+AG217+AG218+AG219+AG220+AG221+AG222+AG223+AG224+AG225+AG226+AG227+AG228+AG229+AG230+AG231+AG232+AG233+AG234+AG235+AG236+AG237+AG238+AG239+AG240+AG241+AG242+AG243+AG244+AG245+AG246+AG247+AG248+AG249+AG250+AG251+AG252+AG253+AG254+AG255+AG256+AG257+AG258+AG259+AG260+AG261+AG262+AG263+AG264+AG265+AG266+AG267+AG268+AG269+AG270+AG271+AG272+AG273+AG274+AG275+AG276+AG277+AG278+AG279+AG280+AG281+AG282+AG283+AG284+AG285+AG286+AG287+AG288+AG289+AG290+AG291+AG292+AG293+AG294+AG295+AG296+AG297+AG298+AG299+AG300+AG301+AG302+AG303+AG304+AG305+AG306+AG307+AG308+AG309+AG310+AG311+AG312+AG313+AG314+AG315+AG316+AG317+AG318+AG319+AG320+AG321+AG322+AG323+AG324+AG325+AG326+AG327+AG328+AG329+AG330+AG331+AG332+AG333+AG334+AG335+AG336+AG337+AG338+AG339+AG340+AG341+AG342+AG343+AG344+AG345+AG346+AG347+AG348+AG349+AG350+AG351+AG352+AG353+AG354+AG355+AG356+AG357+AG358+AG359+AG360+AG361+AG362+AG363+AG364+AG365+AG366+AG367+AG368+AG369+AG370+AG371+AG372+AG373+AG374+AG375+AG376+AG377+AG378+AG379+AG380+AG381+AG382+AG383+AG384+AG385+AG386+AG387+AG388+AG389+AG390+AG391+AG392+AG393+AG394+AG395+AG396+AG397+AG398+AG399+AG400+AG401+AG402+AG403+AG404+AG405+AG406+AG407+AG408+AG409+AG410+AG411+AG412+AG413+AG414+AG415+AG416+AG417+AG418+AG419+AG420+AG421+AG422+AG423+AG424+AG425+AG426+AG427+AG428+AG429+AG430+AG431+AG432+AG433+AG434+AG435+AG436+AG437+AG438+AG439+AG440+AG441+AG442+AG443+AG444+AG445+AG446+AG447+AG448+AG449+AG450+AG451+AG452+AG453+AG454+AG455+AG456+AG457+AG458+AG459+AG460+AG461+AG462+AG463+AG464+AG465+AG466+AG467+AG468+AG469+AG470+AG471+AG472+AG473+AG474+AG475+AG476+AG477+AG478+AG479+AG480+AG481+AG482+AG483+AG484+AG485+AG486+AG487+AG488+AG489+AG490+AG491+AG492+AG493+AG494+AG495+AG496+AG497+AG498+AG499+AG500+AG501+AG502+AG503+AG504+AG505+AG506+AG507+AG508+AG509+AG510+AG511+AG512+AG513+AG514+AG515+AG516+AG517+AG518+AG519+AG520+AG521+AG522+AG523+AG524+AG525+AG526+AG527+AG528+AG529+AG530+AG531+AG532+AG533+AG534+AG535+AG536+AG537+AG538+AG539+AG540+AG541+AG542+AG543+AG544+AG545+AG546+AG547+AG548+AG549+AG550+AG551+AG552+AG553+AG554+AG555+AG556+AG557+AG558+AG559+AG560 -> 1000 | AO9: 1 | AP9: =U9*B9 -> 1600 | AQ9: =U9*C9 -> 2000 | AR9: =AQ9-AP9 -> 400 | AS9: =X9*B9 -> 1600
A10: 2 | B10: 1800 | C10: 2500 | D10: =C10-B10 -> 700 | E10: Reloj Jesus Grande | F10: 0 | U10: =T10+R10+P10+N10+L10+J10+H10 -> 0 | X10: =F10+G10+I10+K10+M10+O10+Q10+S10-H10-J10-L10-N10-P10-R10-T10-V10-W10 -> 0 | Y10: =G10+I10+K10+M10+O10+Q10+S10 -> 0 | Z10: =Y10*B10 -> 0 | AA10: =H10*C10 -> 0 | AB10: =J10*C10 -> 0 | AC10: =L10*C10 -> 0 | AD10: =N10*C10 -> 0 | AE10: =P10*C10 -> 0 | AF10: =R10*C10 -> 0 | AG10: =T10*C10 -> 0 | AO10: 2 | AP10: =U10*B10 -> 0 | AQ10: =U10*C10 -> 0 | AR10: =AQ10-AP10 -> 0 | AS10: =X10*B10 -> 0
A11: 3 | B11: 3300 | C11: 4500 | D11: =C11-B11 -> 1200 | E11: Reloj x 4500 | F11: 1 | U11: =T11+R11+P11+N11+L11+J11+H11 -> 0 | X11: =F11+G11+I11+K11+M11+O11+Q11+S11-H11-J11-L11-N11-P11-R11-T11-V11-W11 -> 1 | Y11: =G11+I11+K11+M11+O11+Q11+S11 -> 0 | Z11: =Y11*B11 -> 0 | AA11: =H11*C11 -> 0 | AB11: =J11*C11 -> 0 | AC11: =L11*C11 -> 0 | AD11: =N11*C11 -> 0 | AE11: =P11*C11 -> 0 | AF11: =R11*C11 -> 0 | AG11: =T11*C11 -> 0 | AO11: 3 | AP11: =U11*B11 -> 0 | AQ11: =U11*C11 -> 0 | AR11: =AQ11-AP11 -> 0 | AS11: =X11*B11 -> 3300
A12: 4 | B12: 5800 | C12: 7500 | D12: =C12-B12 -> 1700 | E12: Reloj c/pendulo | F12: 1 | U12: =T12+R12+P12+N12+L12+J12+H12 -> 0 | X12: =F12+G12+I12+K12+M12+O12+Q12+S12-H12-J12-L12-N12-P12-R12-T12-V12-W12 -> 1 | Y12: =G12+I12+K12+M12+O12+Q12+S12 -> 0 | Z12: =Y12*B12 -> 0 | AA12: =H12*C12 -> 0 | AB12: =J12*C12 -> 0 | AC12: =L12*C12 -> 0 | AD12: =N12*C12 -> 0 | AE12: =P12*C12 -> 0 | AF12: =R12*C12 -> 0 | AG12: =T12*C12 -> 0 | AH12: Total de la semana | AI12: =AH9+AI9+AJ9+AK9+AL9+AM9+AN9 -> 22200 | AO12: 4 | AP12: =U12*B12 -> 0 | AQ12: =U12*C12 -> 0 | AR12: =AQ12-AP12 -> 0 | AS12: =X12*B12 -> 5800
A13: 5 | F13: 0 | U13: =T13+R13+P13+N13+L13+J13+H13 -> 0 | X13: =F13+G13+I13+K13+M13+O13+Q13+S13-H13-J13-L13-N13-P13-R13-T13-V13-W13 -> 0 | Y13: =G13+I13+K13+M13+O13+Q13+S13 -> 0 | Z13: =Y13*B13 -> 0 | AA13: =H13*C13 -> 0 | AB13: =J13*C13 -> 0 | AC13: =L13*C13 -> 0 | AD13: =N13*C13 -> 0 | AE13: =P13*C13 -> 0 | AF13: =R13*C13 -> 0 | AG13: =T13*C13 -> 0 | AO13: 5 | AP13: =U13*B13 -> 0 | AQ13: =U13*C13 -> 0 | AR13: =AQ13-AP13 -> 0 | AS13: =X13*B13 -> 0
A14: 6 | D14: =C14-B14 -> 0 | F14: 0 | U14: =T14+R14+P14+N14+L14+J14+H14 -> 0 | X14: =F14+G14+I14+K14+M14+O14+Q14+S14-H14-J14-L14-N14-P14-R14-T14-V14-W14 -> 0 | Y14: =G14+I14+K14+M14+O14+Q14+S14 -> 0 | Z14: =Y14*B14 -> 0 | AA14: =H14*C14 -> 0 | AB14: =J14*C14 -> 0 | AC14: =L14*C14 -> 0 | AD14: =N14*C14 -> 0 | AE14: =P14*C14 -> 0 | AF14: =R14*C14 -> 0 | AG14: =T14*C14 -> 0 | AO14: 6 | AP14: =U14*B14 -> 0 | AQ14: =U14*C14 -> 0 | AR14: =AQ14-AP14 -> 0 | AS14: =X14*B14 -> 0
A15: 7 | B15: 220 | C15: 400 | D15: =C15-B15 -> 180 | E15: Cenicero diamante | F15: 0 | M15: 4 | N15: 2 | U15: =T15+R15+P15+N15+L15+J15+H15 -> 2 | X15: =F15+G15+I15+K15+M15+O15+Q15+S15-H15-J15-L15-N15-P15-R15-T15-V15-W15 -> 2 | Y15: =G15+I15+K15+M15+O15+Q15+S15 -> 4 | Z15: =Y15*B15 -> 880 | AA15: =H15*C15 -> 0 | AB15: =J15*C15 -> 0 | AC15: =L15*C15 -> 0 | AD15: =N15*C15 -> 800 | AE15: =P15*C15 -> 0 | AF15: =R15*C15 -> 0 | AG15: =T15*C15 -> 0 | AO15: 7 | AP15: =U15*B15 -> 440 | AQ15: =U15*C15 -> 800 | AR15: =AQ15-AP15 -> 360 | AS15: =X15*B15 -> 440
A16: 8 | B16: 120 | C16: 250 | D16: =C16-B16 -> 130 | E16: Cenicero chico | F16: 0 | U16: =T16+R16+P16+N16+L16+J16+H16 -> 0 | X16: =F16+G16+I16+K16+M16+O16+Q16+S16-H16-J16-L16-N16-P16-R16-T16-V16-W16 -> 0 | Y16: =G16+I16+K16+M16+O16+Q16+S16 -> 0 | Z16: =Y16*B16 -> 0 | AA16: =H16*C16 -> 0 | AB16: =J16*C16 -> 0 | AC16: =L16*C16 -> 0 | AD16: =N16*C16 -> 0 | AE16: =P16*C16 -> 0 | AF16: =R16*C16 -> 0 | AG16: =T16*C16 -> 0 | AO16: 9 | AP16: =U16*B16 -> 0 | AQ16: =U16*C16 -> 0 | AR16: =AQ16-AP16 -> 0 | AS16: =X16*B16 -> 0
A17: 9 | B17: 800 | C17: 1200 | D17: =C17-B17 -> 400 | E17: Cenicero cristal | F17: 0 | U17: =T17+R17+P17+N17+L17+J17+H17 -> 0 | X17: =F17+G17+I17+K17+M17+O17+Q17+S17-H17-J17-L17-N17-P17-R17-T17-V17-W17 -> 0 | Y17: =G17+I17+K17+M17+O17+Q17+S17 -> 0 | Z17: =Y17*B17 -> 0 | AA17: =H17*C17 -> 0 | AB17: =J17*C17 -> 0 | AC17: =L17*C17 -> 0 | AD17: =N17*C17 -> 0 | AE17: =P17*C17 -> 0 | AF17: =R17*C17 -> 0 | AG17: =T17*C17 -> 0 | AO17: 10 | AP17: =U17*B17 -> 0 | AQ17: =U17*C17 -> 0 | AR17: =AQ17-AP17 -> 0 | AS17: =X17*B17 -> 0
A18: 10 | B18: 300 | C18: 450 | D18: =C18-B18 -> 150 | E18: Huevos grandes | F18: 3 | J18: 1 | K18: 6 | N18: 1 | U18: =T18+R18+P18+N18+L18+J18+H18 -> 2 | X18: =F18+G18+I18+K18+M18+O18+Q18+S18-H18-J18-L18-N18-P18-R18-T18-V18-W18 -> 7 | Y18: =G18+I18+K18+M18+O18+Q18+S18 -> 6 | Z18: =Y18*B18 -> 1800 | AA18: =H18*C18 -> 0 | AB18: =J18*C18 -> 450 | AC18: =L18*C18 -> 0 | AD18: =N18*C18 -> 450 | AE18: =P18*C18 -> 0 | AF18: =R18*C18 -> 0 | AG18: =T18*C18 -> 0 | AO18: 11 | AP18: =U18*B18 -> 600 | AQ18: =U18*C18 -> 900 | AR18: =AQ18-AP18 -> 300 | AS18: =X18*B18 -> 2100
A19: 11 | B19: 200 | C19: 350 | D19: =C19-B19 -> 150 | E19: Huevos chicos | F19: 3 | K19: 6 | N19: 2 | U19: =T19+R19+P19+N19+L19+J19+H19 -> 2 | X19: =F19+G19+I19+K19+M19+O19+Q19+S19-H19-J19-L19-N19-P19-R19-T19-V19-W19 -> 7 | Y19: =G19+I19+K19+M19+O19+Q19+S19 -> 6 | Z19: =Y19*B19 -> 1200 | AA19: =H19*C19 -> 0 | AB19: =J19*C19 -> 0 | AC19: =L19*C19 -> 0 | AD19: =N19*C19 -> 700 | AE19: =P19*C19 -> 0 | AF19: =R19*C19 -> 0 | AG19: =T19*C19 -> 0 | AO19: 12 | AP19: =U19*B19 -> 400 | AQ19: =U19*C19 -> 700 | AR19: =AQ19-AP19 -> 300 | AS19: =X19*B19 -> 1400
A20: 12 | B20: 750 | C20: 1000 | D20: =C20-B20 -> 250 | E20: Manzana | F20: 2 | J20: 1 | K20: 13 | N20: 1 | T20: 1 | U20: =T20+R20+P20+N20+L20+J20+H20 -> 3 | X20: =F20+G20+I20+K20+M20+O20+Q20+S20-H20-J20-L20-N20-P20-R20-T20-V20-W20 -> 12 | Y20: =G20+I20+K20+M20+O20+Q20+S20 -> 13 | Z20: =Y20*B20 -> 9750 | AA20: =H20*C20 -> 0 | AB20: =J20*C20 -> 1000 | AC20: =L20*C20 -> 0 | AD20: =N20*C20 -> 1000 | AE20: =P20*C20 -> 0 | AF20: =R20*C20 -> 0 | AG20: =T20*C20 -> 1000 | AO20: 13 | AP20: =U20*B20 -> 2250 | AQ20: =U20*C20 -> 3000 | AR20: =AQ20-AP20 -> 750 | AS20: =X20*B20 -> 9000
A21: 13 | B21: 850 | C21: 1100 | D21: =C21-B21 -> 250 | E21: Manzana corazon | F21: 0 | U21: =T21+R21+P21+N21+L21+J21+H21 -> 0 | X21: =F21+G21+I21+K21+M21+O21+Q21+S21-H21-J21-L21-N21-P21-R21-T21-V21-W21 -> 0 | Y21: =G21+I21+K21+M21+O21+Q21+S21 -> 0 | Z21: =Y21*B21 -> 0 | AA21: =H21*C21 -> 0 | AB21: =J21*C21 -> 0 | AC21: =L21*C21 -> 0 | AD21: =N21*C21 -> 0 | AE21: =P21*C21 -> 0 | AF21: =R21*C21 -> 0 | AG21: =T21*C21 -> 0 | AO21: 14 | AP21: =U21*B21 -> 0 | AQ21: =U21*C21 -> 0 | AR21: =AQ21-AP21 -> 0 | AS21: =X21*B21 -> 0
A22: 14 | B22: 1200 | C22: 1500 | D22: =C22-B22 -> 300 | E22: Bucaro cuadrado | F22: 1 | U22: =T22+R22+P22+N22+L22+J22+H22 -> 0 | X22: =F22+G22+I22+K22+M22+O22+Q22+S22-H22-J22-L22-N22-P22-R22-T22-V22-W22 -> 1 | Y22: =G22+I22+K22+M22+O22+Q22+S22 -> 0 | Z22: =Y22*B22 -> 0 | AA22: =H22*C22 -> 0 | AB22: =J22*C22 -> 0 | AC22: =L22*C22 -> 0 | AD22: =N22*C22 -> 0 | AE22: =P22*C22 -> 0 | AF22: =R22*C22 -> 0 | AG22: =T22*C22 -> 0 | AO22: 15 | AP22: =U22*B22 -> 0 | AQ22: =U22*C22 -> 0 | AR22: =AQ22-AP22 -> 0 | AS22: =X22*B22 -> 1200
A23: 15 | B23: 1000 | C23: 1300 | D23: =C23-B23 -> 300 | E23: Bucaro cuadrado chico | F23: 1 | K23: 1 | N23: 1 | U23: =T23+R23+P23+N23+L23+J23+H23 -> 1 | X23: =F23+G23+I23+K23+M23+O23+Q23+S23-H23-J23-L23-N23-P23-R23-T23-V23-W23 -> 1 | Y23: =G23+I23+K23+M23+O23+Q23+S23 -> 1 | Z23: =Y23*B23 -> 1000 | AA23: =H23*C23 -> 0 | AB23: =J23*C23 -> 0 | AC23: =L23*C23 -> 0 | AD23: =N23*C23 -> 1300 | AE23: =P23*C23 -> 0 | AF23: =R23*C23 -> 0 | AG23: =T23*C23 -> 0 | AO23: 16 | AP23: =U23*B23 -> 1000 | AQ23: =U23*C23 -> 1300 | AR23: =AQ23-AP23 -> 300 | AS23: =X23*B23 -> 1000
A24: 16 | B24: 1300 | C24: 1600 | D24: =C24-B24 -> 300 | E24: Bucaro Redondo | F24: 4 | K24: 2 | P24: 1 | U24: =T24+R24+P24+N24+L24+J24+H24 -> 1 | X24: =F24+G24+I24+K24+M24+O24+Q24+S24-H24-J24-L24-N24-P24-R24-T24-V24-W24 -> 5 | Y24: =G24+I24+K24+M24+O24+Q24+S24 -> 2 | Z24: =Y24*B24 -> 2600 | AA24: =H24*C24 -> 0 | AB24: =J24*C24 -> 0 | AC24: =L24*C24 -> 0 | AD24: =N24*C24 -> 0 | AE24: =P24*C24 -> 1600 | AF24: =R24*C24 -> 0 | AG24: =T24*C24 -> 0 | AO24: 17 | AP24: =U24*B24 -> 1300 | AQ24: =U24*C24 -> 1600 | AR24: =AQ24-AP24 -> 300 | AS24: =X24*B24 -> 6500
A25: 17 | B25: 650 | C25: 800 | D25: =C25-B25 -> 150 | E25: Bucaro Chico | F25: 41 | K25: 3 | L25: 1 | N25: 3 | P25: 1 | U25: =T25+R25+P25+N25+L25+J25+H25 -> 5 | X25: =F25+G25+I25+K25+M25+O25+Q25+S25-H25-J25-L25-N25-P25-R25-T25-V25-W25 -> 39 | Y25: =G25+I25+K25+M25+O25+Q25+S25 -> 3 | Z25: =Y25*B25 -> 1950 | AA25: =H25*C25 -> 0 | AB25: =J25*C25 -> 0 | AC25: =L25*C25 -> 800 | AD25: =N25*C25 -> 2400 | AE25: =P25*C25 -> 800 | AF25: =R25*C25 -> 0 | AG25: =T25*C25 -> 0 | AO25: 18 | AP25: =U25*B25 -> 3250 | AQ25: =U25*C25 -> 4000 | AR25: =AQ25-AP25 -> 750 | AS25: =X25*B25 -> 25350
A26: 18 | B26: 800 | C26: 1000 | D26: =C26-B26 -> 200 | E26: Bucaro grande | F26: 3 | J26: 1 | U26: =T26+R26+P26+N26+L26+J26+H26 -> 1 | X26: =F26+G26+I26+K26+M26+O26+Q26+S26-H26-J26-L26-N26-P26-R26-T26-V26-W26 -> 2 | Y26: =G26+I26+K26+M26+O26+Q26+S26 -> 0 | Z26: =Y26*B26 -> 0 | AA26: =H26*C26 -> 0 | AB26: =J26*C26 -> 1000 | AC26: =L26*C26 -> 0 | AD26: =N26*C26 -> 0 | AE26: =P26*C26 -> 0 | AF26: =R26*C26 -> 0 | AG26: =T26*C26 -> 0 | AO26: 19 | AP26: =U26*B26 -> 800 | AQ26: =U26*C26 -> 1000 | AR26: =AQ26-AP26 -> 200 | AS26: =X26*B26 -> 1600
A27: 19 | B27: 1500 | C27: 1800 | D27: =C27-B27 -> 300 | E27: Bucaro Ovalado | F27: 2 | K27: 1 | U27: =T27+R27+P27+N27+L27+J27+H27 -> 0 | X27: =F27+G27+I27+K27+M27+O27+Q27+S27-H27-J27-L27-N27-P27-R27-T27-V27-W27 -> 3 | Y27: =G27+I27+K27+M27+O27+Q27+S27 -> 1 | Z27: =Y27*B27 -> 1500 | AA27: =H27*C27 -> 0 | AB27: =J27*C27 -> 0 | AC27: =L27*C27 -> 0 | AD27: =N27*C27 -> 0 | AE27: =P27*C27 -> 0 | AF27: =R27*C27 -> 0 | AG27: =T27*C27 -> 0 | AO27: 20 | AP27: =U27*B27 -> 0 | AQ27: =U27*C27 -> 0 | AR27: =AQ27-AP27 -> 0 | AS27: =X27*B27 -> 4500
A28: 20 | B28: 850 | C28: 1200 | D28: =C28-B28 -> 350 | E28: Bucaro redondo chico | F28: 11 | K28: 1 | L28: 1 | N28: 1 | U28: =T28+R28+P28+N28+L28+J28+H28 -> 2 | X28: =F28+G28+I28+K28+M28+O28+Q28+S28-H28-J28-L28-N28-P28-R28-T28-V28-W28 -> 10 | Y28: =G28+I28+K28+M28+O28+Q28+S28 -> 1 | Z28: =Y28*B28 -> 850 | AA28: =H28*C28 -> 0 | AB28: =J28*C28 -> 0 | AC28: =L28*C28 -> 1200 | AD28: =N28*C28 -> 1200 | AE28: =P28*C28 -> 0 | AF28: =R28*C28 -> 0 | AG28: =T28*C28 -> 0 | AO28: 21 | AP28: =U28*B28 -> 1700 | AQ28: =U28*C28 -> 2400 | AR28: =AQ28-AP28 -> 700 | AS28: =X28*B28 -> 8500
A29: 21 | B29: 800 | C29: 1200 | D29: =C29-B29 -> 400 | E29: Bucaro Luna chico | K29: 3 | U29: =T29+R29+P29+N29+L29+J29+H29 -> 0 | X29: =F29+G29+I29+K29+M29+O29+Q29+S29-H29-J29-L29-N29-P29-R29-T29-V29-W29 -> 3 | Y29: =G29+I29+K29+M29+O29+Q29+S29 -> 3 | Z29: =Y29*B29 -> 2400 | AA29: =H29*C29 -> 0 | AB29: =J29*C29 -> 0 | AC29: =L29*C29 -> 0 | AD29: =N29*C29 -> 0 | AE29: =P29*C29 -> 0 | AF29: =R29*C29 -> 0 | AG29: =T29*C29 -> 0 | AO29: 22 | AP29: =U29*B29 -> 0 | AQ29: =U29*C29 -> 0 | AR29: =AQ29-AP29 -> 0 | AS29: =X29*B29 -> 2400
A30: 22 | B30: 800 | C30: 1100 | D30: =C30-B30 -> 300 | E30: Bucaro Luna chico | F30: 2 | U30: =T30+R30+P30+N30+L30+J30+H30 -> 0 | X30: =F30+G30+I30+K30+M30+O30+Q30+S30-H30-J30-L30-N30-P30-R30-T30-V30-W30 -> 2 | Y30: =G30+I30+K30+M30+O30+Q30+S30 -> 0 | Z30: =Y30*B30 -> 0 | AA30: =H30*C30 -> 0 | AB30: =J30*C30 -> 0 | AC30: =L30*C30 -> 0 | AD30: =N30*C30 -> 0 | AE30: =P30*C30 -> 0 | AF30: =R30*C30 -> 0 | AG30: =T30*C30 -> 0 | AO30: 23 | AP30: =U30*B30 -> 0 | AQ30: =U30*C30 -> 0 | AR30: =AQ30-AP30 -> 0 | AS30: =X30*B30 -> 1600
A31: 23 | B31: 1000 | C31: 1300 | D31: =C31-B31 -> 300 | E31: Bucaro Luna | F31: 1 | U31: =T31+R31+P31+N31+L31+J31+H31 -> 0 | X31: =F31+G31+I31+K31+M31+O31+Q31+S31-H31-J31-L31-N31-P31-R31-T31-V31-W31 -> 1 | Y31: =G31+I31+K31+M31+O31+Q31+S31 -> 0 | Z31: =Y31*B31 -> 0 | AA31: =H31*C31 -> 0 | AB31: =J31*C31 -> 0 | AC31: =L31*C31 -> 0 | AD31: =N31*C31 -> 0 | AE31: =P31*C31 -> 0 | AF31: =R31*C31 -> 0 | AG31: =T31*C31 -> 0 | AO31: 24 | AP31: =U31*B31 -> 0 | AQ31: =U31*C31 -> 0 | AR31: =AQ31-AP31 -> 0 | AS31: =X31*B31 -> 1000
A32: 24 | B32: 1500 | C32: 2000 | D32: 500 | E32: Bucaro alto | F32: 1 | U32: =T32+R32+P32+N32+L32+J32+H32 -> 0 | X32: =F32+G32+I32+K32+M32+O32+Q32+S32-H32-J32-L32-N32-P32-R32-T32-V32-W32 -> 1 | Y32: =G32+I32+K32+M32+O32+Q32+S32 -> 0 | Z32: =Y32*B32 -> 0 | AA32: =H32*C32 -> 0 | AB32: =J32*C32 -> 0 | AC32: =L32*C32 -> 0 | AD32: =N32*C32 -> 0 | AE32: =P32*C32 -> 0 | AF32: =R32*C32 -> 0 | AG32: =T32*C32 -> 0 | AO32: 25 | AP32: =U32*B32 -> 0 | AQ32: =U32*C32 -> 0 | AR32: =AQ32-AP32 -> 0 | AS32: =X32*B32 -> 1500
A33: 25 | B33: 1100 | C33: 1600 | D33: =C33-B33 -> 500 | E33: Juego 3 bolas | F33: 0 | K33: 4 | U33: =T33+R33+P33+N33+L33+J33+H33 -> 0 | X33: =F33+G33+I33+K33+M33+O33+Q33+S33-H33-J33-L33-N33-P33-R33-T33-V33-W33 -> 4 | Y33: =G33+I33+K33+M33+O33+Q33+S33 -> 4 | Z33: =Y33*B33 -> 4400 | AA33: =H33*C33 -> 0 | AB33: =J33*C33 -> 0 | AC33: =L33*C33 -> 0 | AD33: =N33*C33 -> 0 | AE33: =P33*C33 -> 0 | AF33: =R33*C33 -> 0 | AG33: =T33*C33 -> 0 | AO33: 26 | AP33: =U33*B33 -> 0 | AQ33: =U33*C33 -> 0 | AR33: =AQ33-AP33 -> 0 | AS33: =X33*B33 -> 4400
A34: 26 | B34: 300 | C34: 500 | D34: 200 | E34: Plumeros | K34: 8 | N34: 6 | U34: =T34+R34+P34+N34+L34+J34+H34 -> 6 | X34: =F34+G34+I34+K34+M34+O34+Q34+S34-H34-J34-L34-N34-P34-R34-T34-V34-W34 -> 2 | Y34: =G34+I34+K34+M34+O34+Q34+S34 -> 8 | Z34: =Y34*B34 -> 2400 | AA34: =H34*C34 -> 0 | AB34: =J34*C34 -> 0 | AC34: =L34*C34 -> 0 | AD34: =N34*C34 -> 3000 | AE34: =P34*C34 -> 0 | AF34: =R34*C34 -> 0 | AG34: =T34*C34 -> 0 | AO34: 27 | AP34: =U34*B34 -> 1800 | AQ34: =U34*C34 -> 3000 | AR34: =AQ34-AP34 -> 1200 | AS34: =X34*B34 -> 600
A35: 27 | B35: 350 | C35: 500 | D35: =C35-B35 -> 150 | E35: osos | F35: 1 | K35: 4 | U35: =T35+R35+P35+N35+L35+J35+H35 -> 0 | X35: =F35+G35+I35+K35+M35+O35+Q35+S35-H35-J35-L35-N35-P35-R35-T35-V35-W35 -> 5 | Y35: =G35+I35+K35+M35+O35+Q35+S35 -> 4 | Z35: =Y35*B35 -> 1400 | AA35: =H35*C35 -> 0 | AB35: =J35*C35 -> 0 | AC35: =L35*C35 -> 0 | AD35: =N35*C35 -> 0 | AE35: =P35*C35 -> 0 | AF35: =R35*C35 -> 0 | AG35: =T35*C35 -> 0 | AO35: 28 | AP35: =U35*B35 -> 0 | AQ35: =U35*C35 -> 0 | AR35: =AQ35-AP35 -> 0 | AS35: =X35*B35 -> 1750
A36: 28 | B36: 120 | C36: 200 | D36: =C36-B36 -> 80 | E36: Ranitas | F36: 0 | U36: =T36+R36+P36+N36+L36+J36+H36 -> 0 | X36: =F36+G36+I36+K36+M36+O36+Q36+S36-H36-J36-L36-N36-P36-R36-T36-V36-W36 -> 0 | Y36: =G36+I36+K36+M36+O36+Q36+S36 -> 0 | Z36: =Y36*B36 -> 0 | AA36: =H36*C36 -> 0 | AB36: =J36*C36 -> 0 | AC36: =L36*C36 -> 0 | AD36: =N36*C36 -> 0 | AE36: =P36*C36 -> 0 | AF36: =R36*C36 -> 0 | AG36: =T36*C36 -> 0 | AO36: 29 | AP36: =U36*B36 -> 0 | AQ36: =U36*C36 -> 0 | AR36: =AQ36-AP36 -> 0 | AS36: =X36*B36 -> 0
A37: 29 | B37: 350 | C37: 500 | D37: =C37-B37 -> 150 | E37: Gallina | F37: 0 | U37: =T37+R37+P37+N37+L37+J37+H37 -> 0 | X37: =F37+G37+I37+K37+M37+O37+Q37+S37-H37-J37-L37-N37-P37-R37-T37-V37-W37 -> 0 | Y37: =G37+I37+K37+M37+O37+Q37+S37 -> 0 | Z37: =Y37*B37 -> 0 | AA37: =H37*C37 -> 0 | AB37: =J37*C37 -> 0 | AC37: =L37*C37 -> 0 | AD37: =N37*C37 -> 0 | AE37: =P37*C37 -> 0 | AF37: =R37*C37 -> 0 | AG37: =T37*C37 -> 0 | AO37: 30 | AP37: =U37*B37 -> 0 | AQ37: =U37*C37 -> 0 | AR37: =AQ37-AP37 -> 0 | AS37: =X37*B37 -> 0
A38: 30 | B38: 350 | C38: 500 | D38: =C38-B38 -> 150 | E38: Conejo | F38: 0 | K38: 1 | N38: 1 | U38: =T38+R38+P38+N38+L38+J38+H38 -> 1 | X38: =F38+G38+I38+K38+M38+O38+Q38+S38-H38-J38-L38-N38-P38-R38-T38-V38-W38 -> 0 | Y38: =G38+I38+K38+M38+O38+Q38+S38 -> 1 | Z38: =Y38*B38 -> 350 | AA38: =H38*C38 -> 0 | AB38: =J38*C38 -> 0 | AC38: =L38*C38 -> 0 | AD38: =N38*C38 -> 500 | AE38: =P38*C38 -> 0 | AF38: =R38*C38 -> 0 | AG38: =T38*C38 -> 0 | AO38: 31 | AP38: =U38*B38 -> 350 | AQ38: =U38*C38 -> 500 | AR38: =AQ38-AP38 -> 150 | AS38: =X38*B38 -> 0
A39: 31 | B39: 350 | C39: 500 | D39: =C39-B39 -> 150 | E39: Pajaro | F39: 0 | K39: 4 | N39: 2 | U39: =T39+R39+P39+N39+L39+J39+H39 -> 2 | X39: =F39+G39+I39+K39+M39+O39+Q39+S39-H39-J39-L39-N39-P39-R39-T39-V39-W39 -> 2 | Y39: =G39+I39+K39+M39+O39+Q39+S39 -> 4 | Z39: =Y39*B39 -> 1400 | AA39: =H39*C39 -> 0 | AB39: =J39*C39 -> 0 | AC39: =L39*C39 -> 0 | AD39: =N39*C39 -> 1000 | AE39: =P39*C39 -> 0 | AF39: =R39*C39 -> 0 | AG39: =T39*C39 -> 0 | AO39: 32 | AP39: =U39*B39 -> 700 | AQ39: =U39*C39 -> 1000 | AR39: =AQ39-AP39 -> 300 | AS39: =X39*B39 -> 700
A40: 32 | B40: 1700 | C40: 2500 | D40: =C40-B40 -> 800 | E40: Pareja | F40: 0 | U40: =T40+R40+P40+N40+L40+J40+H40 -> 0 | X40: =F40+G40+I40+K40+M40+O40+Q40+S40-H40-J40-L40-N40-P40-R40-T40-V40-W40 -> 0 | Y40: =G40+I40+K40+M40+O40+Q40+S40 -> 0 | Z40: =Y40*B40 -> 0 | AA40: =H40*C40 -> 0 | AB40: =J40*C40 -> 0 | AC40: =L40*C40 -> 0 | AD40: =N40*C40 -> 0 | AE40: =P40*C40 -> 0 | AF40: =R40*C40 -> 0 | AG40: =T40*C40 -> 0 | AO40: 33 | AP40: =U40*B40 -> 0 | AQ40: =U40*C40 -> 0 | AR40: =AQ40-AP40 -> 0 | AS40: =X40*B40 -> 0
A41: 33 | B41: 750 | C41: 1100 | D41: =C41-B41 -> 350 | E41: Calabaza | F41: 0 | U41: =T41+R41+P41+N41+L41+J41+H41 -> 0 | X41: =F41+G41+I41+K41+M41+O41+Q41+S41-H41-J41-L41-N41-P41-R41-T41-V41-W41 -> 0 | Y41: =G41+I41+K41+M41+O41+Q41+S41 -> 0 | Z41: =Y41*B41 -> 0 | AA41: =H41*C41 -> 0 | AB41: =J41*C41 -> 0 | AC41: =L41*C41 -> 0 | AD41: =N41*C41 -> 0 | AE41: =P41*C41 -> 0 | AF41: =R41*C41 -> 0 | AG41: =T41*C41 -> 0 | AO41: 34 | AP41: =U41*B41 -> 0 | AQ41: =U41*C41 -> 0 | AR41: =AQ41-AP41 -> 0 | AS41: =X41*B41 -> 0
A42: 34 | B42: 800 | C42: 1000 | D42: =C42-B42 -> 200 | E42: Elefante chico | F42: 0 | U42: =T42+R42+P42+N42+L42+J42+H42 -> 0 | X42: =F42+G42+I42+K42+M42+O42+Q42+S42-H42-J42-L42-N42-P42-R42-T42-V42-W42 -> 0 | Y42: =G42+I42+K42+M42+O42+Q42+S42 -> 0 | Z42: =Y42*B42 -> 0 | AA42: =H42*C42 -> 0 | AB42: =J42*C42 -> 0 | AC42: =L42*C42 -> 0 | AD42: =N42*C42 -> 0 | AE42: =P42*C42 -> 0 | AF42: =R42*C42 -> 0 | AG42: =T42*C42 -> 0 | AO42: 35 | AP42: =U42*B42 -> 0 | AQ42: =U42*C42 -> 0 | AR42: =AQ42-AP42 -> 0 | AS42: =X42*B42 -> 0
A43: 35 | B43: 1000 | C43: 1300 | D43: =C43-B43 -> 300 | E43: Elefante Grande | F43: 0 | U43: =T43+R43+P43+N43+L43+J43+H43 -> 0 | X43: =F43+G43+I43+K43+M43+O43+Q43+S43-H43-J43-L43-N43-P43-R43-T43-V43-W43 -> 0 | Y43: =G43+I43+K43+M43+O43+Q43+S43 -> 0 | Z43: =Y43*B43 -> 0 | AA43: =H43*C43 -> 0 | AB43: =J43*C43 -> 0 | AC43: =L43*C43 -> 0 | AD43: =N43*C43 -> 0 | AE43: =P43*C43 -> 0 | AF43: =R43*C43 -> 0 | AG43: =T43*C43 -> 0 | AO43: 36 | AP43: =U43*B43 -> 0 | AQ43: =U43*C43 -> 0 | AR43: =AQ43-AP43 -> 0 | AS43: =X43*B43 -> 0
A44: 36 | U44: =T44+R44+P44+N44+L44+J44+H44 -> 0 | X44: =F44+G44+I44+K44+M44+O44+Q44+S44-H44-J44-L44-N44-P44-R44-T44-V44-W44 -> 0 | Y44: =G44+I44+K44+M44+O44+Q44+S44 -> 0 | Z44: =Y44*B44 -> 0 | AA44: =H44*C44 -> 0 | AB44: =J44*C44 -> 0 | AC44: =L44*C44 -> 0 | AD44: =N44*C44 -> 0 | AE44: =P44*C44 -> 0 | AF44: =R44*C44 -> 0 | AG44: =T44*C44 -> 0 | AO44: 37 | AP44: =U44*B44 -> 0 | AQ44: =U44*C44 -> 0 | AR44: =AQ44-AP44 -> 0 | AS44: =X44*B44 -> 0
A45: 37 | U45: =T45+R45+P45+N45+L45+J45+H45 -> 0 | X45: =F45+G45+I45+K45+M45+O45+Q45+S45-H45-J45-L45-N45-P45-R45-T45-V45-W45 -> 0 | Y45: =G45+I45+K45+M45+O45+Q45+S45 -> 0 | Z45: =Y45*B45 -> 0 | AA45: =H45*C45 -> 0 | AB45: =J45*C45 -> 0 | AC45: =L45*C45 -> 0 | AD45: =N45*C45 -> 0 | AE45: =P45*C45 -> 0 | AF45: =R45*C45 -> 0 | AG45: =T45*C45 -> 0 | AO45: 38 | AP45: =U45*B45 -> 0 | AQ45: =U45*C45 -> 0 | AR45: =AQ45-AP45 -> 0 | AS45: =X45*B45 -> 0
A46: 38 | U46: =T46+R46+P46+N46+L46+J46+H46 -> 0 | X46: =F46+G46+I46+K46+M46+O46+Q46+S46-H46-J46-L46-N46-P46-R46-T46-V46-W46 -> 0 | Y46: =G46+I46+K46+M46+O46+Q46+S46 -> 0 | Z46: =Y46*B46 -> 0 | AA46: =H46*C46 -> 0 | AB46: =J46*C46 -> 0 | AC46: =L46*C46 -> 0 | AD46: =N46*C46 -> 0 | AE46: =P46*C46 -> 0 | AF46: =R46*C46 -> 0 | AG46: =T46*C46 -> 0 | AO46: 39 | AP46: =U46*B46 -> 0 | AQ46: =U46*C46 -> 0 | AR46: =AQ46-AP46 -> 0 | AS46: =X46*B46 -> 0
A47: 39 | U47: =T47+R47+P47+N47+L47+J47+H47 -> 0 | X47: =F47+G47+I47+K47+M47+O47+Q47+S47-H47-J47-L47-N47-P47-R47-T47-V47-W47 -> 0 | Y47: =G47+I47+K47+M47+O47+Q47+S47 -> 0 | Z47: =Y47*B47 -> 0 | AA47: =H47*C47 -> 0 | AB47: =J47*C47 -> 0 | AC47: =L47*C47 -> 0 | AD47: =N47*C47 -> 0 | AE47: =P47*C47 -> 0 | AF47: =R47*C47 -> 0 | AG47: =T47*C47 -> 0 | AO47: 40 | AP47: =U47*B47 -> 0 | AQ47: =U47*C47 -> 0 | AR47: =AQ47-AP47 -> 0 | AS47: =X47*B47 -> 0
A48: 40 | U48: =T48+R48+P48+N48+L48+J48+H48 -> 0 | X48: =F48+G48+I48+K48+M48+O48+Q48+S48-H48-J48-L48-N48-P48-R48-T48-V48-W48 -> 0 | Y48: =G48+I48+K48+M48+O48+Q48+S48 -> 0 | Z48: =Y48*B48 -> 0 | AA48: =H48*C48 -> 0 | AB48: =J48*C48 -> 0 | AC48: =L48*C48 -> 0 | AD48: =N48*C48 -> 0 | AE48: =P48*C48 -> 0 | AF48: =R48*C48 -> 0 | AG48: =T48*C48 -> 0 | AO48: 41 | AP48: =U48*B48 -> 0 | AQ48: =U48*C48 -> 0 | AR48: =AQ48-AP48 -> 0 | AS48: =X48*B48 -> 0
A49: 41 | U49: =T49+R49+P49+N49+L49+J49+H49 -> 0 | X49: =F49+G49+I49+K49+M49+O49+Q49+S49-H49-J49-L49-N49-P49-R49-T49-V49-W49 -> 0 | Y49: =G49+I49+K49+M49+O49+Q49+S49 -> 0 | Z49: =Y49*B49 -> 0 | AA49: =H49*C49 -> 0 | AB49: =J49*C49 -> 0 | AC49: =L49*C49 -> 0 | AD49: =N49*C49 -> 0 | AE49: =P49*C49 -> 0 | AF49: =R49*C49 -> 0 | AG49: =T49*C49 -> 0 | AO49: 42 | AP49: =U49*B49 -> 0 | AQ49: =U49*C49 -> 0 | AR49: =AQ49-AP49 -> 0 | AS49: =X49*B49 -> 0
A50: 42 | U50: =T50+R50+P50+N50+L50+J50+H50 -> 0 | X50: =F50+G50+I50+K50+M50+O50+Q50+S50-H50-J50-L50-N50-P50-R50-T50-V50-W50 -> 0 | Y50: =G50+I50+K50+M50+O50+Q50+S50 -> 0 | Z50: =Y50*B50 -> 0 | AA50: =H50*C50 -> 0 | AB50: =J50*C50 -> 0 | AC50: =L50*C50 -> 0 | AD50: =N50*C50 -> 0 | AE50: =P50*C50 -> 0 | AF50: =R50*C50 -> 0 | AG50: =T50*C50 -> 0 | AO50: 43 | AP50: =U50*B50 -> 0 | AQ50: =U50*C50 -> 0 | AR50: =AQ50-AP50 -> 0 | AS50: =X50*B50 -> 0
A51: 43 | U51: =T51+R51+P51+N51+L51+J51+H51 -> 0 | X51: =F51+G51+I51+K51+M51+O51+Q51+S51-H51-J51-L51-N51-P51-R51-T51-V51-W51 -> 0 | Y51: =G51+I51+K51+M51+O51+Q51+S51 -> 0 | Z51: =Y51*B51 -> 0 | AA51: =H51*C51 -> 0 | AB51: =J51*C51 -> 0 | AC51: =L51*C51 -> 0 | AD51: =N51*C51 -> 0 | AE51: =P51*C51 -> 0 | AF51: =R51*C51 -> 0 | AG51: =T51*C51 -> 0 | AO51: 44 | AP51: =U51*B51 -> 0 | AQ51: =U51*C51 -> 0 | AR51: =AQ51-AP51 -> 0 | AS51: =X51*B51 -> 0
A52: 44 | U52: =T52+R52+P52+N52+L52+J52+H52 -> 0 | X52: =F52+G52+I52+K52+M52+O52+Q52+S52-H52-J52-L52-N52-P52-R52-T52-V52-W52 -> 0 | Y52: =G52+I52+K52+M52+O52+Q52+S52 -> 0 | Z52: =Y52*B52 -> 0 | AA52: =H52*C52 -> 0 | AB52: =J52*C52 -> 0 | AC52: =L52*C52 -> 0 | AD52: =N52*C52 -> 0 | AE52: =P52*C52 -> 0 | AF52: =R52*C52 -> 0 | AG52: =T52*C52 -> 0 | AO52: 45 | AP52: =U52*B52 -> 0 | AQ52: =U52*C52 -> 0 | AR52: =AQ52-AP52 -> 0 | AS52: =X52*B52 -> 0
A53: 45 | U53: =T53+R53+P53+N53+L53+J53+H53 -> 0 | X53: =F53+G53+I53+K53+M53+O53+Q53+S53-H53-J53-L53-N53-P53-R53-T53-V53-W53 -> 0 | Y53: =G53+I53+K53+M53+O53+Q53+S53 -> 0 | Z53: =Y53*B53 -> 0 | AA53: =H53*C53 -> 0 | AB53: =J53*C53 -> 0 | AC53: =L53*C53 -> 0 | AD53: =N53*C53 -> 0 | AE53: =P53*C53 -> 0 | AF53: =R53*C53 -> 0 | AG53: =T53*C53 -> 0 | AO53: 46 | AP53: =U53*B53 -> 0 | AQ53: =U53*C53 -> 0 | AR53: =AQ53-AP53 -> 0 | AS53: =X53*B53 -> 0
A54: 46 | U54: =T54+R54+P54+N54+L54+J54+H54 -> 0 | X54: =F54+G54+I54+K54+M54+O54+Q54+S54-H54-J54-L54-N54-P54-R54-T54-V54-W54 -> 0 | Y54: =G54+I54+K54+M54+O54+Q54+S54 -> 0 | Z54: =Y54*B54 -> 0 | AA54: =H54*C54 -> 0 | AB54: =J54*C54 -> 0 | AC54: =L54*C54 -> 0 | AD54: =N54*C54 -> 0 | AE54: =P54*C54 -> 0 | AF54: =R54*C54 -> 0 | AG54: =T54*C54 -> 0 | AO54: 47 | AP54: =U54*B54 -> 0 | AQ54: =U54*C54 -> 0 | AR54: =AQ54-AP54 -> 0 | AS54: =X54*B54 -> 0
A55: 47 | U55: =T55+R55+P55+N55+L55+J55+H55 -> 0 | X55: =F55+G55+I55+K55+M55+O55+Q55+S55-H55-J55-L55-N55-P55-R55-T55-V55-W55 -> 0 | Y55: =G55+I55+K55+M55+O55+Q55+S55 -> 0 | Z55: =Y55*B55 -> 0 | AA55: =H55*C55 -> 0 | AB55: =J55*C55 -> 0 | AC55: =L55*C55 -> 0 | AD55: =N55*C55 -> 0 | AE55: =P55*C55 -> 0 | AF55: =R55*C55 -> 0 | AG55: =T55*C55 -> 0 | AO55: 48 | AP55: =U55*B55 -> 0 | AQ55: =U55*C55 -> 0 | AR55: =AQ55-AP55 -> 0 | AS55: =X55*B55 -> 0
... A59: 51 | U59: =T59+R59+P59+N59+L59+J59+H59 -> 0 | X59: =F59+G59+I59+K59+M59+O59+Q59+S59-H59-J59-L59-N59-P59-R59-T59-V59-W59 -> 0 | Y59: =G59+I59+K59+M59+O59+Q59+S59 -> 0 | Z59: =Y59*B59 -> 0 | AA59: =H59*C59 -> 0 | AB59: =J59*C59 -> 0 | AC59: =L59*C59 -> 0 | AD59: =N59*C59 -> 0 | AE59: =P59*C59 -> 0 | AF59: =R59*C59 -> 0 | AG59: =T59*C59 -> 0 | AO59: 52 | AP59: =U59*B59 -> 0 | AQ59: =U59*C59 -> 0 | AR59: =AQ59-AP59 -> 0 | AS59: =X59*B59 -> 0
A60: 52 | U60: =T60+R60+P60+N60+L60+J60+H60 -> 0 | X60: =F60+G60+I60+K60+M60+O60+Q60+S60-H60-J60-L60-N60-P60-R60-T60-V60-W60 -> 0 | Y60: =G60+I60+K60+M60+O60+Q60+S60 -> 0 | Z60: =Y60*B60 -> 0 | AA60: =H60*C60 -> 0 | AB60: =J60*C60 -> 0 | AC60: =L60*C60 -> 0 | AD60: =N60*C60 -> 0 | AE60: =P60*C60 -> 0 | AF60: =R60*C60 -> 0 | AG60: =T60*C60 -> 0
A61: 53 | U61: =T61+R61+P61+N61+L61+J61+H61 -> 0 | X61: =F61+G61+I61+K61+M61+O61+Q61+S61-H61-J61-L61-N61-P61-R61-T61-V61-W61 -> 0 | Y61: =G61+I61+K61+M61+O61+Q61+S61 -> 0 | Z61: =Y61*B61 -> 0 | AA61: =H61*C61 -> 0 | AB61: =J61*C61 -> 0 | AC61: =L61*C61 -> 0 | AD61: =N61*C61 -> 0 | AE61: =P61*C61 -> 0 | AF61: =R61*C61 -> 0 | AG61: =T61*C61 -> 0
A62: 54 | U62: =T62+R62+P62+N62+L62+J62+H62 -> 0 | X62: =F62+G62+I62+K62+M62+O62+Q62+S62-H62-J62-L62-N62-P62-R62-T62-V62-W62 -> 0 | Y62: =G62+I62+K62+M62+O62+Q62+S62 -> 0 | Z62: =Y62*B62 -> 0 | AA62: =H62*C62 -> 0 | AB62: =J62*C62 -> 0 | AC62: =L62*C62 -> 0 | AD62: =N62*C62 -> 0 | AE62: =P62*C62 -> 0 | AF62: =R62*C62 -> 0 | AG62: =T62*C62 -> 0
A63: 55 | U63: =T63+R63+P63+N63+L63+J63+H63 -> 0 | X63: =F63+G63+I63+K63+M63+O63+Q63+S63-H63-J63-L63-N63-P63-R63-T63-V63-W63 -> 0 | Y63: =G63+I63+K63+M63+O63+Q63+S63 -> 0 | Z63: =Y63*B63 -> 0 | AA63: =H63*C63 -> 0 | AB63: =J63*C63 -> 0 | AC63: =L63*C63 -> 0 | AD63: =N63*C63 -> 0 | AE63: =P63*C63 -> 0 | AF63: =R63*C63 -> 0 | AG63: =T63*C63 -> 0
A64: 56 | U64: =T64+R64+P64+N64+L64+J64+H64 -> 0 | X64: =F64+G64+I64+K64+M64+O64+Q64+S64-H64-J64-L64-N64-P64-R64-T64-V64-W64 -> 0 | Y64: =G64+I64+K64+M64+O64+Q64+S64 -> 0 | Z64: =Y64*B64 -> 0 | AA64: =H64*C64 -> 0 | AB64: =J64*C64 -> 0 | AC64: =L64*C64 -> 0 | AD64: =N64*C64 -> 0 | AE64: =P64*C64 -> 0 | AF64: =R64*C64 -> 0 | AG64: =T64*C64 -> 0
A65: 57 | U65: =T65+R65+P65+N65+L65+J65+H65 -> 0 | X65: =F65+G65+I65+K65+M65+O65+Q65+S65-H65-J65-L65-N65-P65-R65-T65-V65-W65 -> 0 | Y65: =G65+I65+K65+M65+O65+Q65+S65 -> 0 | Z65: =Y65*B65 -> 0 | AA65: =H65*C65 -> 0 | AB65: =J65*C65 -> 0 | AC65: =L65*C65 -> 0 | AD65: =N65*C65 -> 0 | AE65: =P65*C65 -> 0 | AF65: =R65*C65 -> 0 | AG65: =T65*C65 -> 0
A66: 58 | U66: =T66+R66+P66+N66+L66+J66+H66 -> 0 | X66: =F66+G66+I66+K66+M66+O66+Q66+S66-H66-J66-L66-N66-P66-R66-T66-V66-W66 -> 0 | Y66: =G66+I66+K66+M66+O66+Q66+S66 -> 0 | Z66: =Y66*B66 -> 0 | AA66: =H66*C66 -> 0 | AB66: =J66*C66 -> 0 | AC66: =L66*C66 -> 0 | AD66: =N66*C66 -> 0 | AE66: =P66*C66 -> 0 | AF66: =R66*C66 -> 0 | AG66: =T66*C66 -> 0
A67: 59 | U67: =T67+R67+P67+N67+L67+J67+H67 -> 0 | X67: =F67+G67+I67+K67+M67+O67+Q67+S67-H67-J67-L67-N67-P67-R67-T67-V67-W67 -> 0 | Y67: =G67+I67+K67+M67+O67+Q67+S67 -> 0 | Z67: =Y67*B67 -> 0 | AA67: =H67*C67 -> 0 | AB67: =J67*C67 -> 0 | AC67: =L67*C67 -> 0 | AD67: =N67*C67 -> 0 | AE67: =P67*C67 -> 0 | AF67: =R67*C67 -> 0 | AG67: =T67*C67 -> 0
A68: 60 | U68: =T68+R68+P68+N68+L68+J68+H68 -> 0 | X68: =F68+G68+I68+K68+M68+O68+Q68+S68-H68-J68-L68-N68-P68-R68-T68-V68-W68 -> 0 | Y68: =G68+I68+K68+M68+O68+Q68+S68 -> 0 | Z68: =Y68*B68 -> 0 | AA68: =H68*C68 -> 0 | AB68: =J68*C68 -> 0 | AC68: =L68*C68 -> 0 | AD68: =N68*C68 -> 0 | AE68: =P68*C68 -> 0 | AF68: =R68*C68 -> 0 | AG68: =T68*C68 -> 0
A69: 61 | U69: =T69+R69+P69+N69+L69+J69+H69 -> 0 | X69: =F69+G69+I69+K69+M69+O69+Q69+S69-H69-J69-L69-N69-P69-R69-T69-V69-W69 -> 0 | Y69: =G69+I69+K69+M69+O69+Q69+S69 -> 0 | Z69: =Y69*B69 -> 0 | AA69: =H69*C69 -> 0 | AB69: =J69*C69 -> 0 | AC69: =L69*C69 -> 0 | AD69: =N69*C69 -> 0 | AE69: =P69*C69 -> 0 | AF69: =R69*C69 -> 0 | AG69: =T69*C69 -> 0
A70: 62 | U70: =T70+R70+P70+N70+L70+J70+H70 -> 0 | X70: =F70+G70+I70+K70+M70+O70+Q70+S70-H70-J70-L70-N70-P70-R70-T70-V70-W70 -> 0 | Y70: =G70+I70+K70+M70+O70+Q70+S70 -> 0 | Z70: =Y70*B70 -> 0 | AA70: =H70*C70 -> 0 | AB70: =J70*C70 -> 0 | AC70: =L70*C70 -> 0 | AD70: =N70*C70 -> 0 | AE70: =P70*C70 -> 0 | AF70: =R70*C70 -> 0 | AG70: =T70*C70 -> 0
A71: 63 | U71: =T71+R71+P71+N71+L71+J71+H71 -> 0 | X71: =F71+G71+I71+K71+M71+O71+Q71+S71-H71-J71-L71-N71-P71-R71-T71-V71-W71 -> 0 | Y71: =G71+I71+K71+M71+O71+Q71+S71 -> 0 | Z71: =Y71*B71 -> 0 | AA71: =H71*C71 -> 0 | AB71: =J71*C71 -> 0 | AC71: =L71*C71 -> 0 | AD71: =N71*C71 -> 0 | AE71: =P71*C71 -> 0 | AF71: =R71*C71 -> 0 | AG71: =T71*C71 -> 0
... A140: 132 | U140: =T140+R140+P140+N140+L140+J140+H140 -> 0 | X140: =F140+G140+I140+K140+M140+O140+Q140+S140-H140-J140-L140-N140-P140-R140-T140-V140-W140 -> 0 | Y140: =G140+I140+K140+M140+O140+Q140+S140 -> 0 | Z140: =Y140*B140 -> 0 | AA140: =H140*C140 -> 0 | AB140: =J140*C140 -> 0 | AC140: =L140*C140 -> 0 | AD140: =N140*C140 -> 0 | AE140: =P140*C140 -> 0 | AF140: =R140*C140 -> 0 | AG140: =T140*C140 -> 0
A141: 133 | U141: =T141+R141+P141+N141+L141+J141+H141 -> 0 | X141: =F141+G141+I141+K141+M141+O141+Q141+S141-H141-J141-L141-N141-P141-R141-T141-W141 -> 0 | Y141: =G141+I141+K141+M141+O141+Q141+S141 -> 0 | Z141: =Y141*B141 -> 0 | AA141: =H141*C141 -> 0 | AB141: =J141*C141 -> 0 | AC141: =L141*C141 -> 0 | AD141: =N141*C141 -> 0 | AE141: =P141*C141 -> 0 | AF141: =R141*C141 -> 0 | AG141: =T141*C141 -> 0
A142: 134 | U142: =T142+R142+P142+N142+L142+J142+H142 -> 0 | X142: =F142+G142+I142+K142+M142+O142+Q142+S142-H142-J142-L142-N142-P142-R142-T142-W142 -> 0 | Y142: =G142+I142+K142+M142+O142+Q142+S142 -> 0 | Z142: =Y142*B142 -> 0 | AA142: =H142*C142 -> 0 | AB142: =J142*C142 -> 0 | AC142: =L142*C142 -> 0 | AD142: =N142*C142 -> 0 | AE142: =P142*C142 -> 0 | AF142: =R142*C142 -> 0 | AG142: =T142*C142 -> 0
A143: 135 | U143: =T143+R143+P143+N143+L143+J143+H143 -> 0 | X143: =F143+G143+I143+K143+M143+O143+Q143+S143-H143-J143-L143-N143-P143-R143-T143-W143 -> 0 | Y143: =G143+I143+K143+M143+O143+Q143+S143 -> 0 | Z143: =Y143*B143 -> 0 | AA143: =H143*C143 -> 0 | AB143: =J143*C143 -> 0 | AC143: =L143*C143 -> 0 | AD143: =N143*C143 -> 0 | AE143: =P143*C143 -> 0 | AF143: =R143*C143 -> 0 | AG143: =T143*C143 -> 0
A144: 136 | U144: =T144+R144+P144+N144+L144+J144+H144 -> 0 | X144: =F144+G144+I144+K144+M144+O144+Q144+S144-H144-J144-L144-N144-P144-R144-T144-W144 -> 0 | Y144: =G144+I144+K144+M144+O144+Q144+S144 -> 0 | Z144: =Y144*B144 -> 0 | AA144: =H144*C144 -> 0 | AB144: =J144*C144 -> 0 | AC144: =L144*C144 -> 0 | AD144: =N144*C144 -> 0 | AE144: =P144*C144 -> 0 | AF144: =R144*C144 -> 0 | AG144: =T144*C144 -> 0
A145: 137 | U145: =T145+R145+P145+N145+L145+J145+H145 -> 0 | X145: =F145+G145+I145+K145+M145+O145+Q145+S145-H145-J145-L145-N145-P145-R145-T145-W145 -> 0 | Y145: =G145+I145+K145+M145+O145+Q145+S145 -> 0 | Z145: =Y145*B145 -> 0 | AA145: =H145*C145 -> 0 | AB145: =J145*C145 -> 0 | AC145: =L145*C145 -> 0 | AD145: =N145*C145 -> 0 | AE145: =P145*C145 -> 0 | AF145: =R145*C145 -> 0 | AG145: =T145*C145 -> 0
A146: 138 | U146: =T146+R146+P146+N146+L146+J146+H146 -> 0 | X146: =F146+G146+I146+K146+M146+O146+Q146+S146-H146-J146-L146-N146-P146-R146-T146-W146 -> 0 | Y146: =G146+I146+K146+M146+O146+Q146+S146 -> 0 | Z146: =Y146*B146 -> 0 | AA146: =H146*C146 -> 0 | AB146: =J146*C146 -> 0 | AC146: =L146*C146 -> 0 | AD146: =N146*C146 -> 0 | AE146: =P146*C146 -> 0 | AF146: =R146*C146 -> 0 | AG146: =T146*C146 -> 0
A147: 139 | U147: =T147+R147+P147+N147+L147+J147+H147 -> 0 | X147: =F147+G147+I147+K147+M147+O147+Q147+S147-H147-J147-L147-N147-P147-R147-T147-W147 -> 0 | Y147: =G147+I147+K147+M147+O147+Q147+S147 -> 0 | Z147: =Y147*B147 -> 0 | AA147: =H147*C147 -> 0 | AB147: =J147*C147 -> 0 | AC147: =L147*C147 -> 0 | AD147: =N147*C147 -> 0 | AE147: =P147*C147 -> 0 | AF147: =R147*C147 -> 0 | AG147: =T147*C147 -> 0
A148: 140 | U148: =T148+R148+P148+N148+L148+J148+H148 -> 0 | X148: =F148+G148+I148+K148+M148+O148+Q148+S148-H148-J148-L148-N148-P148-R148-T148-W148 -> 0 | Y148: =G148+I148+K148+M148+O148+Q148+S148 -> 0 | Z148: =Y148*B148 -> 0 | AA148: =H148*C148 -> 0 | AB148: =J148*C148 -> 0 | AC148: =L148*C148 -> 0 | AD148: =N148*C148 -> 0 | AE148: =P148*C148 -> 0 | AF148: =R148*C148 -> 0 | AG148: =T148*C148 -> 0
A149: 141 | U149: =T149+R149+P149+N149+L149+J149+H149 -> 0 | X149: =F149+G149+I149+K149+M149+O149+Q149+S149-H149-J149-L149-N149-P149-R149-T149-W149 -> 0 | Y149: =G149+I149+K149+M149+O149+Q149+S149 -> 0 | Z149: =Y149*B149 -> 0 | AA149: =H149*C149 -> 0 | AB149: =J149*C149 -> 0 | AC149: =L149*C149 -> 0 | AD149: =N149*C149 -> 0 | AE149: =P149*C149 -> 0 | AF149: =R149*C149 -> 0 | AG149: =T149*C149 -> 0
A150: 142 | U150: =T150+R150+P150+N150+L150+J150+H150 -> 0 | X150: =F150+G150+I150+K150+M150+O150+Q150+S150-H150-J150-L150-N150-P150-R150-T150-W150 -> 0 | Y150: =G150+I150+K150+M150+O150+Q150+S150 -> 0 | Z150: =Y150*B150 -> 0 | AA150: =H150*C150 -> 0 | AB150: =J150*C150 -> 0 | AC150: =L150*C150 -> 0 | AD150: =N150*C150 -> 0 | AE150: =P150*C150 -> 0 | AF150: =R150*C150 -> 0 | AG150: =T150*C150 -> 0
A151: 143 | U151: =T151+R151+P151+N151+L151+J151+H151 -> 0 | X151: =F151+G151+I151+K151+M151+O151+Q151+S151-H151-J151-L151-N151-P151-R151-T151-W151 -> 0 | Y151: =G151+I151+K151+M151+O151+Q151+S151 -> 0 | Z151: =Y151*B151 -> 0 | AA151: =H151*C151 -> 0 | AB151: =J151*C151 -> 0 | AC151: =L151*C151 -> 0 | AD151: =N151*C151 -> 0 | AE151: =P151*C151 -> 0 | AF151: =R151*C151 -> 0 | AG151: =T151*C151 -> 0
A152: 144 | U152: =T152+R152+P152+N152+L152+J152+H152 -> 0 | X152: =F152+G152+I152+K152+M152+O152+Q152+S152-H152-J152-L152-N152-P152-R152-T152-W152 -> 0 | Y152: =G152+I152+K152+M152+O152+Q152+S152 -> 0 | Z152: =Y152*B152 -> 0 | AA152: =H152*C152 -> 0 | AB152: =J152*C152 -> 0 | AC152: =L152*C152 -> 0 | AD152: =N152*C152 -> 0 | AE152: =P152*C152 -> 0 | AF152: =R152*C152 -> 0 | AG152: =T152*C152 -> 0
... A166: 158 | U166: =T166+R166+P166+N166+L166+J166+H166 -> 0 | X166: =F166+G166+I166+K166+M166+O166+Q166+S166-H166-J166-L166-N166-P166-R166-T166-W166 -> 0 | Y166: =G166+I166+K166+M166+O166+Q166+S166 -> 0 | Z166: =Y166*B166 -> 0 | AA166: =H166*C166 -> 0 | AB166: =J166*C166 -> 0 | AC166: =L166*C166 -> 0 | AD166: =N166*C166 -> 0 | AE166: =P166*C166 -> 0 | AF166: =R166*C166 -> 0 | AG166: =T166*C166 -> 0
A167: 159 | U167: =T167+R167+P167+N167+L167+J167+H167 -> 0 | X167: =F167+G167+I167+K167+M167+O167+Q167+S167-H167-J167-L167-N167-P167-R167-T167-W167 -> 0 | Y167: =G167+I167+K167+M167+O167+Q167+S167 -> 0 | AA167: =H167*C167 -> 0 | AB167: =J167*C167 -> 0 | AC167: =L167*C167 -> 0 | AD167: =N167*C167 -> 0 | AE167: =P167*C167 -> 0 | AF167: =R167*C167 -> 0 | AG167: =T167*C167 -> 0
A168: 160 | U168: =T168+R168+P168+N168+L168+J168+H168 -> 0 | X168: =F168+G168+I168+K168+M168+O168+Q168+S168-H168-J168-L168-N168-P168-R168-T168-W168 -> 0 | Y168: =G168+I168+K168+M168+O168+Q168+S168 -> 0 | AA168: =H168*C168 -> 0 | AB168: =J168*C168 -> 0 | AC168: =L168*C168 -> 0 | AD168: =N168*C168 -> 0 | AE168: =P168*C168 -> 0 | AF168: =R168*C168 -> 0 | AG168: =T168*C168 -> 0
A169: 161 | U169: =T169+R169+P169+N169+L169+J169+H169 -> 0 | X169: =F169+G169+I169+K169+M169+O169+Q169+S169-H169-J169-L169-N169-P169-R169-T169-W169 -> 0 | Y169: =G169+I169+K169+M169+O169+Q169+S169 -> 0 | AA169: =H169*C169 -> 0 | AB169: =J169*C169 -> 0 | AC169: =L169*C169 -> 0 | AD169: =N169*C169 -> 0 | AE169: =P169*C169 -> 0 | AF169: =R169*C169 -> 0 | AG169: =T169*C169 -> 0
A170: 162 | U170: =T170+R170+P170+N170+L170+J170+H170 -> 0 | X170: =F170+G170+I170+K170+M170+O170+Q170+S170-H170-J170-L170-N170-P170-R170-T170-W170 -> 0 | Y170: =G170+I170+K170+M170+O170+Q170+S170 -> 0 | AA170: =H170*C170 -> 0 | AB170: =J170*C170 -> 0 | AC170: =L170*C170 -> 0 | AD170: =N170*C170 -> 0 | AE170: =P170*C170 -> 0 | AF170: =R170*C170 -> 0 | AG170: =T170*C170 -> 0
A171: 163 | U171: =T171+R171+P171+N171+L171+J171+H171 -> 0 | X171: =F171+G171+I171+K171+M171+O171+Q171+S171-H171-J171-L171-N171-P171-R171-T171-W171 -> 0 | Y171: =G171+I171+K171+M171+O171+Q171+S171 -> 0 | AA171: =H171*C171 -> 0 | AB171: =J171*C171 -> 0 | AC171: =L171*C171 -> 0 | AD171: =N171*C171 -> 0 | AE171: =P171*C171 -> 0 | AF171: =R171*C171 -> 0 | AG171: =T171*C171 -> 0
A172: 164 | U172: =T172+R172+P172+N172+L172+J172+H172 -> 0 | X172: =F172+G172+I172+K172+M172+O172+Q172+S172-H172-J172-L172-N172-P172-R172-T172-W172 -> 0 | Y172: =G172+I172+K172+M172+O172+Q172+S172 -> 0 | AA172: =H172*C172 -> 0 | AB172: =J172*C172 -> 0 | AC172: =L172*C172 -> 0 | AD172: =N172*C172 -> 0 | AE172: =P172*C172 -> 0 | AF172: =R172*C172 -> 0 | AG172: =T172*C172 -> 0
A173: 165 | U173: =T173+R173+P173+N173+L173+J173+H173 -> 0 | X173: =F173+G173+I173+K173+M173+O173+Q173+S173-H173-J173-L173-N173-P173-R173-T173-W173 -> 0 | Y173: =G173+I173+K173+M173+O173+Q173+S173 -> 0 | AA173: =H173*C173 -> 0 | AB173: =J173*C173 -> 0 | AC173: =L173*C173 -> 0 | AD173: =N173*C173 -> 0 | AE173: =P173*C173 -> 0 | AF173: =R173*C173 -> 0 | AG173: =T173*C173 -> 0
A174: 166 | U174: =T174+R174+P174+N174+L174+J174+H174 -> 0 | X174: =F174+G174+I174+K174+M174+O174+Q174+S174-H174-J174-L174-N174-P174-R174-T174-W174 -> 0 | Y174: =G174+I174+K174+M174+O174+Q174+S174 -> 0 | AA174: =H174*C174 -> 0 | AB174: =J174*C174 -> 0 | AC174: =L174*C174 -> 0 | AD174: =N174*C174 -> 0 | AE174: =P174*C174 -> 0 | AF174: =R174*C174 -> 0 | AG174: =T174*C174 -> 0
A175: 167 | U175: =T175+R175+P175+N175+L175+J175+H175 -> 0 | X175: =F175+G175+I175+K175+M175+O175+Q175+S175-H175-J175-L175-N175-P175-R175-T175-W175 -> 0 | Y175: =G175+I175+K175+M175+O175+Q175+S175 -> 0 | AA175: =H175*C175 -> 0 | AB175: =J175*C175 -> 0 | AC175: =L175*C175 -> 0 | AD175: =N175*C175 -> 0 | AE175: =P175*C175 -> 0 | AF175: =R175*C175 -> 0 | AG175: =T175*C175 -> 0
A176: 168 | U176: =T176+R176+P176+N176+L176+J176+H176 -> 0 | X176: =F176+G176+I176+K176+M176+O176+Q176+S176-H176-J176-L176-N176-P176-R176-T176-W176 -> 0 | Y176: =G176+I176+K176+M176+O176+Q176+S176 -> 0 | AA176: =H176*C176 -> 0 | AB176: =J176*C176 -> 0 | AC176: =L176*C176 -> 0 | AD176: =N176*C176 -> 0 | AE176: =P176*C176 -> 0 | AF176: =R176*C176 -> 0 | AG176: =T176*C176 -> 0
A177: 169 | U177: =T177+R177+P177+N177+L177+J177+H177 -> 0 | X177: =F177+G177+I177+K177+M177+O177+Q177+S177-H177-J177-L177-N177-P177-R177-T177-W177 -> 0 | Y177: =G177+I177+K177+M177+O177+Q177+S177 -> 0 | AA177: =H177*C177 -> 0 | AB177: =J177*C177 -> 0 | AC177: =L177*C177 -> 0 | AD177: =N177*C177 -> 0 | AE177: =P177*C177 -> 0 | AF177: =R177*C177 -> 0 | AG177: =T177*C177 -> 0
A178: 170 | U178: =T178+R178+P178+N178+L178+J178+H178 -> 0 | X178: =F178+G178+I178+K178+M178+O178+Q178+S178-H178-J178-L178-N178-P178-R178-T178-W178 -> 0 | Y178: =G178+I178+K178+M178+O178+Q178+S178 -> 0 | AA178: =H178*C178 -> 0 | AB178: =J178*C178 -> 0 | AC178: =L178*C178 -> 0 | AD178: =N178*C178 -> 0 | AE178: =P178*C178 -> 0 | AF178: =R178*C178 -> 0 | AG178: =T178*C178 -> 0
... A200: 91 | U200: =T200+R200+P200+N200+L200+J200+H200 -> 0 | X200: =F200+G200+I200+K200+M200+O200+Q200+S200-H200-J200-L200-N200-P200-R200-T200-W200 -> 0 | Y200: =G200+I200+K200+M200+O200+Q200+S200 -> 0 | AA200: =H200*C200 -> 0 | AB200: =J200*C200 -> 0 | AC200: =L200*C200 -> 0 | AD200: =N200*C200 -> 0 | AE200: =P200*C200 -> 0 | AF200: =R200*C200 -> 0 | AG200: =T200*C200 -> 0
U201: =T201+R201+P201+N201+L201+J201+H201 -> 0 | X201: =F201+G201+I201+K201+M201+O201+Q201+S201-H201-J201-L201-N201-P201-R201-T201-W201 -> 0 | Y201: =G201+I201+K201+M201+O201+Q201+S201 -> 0 | AA201: =H201*C201 -> 0 | AB201: =J201*C201 -> 0 | AC201: =L201*C201 -> 0 | AD201: =N201*C201 -> 0 | AE201: =P201*C201 -> 0 | AF201: =R201*C201 -> 0 | AG201: =T201*C201 -> 0
U202: =T202+R202+P202+N202+L202+J202+H202 -> 0 | X202: =F202+G202+I202+K202+M202+O202+Q202+S202-H202-J202-L202-N202-P202-R202-T202-W202 -> 0 | Y202: =G202+I202+K202+M202+O202+Q202+S202 -> 0 | AA202: =H202*C202 -> 0 | AB202: =J202*C202 -> 0 | AC202: =L202*C202 -> 0 | AD202: =N202*C202 -> 0 | AE202: =P202*C202 -> 0 | AF202: =R202*C202 -> 0 | AG202: =T202*C202 -> 0
U203: =T203+R203+P203+N203+L203+J203+H203 -> 0 | X203: =F203+G203+I203+K203+M203+O203+Q203+S203-H203-J203-L203-N203-P203-R203-T203-W203 -> 0 | Y203: =G203+I203+K203+M203+O203+Q203+S203 -> 0 | AA203: =H203*C203 -> 0 | AB203: =J203*C203 -> 0 | AC203: =L203*C203 -> 0 | AD203: =N203*C203 -> 0 | AE203: =P203*C203 -> 0 | AF203: =R203*C203 -> 0 | AG203: =T203*C203 -> 0
A204: 1 | U204: =T204+R204+P204+N204+L204+J204+H204 -> 0 | X204: =F204+G204+I204+K204+M204+O204+Q204+S204-H204-J204-L204-N204-P204-R204-T204-W204 -> 0 | Y204: =G204+I204+K204+M204+O204+Q204+S204 -> 0 | AA204: =H204*C204 -> 0 | AB204: =J204*C204 -> 0 | AC204: =L204*C204 -> 0 | AD204: =N204*C204 -> 0 | AE204: =P204*C204 -> 0 | AF204: =R204*C204 -> 0 | AG204: =T204*C204 -> 0
A205: 3 | U205: =T205+R205+P205+N205+L205+J205+H205 -> 0 | X205: =F205+G205+I205+K205+M205+O205+Q205+S205-H205-J205-L205-N205-P205-R205-T205-W205 -> 0 | Y205: =G205+I205+K205+M205+O205+Q205+S205 -> 0 | AA205: =H205*C205 -> 0 | AB205: =J205*C205 -> 0 | AC205: =L205*C205 -> 0 | AD205: =N205*C205 -> 0 | AE205: =P205*C205 -> 0 | AF205: =R205*C205 -> 0 | AG205: =T205*C205 -> 0
A206: 5 | U206: =T206+R206+P206+N206+L206+J206+H206 -> 0 | X206: =F206+G206+I206+K206+M206+O206+Q206+S206-H206-J206-L206-N206-P206-R206-T206-W206 -> 0 | Y206: =G206+I206+K206+M206+O206+Q206+S206 -> 0 | AA206: =H206*C206 -> 0 | AB206: =J206*C206 -> 0 | AC206: =L206*C206 -> 0 | AD206: =N206*C206 -> 0 | AE206: =P206*C206 -> 0 | AF206: =R206*C206 -> 0 | AG206: =T206*C206 -> 0
A207: 6 | U207: =T207+R207+P207+N207+L207+J207+H207 -> 0 | X207: =F207+G207+I207+K207+M207+O207+Q207+S207-H207-J207-L207-N207-P207-R207-T207-W207 -> 0 | Y207: =G207+I207+K207+M207+O207+Q207+S207 -> 0 | AA207: =H207*C207 -> 0 | AB207: =J207*C207 -> 0 | AC207: =L207*C207 -> 0 | AD207: =N207*C207 -> 0 | AE207: =P207*C207 -> 0 | AF207: =R207*C207 -> 0 | AG207: =T207*C207 -> 0
...

Sheet Aseo
A1: Basar Ojos Color Sol | Y1: Entradas totales de la semana | Z1: Importe de las Entradas Semanal | AO1: Importe en $
AA2: Basar Ojos Color Sol | AH2: Basar Ojos Color Sol
A5: INVENTARIO | F5: ='Lienzos y espejos'!F5:F7 -> 46152 | G5: ='Lienzos y espejos'!G5:T5 -> Semana del 11 al 16 de Mayo | U5: Venta Total | V5: Deuda | W5: Baja sem. | X5: ='Lienzos y espejos'!X5:X7 -> F. 16/5 /26 | AO5: No | AP5: Total al costo | AQ5: Total a la Venta | AR5: Utilidad Total | AS5: $ en Mercancia
G6: ='Lienzos y espejos'!G6:H6 -> D-10 | I6: ='Lienzos y espejos'!I6:J6 -> L-11 | K6: ='Lienzos y espejos'!K6:L6 -> M-12 | M6: ='Lienzos y espejos'!M6:N6 -> Mi-13 | O6: ='Lienzos y espejos'!O6:P6 -> J-14 | Q6: ='Lienzos y espejos'!Q6:R6 -> V-15 | S6: ='Lienzos y espejos'!S6:T6 -> S-16 | AA6: =G5 -> Semana del 11 al 16 de Mayo | AH6: =AA6 -> Semana del 11 al 16 de Mayo
A7: No | B7: Costo | C7: Venta | D7: Gan. | E7: Producto | G7: Entra. | H7: Venta | I7: Entra. | J7: Venta | K7: Entra. | L7: Venta | M7: Entra. | N7: Venta | O7: Entra. | P7: Venta | Q7: Entra. | R7: Venta | S7: Entra. | T7: Venta | AA7: Domingo | AB7: Lunes | AC7: Martes | AD7: Miercoles | AE7: Jueves | AF7: Viernes | AG7: Sabado | AH7: Cuadre en efectivo de la Semana
E8: Aseo | Z8: =Z9+Z10+Z11+Z12+Z13+Z14+Z15+Z16+Z17+Z18+Z19+Z20+Z21+Z22+Z23+Z24+Z25+Z26+Z27+Z28+Z29+Z30+Z31+Z32+Z33+Z34+Z35+Z36+Z37+Z38+Z39+Z40+Z41+Z42+Z43+Z44+Z45+Z46+Z47+Z48+Z49+Z50+Z51+Z52+Z53+Z54+Z55+Z56+Z57+Z58+Z59+Z60+Z61+Z62+Z63+Z64+Z65+Z66+Z67+Z68+Z69+Z70+Z71+Z72+Z73+Z74+Z75+Z76+Z77+Z78+Z79+Z80+Z81+Z82+Z83+Z84+Z85+Z86+Z87+Z88+Z89+Z90+Z91+Z92+Z93+Z94+Z95+Z96+Z97+Z98+Z99+Z100+Z101+Z102+Z103+Z104+Z105+Z106+Z107+Z108 -> 314770 | AH8: ='Lienzos y espejos'!AH8 -> Domingo | AI8: ='Lienzos y espejos'!AI8 -> Lunes | AJ8: ='Lienzos y espejos'!AJ8 -> Martes | AK8: ='Lienzos y espejos'!AK8 -> Miercoles | AL8: ='Lienzos y espejos'!AL8 -> Jueves | AM8: ='Lienzos y espejos'!AM8 -> Viernes | AN8: ='Lienzos y espejos'!AN8 -> Sabado | AP8: =SUM(AP9:AP170) -> 120420 | AQ8: =AQ9+AQ10+AQ11+AQ12+AQ13+AQ14+AQ15+AQ16+AQ17+AQ18+AQ19+AQ20+AQ21+AQ22+AQ23+AQ24+AQ25+AQ26+AQ27+AQ28+AQ29+AQ30+AQ31+AQ32+AQ33+AQ34+AQ35+AQ36+AQ37+AQ38+AQ39+AQ40+AQ41+AQ42+AQ43+AQ44+AQ45+AQ46+AQ47+AQ48+AQ49+AQ50+AQ51+AQ52+AQ53+AQ54+AQ55+AQ56+AQ57+AQ58+AQ59+AQ60+AQ61+AQ62+AQ63+AQ64+AQ65+AQ66+AQ67+AQ68+AQ69+AQ70+AQ71+AQ72+AQ73+AQ74+AQ75+AQ76+AQ77+AQ78+AQ79+AQ80+AQ81+AQ82+AQ83+AQ84+AQ85+AQ86+AQ87+AQ88+AQ89+AQ90+AQ91+AQ92+AQ93+AQ94+AQ95+AQ96+AQ97+AQ98+AQ99+AQ100+AQ101+AQ102+AQ103+AQ104+AQ105+AQ106+AQ107+AQ108+AQ109+AQ110+AQ111+AQ112+AQ113+AQ114+AQ115+AQ116+AQ117+AQ118+AQ119+AQ120+AQ121+AQ122+AQ123+AQ124+AQ125+AQ126+AQ127+AQ128+AQ129+AQ130+AQ131+AQ132+AQ133+AQ134+AQ135+AQ136+AQ137+AQ138+AQ139+AQ140+AQ141+AQ142+AQ143+AQ144+AQ145+AQ146+AQ147+AQ148+AQ149+AQ150+AQ151+AQ152+AQ153+AQ154+AQ155+AQ156+AQ157+AQ158+AQ159+AQ160+AQ161+AQ162+AQ163+AQ164+AQ165+AQ166+AQ167+AQ168+AQ169+AQ170+AQ171+AQ172+AQ173+AQ174+AQ175+AQ176+AQ177+AQ178+AQ179+AQ180+AQ181+AQ182+AQ183+AQ184+AQ185+AQ186+AQ187+AQ188+AQ189+AQ190+AQ191+AQ192+AQ193+AQ194+AQ195+AQ196+AQ197+AQ198+AQ199+AQ200+AQ201+AQ202+AQ203+AQ204+AQ205+AQ206+AQ207+AQ208+AQ209+AQ210+AQ211+AQ212+AQ213+AQ214+AQ215+AQ216+AQ217+AQ218+AQ219+AQ220+AQ221+AQ222+AQ223+AQ224+AQ225+AQ226+AQ227+AQ228+AQ229+AQ230+AQ231+AQ232+AQ233+AQ234+AQ235+AQ236+AQ237+AQ238+AQ239+AQ240+AQ241+AQ242+AQ243+AQ244+AQ245+AQ246+AQ247+AQ248+AQ249+AQ250+AQ251+AQ252+AQ253+AQ254+AQ255+AQ256+AQ257+AQ258+AQ259+AQ260+AQ261+AQ262+AQ263+AQ264+AQ265+AQ266+AQ267+AQ268+AQ269+AQ270+AQ271+AQ272+AQ273+AQ274+AQ275+AQ276+AQ277+AQ278+AQ279+AQ280+AQ281+AQ282+AQ283+AQ284+AQ285+AQ286+AQ287+AQ288+AQ289+AQ290+AQ291+AQ292+AQ293+AQ294+AQ295+AQ296+AQ297+AQ298+AQ299+AQ300+AQ301+AQ302+AQ303+AQ304+AQ305+AQ306+AQ307+AQ308+AQ309+AQ310+AQ311+AQ312+AQ313+AQ314+AQ315+AQ316+AQ317+AQ318+AQ319+AQ320+AQ321+AQ322+AQ323+AQ324+AQ325+AQ326+AQ327+AQ328+AQ329+AQ330+AQ331+AQ332+AQ333+AQ334+AQ335+AQ336+AQ337+AQ338+AQ339+AQ340+AQ341+AQ342+AQ343+AQ344+AQ345+AQ346+AQ347+AQ348+AQ349+AQ350+AQ351+AQ352+AQ353+AQ354+AQ355+AQ356+AQ357+AQ358+AQ359+AQ360+AQ361+AQ362+AQ363+AQ364+AQ365+AQ366+AQ367+AQ368+AQ369+AQ370+AQ371+AQ372+AQ373+AQ374+AQ375+AQ376+AQ377+AQ378+AQ379+AQ380+AQ381+AQ382+AQ383+AQ384+AQ385+AQ386+AQ387+AQ388+AQ389+AQ390+AQ391+AQ392+AQ393+AQ394+AQ395+AQ396+AQ397+AQ398+AQ399+AQ400+AQ401+AQ402+AQ403+AQ404+AQ405+AQ406+AQ407+AQ408+AQ409+AQ410+AQ411+AQ412+AQ413+AQ414+AQ415+AQ416+AQ417+AQ418+AQ419+AQ420+AQ421+AQ422+AQ423+AQ424+AQ425+AQ426+AQ427+AQ428+AQ429+AQ430+AQ431+AQ432+AQ433+AQ434+AQ435+AQ436+AQ437+AQ438+AQ439+AQ440+AQ441+AQ442+AQ443+AQ444+AQ445+AQ446+AQ447+AQ448+AQ449+AQ450+AQ451+AQ452+AQ453+AQ454+AQ455+AQ456+AQ457+AQ458+AQ459+AQ460+AQ461+AQ462+AQ463+AQ464+AQ465+AQ466+AQ467+AQ468+AQ469+AQ470+AQ471+AQ472+AQ473+AQ474+AQ475+AQ476+AQ477+AQ478+AQ479+AQ480+AQ481+AQ482+AQ483+AQ484+AQ485+AQ486+AQ487+AQ488+AQ489+AQ490+AQ491+AQ492+AQ493+AQ494+AQ495+AQ496+AQ497+AQ498+AQ499+AQ500+AQ501+AQ502+AQ503+AQ504+AQ505+AQ506+AQ507+AQ508+AQ509+AQ510+AQ511+AQ512+AQ513+AQ514+AQ515+AQ516+AQ517+AQ518+AQ519+AQ520+AQ521+AQ522+AQ523+AQ524+AQ525+AQ526+AQ527+AQ528+AQ529+AQ530+AQ531+AQ532+AQ533+AQ534+AQ535+AQ536+AQ537+AQ538+AQ539+AQ540+AQ541+AQ542+AQ543+AQ544+AQ545+AQ546+AQ547+AQ548+AQ549+AQ550+AQ551+AQ552+AQ553 -> 169300 | AR8: =AQ8-AP8 -> 48880 | AS8: =AS9+AS10+AS11+AS12+AS13+AS14+AS15+AS16+AS17+AS18+AS19+AS20+AS21+AS22+AS23+AS24+AS25+AS26+AS27+AS28+AS29+AS30+AS31+AS32+AS33+AS34+AS35+AS36+AS37+AS38+AS39+AS40+AS41+AS42+AS43+AS44+AS45+AS46+AS47+AS48+AS49+AS50+AS51+AS52+AS53+AS54+AS55+AS56+AS57+AS58+AS59+AS60+AS61+AS62+AS63+AS64+AS65+AS66+AS67+AS68+AS69+AS70+AS71+AS72+AS73+AS74+AS75+AS76+AS77+AS78+AS79+AS80+AS81+AS82+AS83+AS84+AS85+AS86+AS87+AS88+AS89+AS90+AS91+AS92+AS93+AS94+AS95+AS96+AS97+AS98+AS99+AS100+AS102+AS103+AS104+AS105+AS106+AS107+AS108+AS109+AS110+AS111+AS112+AS113+AS114+AS115+AS116+AS117+AS118+AS119+AS120+AS121+AS122+AS123+AS124+AS125+AS126+AS127+AS128+AS129+AS131+AS132+AS133+AS134+AS135+AS136+AS137+AS138+AS139+AS140+AS141+AS142+AS143+AS144+AS145+AS146+AS147+AS148+AS149+AS150+AS151+AS152+AS153+AS154+AS155+AS156+AS157+AS158+AS159+AS160+AS161+AS162+AS163+AS164+AS165+AS166+AS167+AS168+AS169+AS170+AS171+AS172+AS173+AS174+AS175+AS176+AS177+AS178+AS179+AS180+AS181+AS182+AS183+AS184+AS185+AS186+AS187+AS188+AS189+AS190+AS191+AS192+AS193+AS194+AS195+AS196+AS197+AS198+AS199+AS200+AS201+AS202+AS204+AS205+AS206+AS207+AS208+AS209+AS210+AS211+AS212+AS213+AS214+AS215+AS217+AS218+AS219+AS220+AS221+AS222+AS223+AS224+AS225+AS226+AS227+AS228+AS229+AS230+AS231+AS232+AS233+AS234+AS235+AS236+AS237+AS238+AS240+AS241+AS242+AS243+AS244+AS245+AS246+AS247+AS248+AS249+AS250+AS251+AS252+AS253+AS254+AS255+AS256+AS257+AS258+AS259+AS260+AS261+AS262+AS263+AS264+AS266+AS267+AS268+AS269+AS270+AS271+AS272+AS273+AS276+AS277+AS278+AS279+AS280+AS281+AS283+AS284+AS285+AS286+AS287+AS288+AS289+AS290+AS291+AS292+AS293+AS294+AS295+AS296+AS297+AS298+AS299+AS300+AS301+AS302+AS303+AS304+AS305+AS306+AS307+AS308+AS309+AS310+AS311+AS312+AS313+AS314+AS315+AS316+AS317+AS318+AS319+AS320+AS321+AS322+AS323+AS324+AS325+AS326+AS327+AS328+AS329+AS330+AS331+AS332+AS333+AS334+AS335+AS336+AS337+AS338+AS339+AS340+AS341+AS342+AS343+AS344+AS345+AS346+AS347+AS348+AS349+AS350+AS351+AS352+AS353+AS354+AS355+AS356+AS357+AS358+AS359+AS360+AS361+AS362+AS363+AS364+AS366+AS367+AS368+AS369+AS370+AS371+AS372+AS373+AS374+AS375+AS376+AS377+AS378+AS379+AS380+AS381+AS382+AS383+AS384+AS385+AS386+AS387+AS388+AS389+AS390+AS391+AS392+AS393+AS394+AS395+AS396+AS397+AS398+AS399+AS400+AS401+AS402+AS403+AS404+AS405+AS406+AS407+AS408+AS409+AS410+AS411+AS412+AS413+AS414+AS415+AS416+AS417+AS419+AS420+AS421+AS422+AS423+AS424+AS425+AS426+AS427+AS428+AS429+AS430+AS431+AS432+AS433+AS434+AS435+AS436+AS437+AS438+AS439+AS440+AS441+AS442+AS443+AS444+AS445+AS446+AS447+AS448+AS449+AS450+AS451+AS452+AS453+AS454+AS455+AS456+AS457+AS458+AS459+AS460+AS461+AS462+AS463+AS464+AS465+AS466+AS467+AS468+AS469+AS470+AS471 -> 410700
A9: 1 | B9: 250 | C9: 350 | D9: =C9-B9 -> 100 | E9: Crema de peinar | F9: 8 | U9: =T9+R9+P9+N9+L9+J9+H9 -> 0 | X9: =F9+G9+I9+K9+M9+O9+Q9+S9-H9-J9-L9-N9-P9-R9-T9-V9-W9 -> 8 | Y9: =G9+I9+K9+M9+O9+Q9+S9 -> 0 | Z9: =Y9*B9 -> 0 | AA9: =H9*C9 -> 0 | AB9: =J9*C9 -> 0 | AC9: =L9*C9 -> 0 | AD9: =N9*C9 -> 0 | AE9: =P9*C9 -> 0 | AF9: =R9*C9 -> 0 | AG9: =T9*C9 -> 0 | AH9: =AA9+AA10+AA11+AA12+AA13+AA14+AA15+AA16+AA17+AA18+AA19+AA20+AA21+AA22+AA23+AA24+AA25+AA26+AA27+AA28+AA29+AA30+AA31+AA32+AA33+AA34+AA35+AA36+AA37+AA38+AA39+AA40+AA41+AA42+AA43+AA44+AA45+AA46+AA47+AA48+AA49+AA50+AA51+AA52+AA53+AA54+AA55+AA56+AA57+AA58+AA59+AA60+AA61+AA62+AA63+AA64+AA65+AA66+AA67+AA68+AA69+AA70+AA71+AA72+AA73+AA74+AA75+AA76+AA77+AA78+AA79+AA80+AA81+AA82+AA83+AA84+AA85+AA86+AA87+AA88+AA89+AA90+AA91+AA92+AA93+AA94+AA95+AA96+AA97+AA98+AA99+AA100+AA101+AA102+AA103+AA104+AA105+AA106+AA107+AA108+AA109+AA110+AA111+AA112+AA113+AA114+AA115+AA116+AA117+AA118+AA119+AA120+AA121+AA122+AA123+AA124+AA125+AA126+AA127+AA128+AA129+AA130+AA131+AA132+AA133+AA134+AA135+AA136+AA137+AA138+AA139+AA140+AA141+AA142+AA143+AA144+AA145+AA146+AA147+AA148+AA149+AA150+AA151+AA152+AA153+AA154+AA155+AA156+AA157+AA158+AA159+AA160+AA161+AA162+AA163+AA164+AA165+AA166+AA167+AA168+AA169+AA170+AA171+AA172+AA173+AA174+AA175+AA176+AA177+AA178+AA179+AA180+AA181+AA182+AA183+AA184+AA185+AA186+AA187+AA188+AA189+AA190+AA191+AA192+AA193+AA194+AA195+AA196+AA197+AA198+AA199+AA200+AA201+AA202+AA203+AA204+AA205+AA206+AA207+AA208+AA209+AA210+AA211+AA212+AA213+AA214+AA215+AA216+AA217+AA218+AA219+AA220+AA221+AA222+AA223+AA224+AA225+AA226+AA227+AA228+AA229+AA230+AA231+AA232+AA233+AA234+AA235+AA236+AA237+AA238+AA239+AA240+AA241+AA242+AA243+AA244+AA245+AA246+AA247+AA248+AA249+AA250+AA251+AA252+AA253+AA254+AA255+AA256+AA257+AA258+AA259+AA260+AA261+AA262+AA263+AA264+AA265+AA266+AA267+AA268+AA269+AA270+AA271+AA272+AA273+AA274+AA275+AA276+AA277+AA278+AA279+AA280+AA281+AA282+AA283+AA284+AA285+AA286+AA287+AA288+AA289+AA290+AA291+AA292+AA293+AA294+AA295+AA296+AA297+AA298+AA299+AA300+AA301+AA302+AA303+AA304+AA305+AA306+AA307+AA308+AA309+AA310+AA311+AA312+AA313+AA314+AA315+AA316+AA317+AA318+AA319+AA320+AA321+AA322+AA323+AA324+AA325+AA326+AA327+AA328+AA329+AA330+AA331+AA332+AA333+AA334+AA335+AA336+AA337+AA338+AA339+AA340+AA341+AA342+AA343+AA344+AA345+AA346+AA347+AA348+AA349+AA350+AA351+AA352+AA353+AA354+AA355+AA356+AA357+AA358+AA359+AA360+AA361+AA362+AA363+AA364+AA365+AA366+AA367+AA368+AA369+AA370+AA371+AA372+AA373+AA374+AA375+AA376+AA377+AA378+AA379+AA380+AA381+AA382+AA383+AA384+AA385+AA386+AA387+AA388+AA389+AA390+AA391+AA392+AA393+AA394+AA395+AA396+AA397+AA398+AA399+AA400+AA401+AA402+AA403+AA404+AA405+AA406+AA407+AA408+AA409+AA410+AA411+AA412+AA413+AA414+AA415+AA416+AA417+AA418+AA419+AA420+AA421+AA422+AA423+AA424+AA425+AA426+AA427+AA428+AA429+AA430+AA431+AA432+AA433+AA434+AA435+AA436+AA437+AA438+AA439+AA440+AA441+AA442+AA443+AA444+AA445+AA446+AA447+AA448+AA449+AA450+AA451+AA452+AA453+AA454+AA455+AA456+AA457+AA458+AA459+AA460+AA461+AA462+AA463+AA464+AA465+AA466+AA467+AA468+AA469+AA470+AA471+AA472+AA473+AA474+AA475+AA476+AA477+AA478+AA479+AA480+AA481+AA482+AA483+AA484+AA485+AA486+AA487+AA488+AA489+AA490+AA491+AA492+AA493+AA494+AA495+AA496+AA497+AA498+AA499+AA500+AA501+AA502+AA503+AA504+AA505+AA506+AA507+AA508+AA509+AA510+AA511+AA512+AA513+AA514+AA515+AA516+AA517+AA518+AA519+AA520+AA521+AA522+AA523+AA524+AA525+AA526+AA527+AA528+AA529+AA530+AA531+AA532+AA533+AA534+AA535+AA536+AA537+AA538+AA539+AA540+AA541+AA542+AA543+AA544+AA545+AA546+AA547+AA548+AA549+AA550+AA551+AA552+AA553+AA554+AA555+AA556+AA557+AA558+AA559+AA560 -> 0 | AI9: =AB9+AB10+AB11+AB12+AB13+AB14+AB15+AB16+AB17+AB18+AB19+AB20+AB21+AB22+AB23+AB24+AB25+AB26+AB27+AB28+AB29+AB30+AB31+AB32+AB33+AB34+AB35+AB36+AB37+AB38+AB39+AB40+AB41+AB42+AB43+AB44+AB45+AB46+AB47+AB48+AB49+AB50+AB51+AB52+AB53+AB54+AB55+AB56+AB57+AB58+AB59+AB60+AB61+AB62+AB63+AB64+AB65+AB66+AB67+AB68+AB69+AB70+AB71+AB72+AB73+AB74+AB75+AB76+AB77+AB78+AB79+AB80+AB81+AB82+AB83+AB84+AB85+AB86+AB87+AB88+AB89+AB90+AB91+AB92+AB93+AB94+AB95+AB96+AB97+AB98+AB99+AB100+AB101+AB102+AB103+AB104+AB105+AB106+AB107+AB108+AB109+AB110+AB111+AB112+AB113+AB114+AB115+AB116+AB117+AB118+AB119+AB120+AB121+AB122+AB123+AB124+AB125+AB126+AB127+AB128+AB129+AB130+AB131+AB132+AB133+AB134+AB135+AB136+AB137+AB138+AB139+AB140+AB141+AB142+AB143+AB144+AB145+AB146+AB147+AB148+AB149+AB150+AB151+AB152+AB153+AB154+AB155+AB156+AB157+AB158+AB159+AB160+AB161+AB162+AB163+AB164+AB165+AB166+AB167+AB168+AB169+AB170+AB171+AB172+AB173+AB174+AB175+AB176+AB177+AB178+AB179+AB180+AB181+AB182+AB183+AB184+AB185+AB186+AB187+AB188+AB189+AB190+AB191+AB192+AB193+AB194+AB195+AB196+AB197+AB198+AB199+AB200+AB201+AB202+AB203+AB204+AB205+AB206+AB207+AB208+AB209+AB210+AB211+AB212+AB213+AB214+AB215+AB216+AB217+AB218+AB219+AB220+AB221+AB222+AB223+AB224+AB225+AB226+AB227+AB228+AB229+AB230+AB231+AB232+AB233+AB234+AB235+AB236+AB237+AB238+AB239+AB240+AB241+AB242+AB243+AB244+AB245+AB246+AB247+AB248+AB249+AB250+AB251+AB252+AB253+AB254+AB255+AB256+AB257+AB258+AB259+AB260+AB261+AB262+AB263+AB264+AB265+AB266+AB267+AB268+AB269+AB270+AB271+AB272+AB273+AB274+AB275+AB276+AB277+AB278+AB279+AB280+AB281+AB282+AB283+AB284+AB285+AB286+AB287+AB288+AB289+AB290+AB291+AB292+AB293+AB294+AB295+AB296+AB297+AB298+AB299+AB300+AB301+AB302+AB303+AB304+AB305+AB306+AB307+AB308+AB309+AB310+AB311+AB312+AB313+AB314+AB315+AB316+AB317+AB318+AB319+AB320+AB321+AB322+AB323+AB324+AB325+AB326+AB327+AB328+AB329+AB330+AB331+AB332+AB333+AB334+AB335+AB336+AB337+AB338+AB339+AB340+AB341+AB342+AB343+AB344+AB345+AB346+AB347+AB348+AB349+AB350+AB351+AB352+AB353+AB354+AB355+AB356+AB357+AB358+AB359+AB360+AB361+AB362+AB363+AB364+AB365+AB366+AB367+AB368+AB369+AB370+AB371+AB372+AB373+AB374+AB375+AB376+AB377+AB378+AB379+AB380+AB381+AB382+AB383+AB384+AB385+AB386+AB387+AB388+AB389+AB390+AB391+AB392+AB393+AB394+AB395+AB396+AB397+AB398+AB399+AB400+AB401+AB402+AB403+AB404+AB405+AB406+AB407+AB408+AB409+AB410+AB411+AB412+AB413+AB414+AB415+AB416+AB417+AB418+AB419+AB420+AB421+AB422+AB423+AB424+AB425+AB426+AB427+AB428+AB429+AB430+AB431+AB432+AB433+AB434+AB435+AB436+AB437+AB438+AB439+AB440+AB441+AB442+AB443+AB444+AB445+AB446+AB447+AB448+AB449+AB450+AB451+AB452+AB453+AB454+AB455+AB456+AB457+AB458+AB459+AB460+AB461+AB462+AB463+AB464+AB465+AB466+AB467+AB468+AB469+AB470+AB471+AB472+AB473+AB474+AB475+AB476+AB477+AB478+AB479+AB480+AB481+AB482+AB483+AB484+AB485+AB486+AB487+AB488+AB489+AB490+AB491+AB492+AB493+AB494+AB495+AB496+AB497+AB498+AB499+AB500+AB501+AB502+AB503+AB504+AB505+AB506+AB507+AB508+AB509+AB510+AB511+AB512+AB513+AB514+AB515+AB516+AB517+AB518+AB519+AB520+AB521+AB522+AB523+AB524+AB525+AB526+AB527+AB528+AB529+AB530+AB531+AB532+AB533+AB534+AB535+AB536+AB537+AB538+AB539+AB540+AB541+AB542+AB543+AB544+AB545+AB546+AB547+AB548+AB549+AB550+AB551+AB552+AB553+AB554+AB555+AB556+AB557+AB558+AB559+AB560 -> 24900 | AJ9: =AC9+AC10+AC11+AC12+AC13+AC14+AC15+AC16+AC17+AC18+AC19+AC20+AC21+AC22+AC23+AC24+AC25+AC26+AC27+AC28+AC29+AC30+AC31+AC32+AC33+AC34+AC35+AC36+AC37+AC38+AC39+AC40+AC41+AC42+AC43+AC44+AC45+AC46+AC47+AC48+AC49+AC50+AC51+AC52+AC53+AC54+AC55+AC56+AC57+AC58+AC59+AC60+AC61+AC62+AC63+AC64+AC65+AC66+AC67+AC68+AC69+AC70+AC71+AC72+AC73+AC74+AC75+AC76+AC77+AC78+AC79+AC80+AC81+AC82+AC83+AC84+AC85+AC86+AC87+AC88+AC89+AC90+AC91+AC92+AC93+AC94+AC95+AC96+AC97+AC98+AC99+AC100+AC101+AC102+AC103+AC104+AC105+AC106+AC107+AC108+AC109+AC110+AC111+AC112+AC113+AC114+AC115+AC116+AC117+AC118+AC119+AC120+AC121+AC122+AC123+AC124+AC125+AC126+AC127+AC128+AC129+AC130+AC131+AC132+AC133+AC134+AC135+AC136+AC137+AC138+AC139+AC140+AC141+AC142+AC143+AC144+AC145+AC146+AC147+AC148+AC149+AC150+AC151+AC152+AC153+AC154+AC155+AC156+AC157+AC158+AC159+AC160+AC161+AC162+AC163+AC164+AC165+AC166+AC167+AC168+AC169+AC170+AC171+AC172+AC173+AC174+AC175+AC176+AC177+AC178+AC179+AC180+AC181+AC182+AC183+AC184+AC185+AC186+AC187+AC188+AC189+AC190+AC191+AC192+AC193+AC194+AC195+AC196+AC197+AC198+AC199+AC200+AC201+AC202+AC203+AC204+AC205+AC206+AC207+AC208+AC209+AC210+AC211+AC212+AC213+AC214+AC215+AC216+AC217+AC218+AC219+AC220+AC221+AC222+AC223+AC224+AC225+AC226+AC227+AC228+AC229+AC230+AC231+AC232+AC233+AC234+AC235+AC236+AC237+AC238+AC239+AC240+AC241+AC242+AC243+AC244+AC245+AC246+AC247+AC248+AC249+AC250+AC251+AC252+AC253+AC254+AC255+AC256+AC257+AC258+AC259+AC260+AC261+AC262+AC263+AC264+AC265+AC266+AC267+AC268+AC269+AC270+AC271+AC272+AC273+AC274+AC275+AC276+AC277+AC278+AC279+AC280+AC281+AC282+AC283+AC284+AC285+AC286+AC287+AC288+AC289+AC290+AC291+AC292+AC293+AC294+AC295+AC296+AC297+AC298+AC299+AC300+AC301+AC302+AC303+AC304+AC305+AC306+AC307+AC308+AC309+AC310+AC311+AC312+AC313+AC314+AC315+AC316+AC317+AC318+AC319+AC320+AC321+AC322+AC323+AC324+AC325+AC326+AC327+AC328+AC329+AC330+AC331+AC332+AC333+AC334+AC335+AC336+AC337+AC338+AC339+AC340+AC341+AC342+AC343+AC344+AC345+AC346+AC347+AC348+AC349+AC350+AC351+AC352+AC353+AC354+AC355+AC356+AC357+AC358+AC359+AC360+AC361+AC362+AC363+AC364+AC365+AC366+AC367+AC368+AC369+AC370+AC371+AC372+AC373+AC374+AC375+AC376+AC377+AC378+AC379+AC380+AC381+AC382+AC383+AC384+AC385+AC386+AC387+AC388+AC389+AC390+AC391+AC392+AC393+AC394+AC395+AC396+AC397+AC398+AC399+AC400+AC401+AC402+AC403+AC404+AC405+AC406+AC407+AC408+AC409+AC410+AC411+AC412+AC413+AC414+AC415+AC416+AC417+AC418+AC419+AC420+AC421+AC422+AC423+AC424+AC425+AC426+AC427+AC428+AC429+AC430+AC431+AC432+AC433+AC434+AC435+AC436+AC437+AC438+AC439+AC440+AC441+AC442+AC443+AC444+AC445+AC446+AC447+AC448+AC449+AC450+AC451+AC452+AC453+AC454+AC455+AC456+AC457+AC458+AC459+AC460+AC461+AC462+AC463+AC464+AC465+AC466+AC467+AC468+AC469+AC470+AC471+AC472+AC473+AC474+AC475+AC476+AC477+AC478+AC479+AC480+AC481+AC482+AC483+AC484+AC485+AC486+AC487+AC488+AC489+AC490+AC491+AC492+AC493+AC494+AC495+AC496+AC497+AC498+AC499+AC500+AC501+AC502+AC503+AC504+AC505+AC506+AC507+AC508+AC509+AC510+AC511+AC512+AC513+AC514+AC515+AC516+AC517+AC518+AC519+AC520+AC521+AC522+AC523+AC524+AC525+AC526+AC527+AC528+AC529+AC530+AC531+AC532+AC533+AC534+AC535+AC536+AC537+AC538+AC539+AC540+AC541+AC542+AC543+AC544+AC545+AC546+AC547+AC548+AC549+AC550+AC551+AC552+AC553+AC554+AC555+AC556+AC557+AC558+AC559+AC560 -> 14000 | AK9: =AD9+AD10+AD11+AD12+AD13+AD14+AD15+AD16+AD17+AD18+AD19+AD20+AD21+AD22+AD23+AD24+AD25+AD26+AD27+AD28+AD29+AD30+AD31+AD32+AD33+AD34+AD35+AD36+AD37+AD38+AD39+AD40+AD41+AD42+AD43+AD44+AD45+AD46+AD47+AD48+AD49+AD50+AD51+AD52+AD53+AD54+AD55+AD56+AD57+AD58+AD59+AD60+AD61+AD62+AD63+AD64+AD65+AD66+AD67+AD68+AD69+AD70+AD71+AD72+AD73+AD74+AD75+AD76+AD77+AD78+AD79+AD80+AD81+AD82+AD83+AD84+AD85+AD86+AD87+AD88+AD89+AD90+AD91+AD92+AD93+AD94+AD95+AD96+AD97+AD98+AD99+AD100+AD101+AD102+AD103+AD104+AD105+AD106+AD107+AD108+AD109+AD110+AD111+AD112+AD113+AD114+AD115+AD116+AD117+AD118+AD119+AD120+AD121+AD122+AD123+AD124+AD125+AD126+AD127+AD128+AD129+AD130+AD131+AD132+AD133+AD134+AD135+AD136+AD137+AD138+AD139+AD140+AD141+AD142+AD143+AD144+AD145+AD146+AD147+AD148+AD149+AD150+AD151+AD152+AD153+AD154+AD155+AD156+AD157+AD158+AD159+AD160+AD161+AD162+AD163+AD164+AD165+AD166+AD167+AD168+AD169+AD170+AD171+AD172+AD173+AD174+AD175+AD176+AD177+AD178+AD179+AD180+AD181+AD182+AD183+AD184+AD185+AD186+AD187+AD188+AD189+AD190+AD191+AD192+AD193+AD194+AD195+AD196+AD197+AD198+AD199+AD200+AD201+AD202+AD203+AD204+AD205+AD206+AD207+AD208+AD209+AD210+AD211+AD212+AD213+AD214+AD215+AD216+AD217+AD218+AD219+AD220+AD221+AD222+AD223+AD224+AD225+AD226+AD227+AD228+AD229+AD230+AD231+AD232+AD233+AD234+AD235+AD236+AD237+AD238+AD239+AD240+AD241+AD242+AD243+AD244+AD245+AD246+AD247+AD248+AD249+AD250+AD251+AD252+AD253+AD254+AD255+AD256+AD257+AD258+AD259+AD260+AD261+AD262+AD263+AD264+AD265+AD266+AD267+AD268+AD269+AD270+AD271+AD272+AD273+AD274+AD275+AD276+AD277+AD278+AD279+AD280+AD281+AD282+AD283+AD284+AD285+AD286+AD287+AD288+AD289+AD290+AD291+AD292+AD293+AD294+AD295+AD296+AD297+AD298+AD299+AD300+AD301+AD302+AD303+AD304+AD305+AD306+AD307+AD308+AD309+AD310+AD311+AD312+AD313+AD314+AD315+AD316+AD317+AD318+AD319+AD320+AD321+AD322+AD323+AD324+AD325+AD326+AD327+AD328+AD329+AD330+AD331+AD332+AD333+AD334+AD335+AD336+AD337+AD338+AD339+AD340+AD341+AD342+AD343+AD344+AD345+AD346+AD347+AD348+AD349+AD350+AD351+AD352+AD353+AD354+AD355+AD356+AD357+AD358+AD359+AD360+AD361+AD362+AD363+AD364+AD365+AD366+AD367+AD368+AD369+AD370+AD371+AD372+AD373+AD374+AD375+AD376+AD377+AD378+AD379+AD380+AD381+AD382+AD383+AD384+AD385+AD386+AD387+AD388+AD389+AD390+AD391+AD392+AD393+AD394+AD395+AD396+AD397+AD398+AD399+AD400+AD401+AD402+AD403+AD404+AD405+AD406+AD407+AD408+AD409+AD410+AD411+AD412+AD413+AD414+AD415+AD416+AD417+AD418+AD419+AD420+AD421+AD422+AD423+AD424+AD425+AD426+AD427+AD428+AD429+AD430+AD431+AD432+AD433+AD434+AD435+AD436+AD437+AD438+AD439+AD440+AD441+AD442+AD443+AD444+AD445+AD446+AD447+AD448+AD449+AD450+AD451+AD452+AD453+AD454+AD455+AD456+AD457+AD458+AD459+AD460+AD461+AD462+AD463+AD464+AD465+AD466+AD467+AD468+AD469+AD470+AD471+AD472+AD473+AD474+AD475+AD476+AD477+AD478+AD479+AD480+AD481+AD482+AD483+AD484+AD485+AD486+AD487+AD488+AD489+AD490+AD491+AD492+AD493+AD494+AD495+AD496+AD497+AD498+AD499+AD500+AD501+AD502+AD503+AD504+AD505+AD506+AD507+AD508+AD509+AD510+AD511+AD512+AD513+AD514+AD515+AD516+AD517+AD518+AD519+AD520+AD521+AD522+AD523+AD524+AD525+AD526+AD527+AD528+AD529+AD530+AD531+AD532+AD533+AD534+AD535+AD536+AD537+AD538+AD539+AD540+AD541+AD542+AD543+AD544+AD545+AD546+AD547+AD548+AD549+AD550+AD551+AD552+AD553+AD554+AD555+AD556+AD557+AD558+AD559+AD560 -> 46550 | AL9: =AE9+AE10+AE11+AE12+AE13+AE14+AE15+AE16+AE17+AE18+AE19+AE20+AE21+AE22+AE23+AE24+AE25+AE26+AE27+AE28+AE29+AE30+AE31+AE32+AE33+AE34+AE35+AE36+AE37+AE38+AE39+AE40+AE41+AE42+AE43+AE44+AE45+AE46+AE47+AE48+AE49+AE50+AE51+AE52+AE53+AE54+AE55+AE56+AE57+AE58+AE59+AE60+AE61+AE62+AE63+AE64+AE65+AE66+AE67+AE68+AE69+AE70+AE71+AE72+AE73+AE74+AE75+AE76+AE77+AE78+AE79+AE80+AE81+AE82+AE83+AE84+AE85+AE86+AE87+AE88+AE89+AE90+AE91+AE92+AE93+AE94+AE95+AE96+AE97+AE98+AE99+AE100+AE101+AE102+AE103+AE104+AE105+AE106+AE107+AE108+AE109+AE110+AE111+AE112+AE113+AE114+AE115+AE116+AE117+AE118+AE119+AE120+AE121+AE122+AE123+AE124+AE125+AE126+AE127+AE128+AE129+AE130+AE131+AE132+AE133+AE134+AE135+AE136+AE137+AE138+AE139+AE140+AE141+AE142+AE143+AE144+AE145+AE146+AE147+AE148+AE149+AE150+AE151+AE152+AE153+AE154+AE155+AE156+AE157+AE158+AE159+AE160+AE161+AE162+AE163+AE164+AE165+AE166+AE167+AE168+AE169+AE170+AE171+AE172+AE173+AE174+AE175+AE176+AE177+AE178+AE179+AE180+AE181+AE182+AE183+AE184+AE185+AE186+AE187+AE188+AE189+AE190+AE191+AE192+AE193+AE194+AE195+AE196+AE197+AE198+AE199+AE200+AE201+AE202+AE203+AE204+AE205+AE206+AE207+AE208+AE209+AE210+AE211+AE212+AE213+AE214+AE215+AE216+AE217+AE218+AE219+AE220+AE221+AE222+AE223+AE224+AE225+AE226+AE227+AE228+AE229+AE230+AE231+AE232+AE233+AE234+AE235+AE236+AE237+AE238+AE239+AE240+AE241+AE242+AE243+AE244+AE245+AE246+AE247+AE248+AE249+AE250+AE251+AE252+AE253+AE254+AE255+AE256+AE257+AE258+AE259+AE260+AE261+AE262+AE263+AE264+AE265+AE266+AE267+AE268+AE269+AE270+AE271+AE272+AE273+AE274+AE275+AE276+AE277+AE278+AE279+AE280+AE281+AE282+AE283+AE284+AE285+AE286+AE287+AE288+AE289+AE290+AE291+AE292+AE293+AE294+AE295+AE296+AE297+AE298+AE299+AE300+AE301+AE302+AE303+AE304+AE305+AE306+AE307+AE308+AE309+AE310+AE311+AE312+AE313+AE314+AE315+AE316+AE317+AE318+AE319+AE320+AE321+AE322+AE323+AE324+AE325+AE326+AE327+AE328+AE329+AE330+AE331+AE332+AE333+AE334+AE335+AE336+AE337+AE338+AE339+AE340+AE341+AE342+AE343+AE344+AE345+AE346+AE347+AE348+AE349+AE350+AE351+AE352+AE353+AE354+AE355+AE356+AE357+AE358+AE359+AE360+AE361+AE362+AE363+AE364+AE365+AE366+AE367+AE368+AE369+AE370+AE371+AE372+AE373+AE374+AE375+AE376+AE377+AE378+AE379+AE380+AE381+AE382+AE383+AE384+AE385+AE386+AE387+AE388+AE389+AE390+AE391+AE392+AE393+AE394+AE395+AE396+AE397+AE398+AE399+AE400+AE401+AE402+AE403+AE404+AE405+AE406+AE407+AE408+AE409+AE410+AE411+AE412+AE413+AE414+AE415+AE416+AE417+AE418+AE419+AE420+AE421+AE422+AE423+AE424+AE425+AE426+AE427+AE428+AE429+AE430+AE431+AE432+AE433+AE434+AE435+AE436+AE437+AE438+AE439+AE440+AE441+AE442+AE443+AE444+AE445+AE446+AE447+AE448+AE449+AE450+AE451+AE452+AE453+AE454+AE455+AE456+AE457+AE458+AE459+AE460+AE461+AE462+AE463+AE464+AE465+AE466+AE467+AE468+AE469+AE470+AE471+AE472+AE473+AE474+AE475+AE476+AE477+AE478+AE479+AE480+AE481+AE482+AE483+AE484+AE485+AE486+AE487+AE488+AE489+AE490+AE491+AE492+AE493+AE494+AE495+AE496+AE497+AE498+AE499+AE500+AE501+AE502+AE503+AE504+AE505+AE506+AE507+AE508+AE509+AE510+AE511+AE512+AE513+AE514+AE515+AE516+AE517+AE518+AE519+AE520+AE521+AE522+AE523+AE524+AE525+AE526+AE527+AE528+AE529+AE530+AE531+AE532+AE533+AE534+AE535+AE536+AE537+AE538+AE539+AE540+AE541+AE542+AE543+AE544+AE545+AE546+AE547+AE548+AE549+AE550+AE551+AE552+AE553+AE554+AE555+AE556+AE557+AE558+AE559+AE560 -> 27400 | AM9: =AF9+AF10+AF11+AF12+AF13+AF14+AF15+AF16+AF17+AF18+AF19+AF20+AF21+AF22+AF23+AF24+AF25+AF26+AF27+AF28+AF29+AF30+AF31+AF32+AF33+AF34+AF35+AF36+AF37+AF38+AF39+AF40+AF41+AF42+AF43+AF44+AF45+AF46+AF47+AF48+AF49+AF50+AF51+AF52+AF53+AF54+AF55+AF56+AF57+AF58+AF59+AF60+AF61+AF62+AF63+AF64+AF65+AF66+AF67+AF68+AF69+AF70+AF71+AF72+AF73+AF74+AF75+AF76+AF77+AF78+AF79+AF80+AF81+AF82+AF83+AF84+AF85+AF86+AF87+AF88+AF89+AF90+AF91+AF92+AF93+AF94+AF95+AF96+AF97+AF98+AF99+AF100+AF101+AF102+AF103+AF104+AF105+AF106+AF107+AF108+AF109+AF110+AF111+AF112+AF113+AF114+AF115+AF116+AF117+AF118+AF119+AF120+AF121+AF122+AF123+AF124+AF125+AF126+AF127+AF128+AF129+AF130+AF131+AF132+AF133+AF134+AF135+AF136+AF137+AF138+AF139+AF140+AF141+AF142+AF143+AF144+AF145+AF146+AF147+AF148+AF149+AF150+AF151+AF152+AF153+AF154+AF155+AF156+AF157+AF158+AF159+AF160+AF161+AF162+AF163+AF164+AF165+AF166+AF167+AF168+AF169+AF170+AF171+AF172+AF173+AF174+AF175+AF176+AF177+AF178+AF179+AF180+AF181+AF182+AF183+AF184+AF185+AF186+AF187+AF188+AF189+AF190+AF191+AF192+AF193+AF194+AF195+AF196+AF197+AF198+AF199+AF200+AF201+AF202+AF203+AF204+AF205+AF206+AF207+AF208+AF209+AF210+AF211+AF212+AF213+AF214+AF215+AF216+AF217+AF218+AF219+AF220+AF221+AF222+AF223+AF224+AF225+AF226+AF227+AF228+AF229+AF230+AF231+AF232+AF233+AF234+AF235+AF236+AF237+AF238+AF239+AF240+AF241+AF242+AF243+AF244+AF245+AF246+AF247+AF248+AF249+AF250+AF251+AF252+AF253+AF254+AF255+AF256+AF257+AF258+AF259+AF260+AF261+AF262+AF263+AF264+AF265+AF266+AF267+AF268+AF269+AF270+AF271+AF272+AF273+AF274+AF275+AF276+AF277+AF278+AF279+AF280+AF281+AF282+AF283+AF284+AF285+AF286+AF287+AF288+AF289+AF290+AF291+AF292+AF293+AF294+AF295+AF296+AF297+AF298+AF299+AF300+AF301+AF302+AF303+AF304+AF305+AF306+AF307+AF308+AF309+AF310+AF311+AF312+AF313+AF314+AF315+AF316+AF317+AF318+AF319+AF320+AF321+AF322+AF323+AF324+AF325+AF326+AF327+AF328+AF329+AF330+AF331+AF332+AF333+AF334+AF335+AF336+AF337+AF338+AF339+AF340+AF341+AF342+AF343+AF344+AF345+AF346+AF347+AF348+AF349+AF350+AF351+AF352+AF353+AF354+AF355+AF356+AF357+AF358+AF359+AF360+AF361+AF362+AF363+AF364+AF365+AF366+AF367+AF368+AF369+AF370+AF371+AF372+AF373+AF374+AF375+AF376+AF377+AF378+AF379+AF380+AF381+AF382+AF383+AF384+AF385+AF386+AF387+AF388+AF389+AF390+AF391+AF392+AF393+AF394+AF395+AF396+AF397+AF398+AF399+AF400+AF401+AF402+AF403+AF404+AF405+AF406+AF407+AF408+AF409+AF410+AF411+AF412+AF413+AF414+AF415+AF416+AF417+AF418+AF419+AF420+AF421+AF422+AF423+AF424+AF425+AF426+AF427+AF428+AF429+AF430+AF431+AF432+AF433+AF434+AF435+AF436+AF437+AF438+AF439+AF440+AF441+AF442+AF443+AF444+AF445+AF446+AF447+AF448+AF449+AF450+AF451+AF452+AF453+AF454+AF455+AF456+AF457+AF458+AF459+AF460+AF461+AF462+AF463+AF464+AF465+AF466+AF467+AF468+AF469+AF470+AF471+AF472+AF473+AF474+AF475+AF476+AF477+AF478+AF479+AF480+AF481+AF482+AF483+AF484+AF485+AF486+AF487+AF488+AF489+AF490+AF491+AF492+AF493+AF494+AF495+AF496+AF497+AF498+AF499+AF500+AF501+AF502+AF503+AF504+AF505+AF506+AF507+AF508+AF509+AF510+AF511+AF512+AF513+AF514+AF515+AF516+AF517+AF518+AF519+AF520+AF521+AF522+AF523+AF524+AF525+AF526+AF527+AF528+AF529+AF530+AF531+AF532+AF533+AF534+AF535+AF536+AF537+AF538+AF539+AF540+AF541+AF542+AF543+AF544+AF545+AF546+AF547+AF548+AF549+AF550+AF551+AF552+AF553+AF554+AF555+AF556+AF557+AF558+AF559+AF560 -> 29550 | AN9: =AG9+AG10+AG11+AG12+AG13+AG14+AG15+AG16+AG17+AG18+AG19+AG20+AG21+AG22+AG23+AG24+AG25+AG26+AG27+AG28+AG29+AG30+AG31+AG32+AG33+AG34+AG35+AG36+AG37+AG38+AG39+AG40+AG41+AG42+AG43+AG44+AG45+AG46+AG47+AG48+AG49+AG50+AG51+AG52+AG53+AG54+AG55+AG56+AG57+AG58+AG59+AG60+AG61+AG62+AG63+AG64+AG65+AG66+AG67+AG68+AG69+AG70+AG71+AG72+AG73+AG74+AG75+AG76+AG77+AG78+AG79+AG80+AG81+AG82+AG83+AG84+AG85+AG86+AG87+AG88+AG89+AG90+AG91+AG92+AG93+AG94+AG95+AG96+AG97+AG98+AG99+AG100+AG101+AG102+AG103+AG104+AG105+AG106+AG107+AG108+AG109+AG110+AG111+AG112+AG113+AG114+AG115+AG116+AG117+AG118+AG119+AG120+AG121+AG122+AG123+AG124+AG125+AG126+AG127+AG128+AG129+AG130+AG131+AG132+AG133+AG134+AG135+AG136+AG137+AG138+AG139+AG140+AG141+AG142+AG143+AG144+AG145+AG146+AG147+AG148+AG149+AG150+AG151+AG152+AG153+AG154+AG155+AG156+AG157+AG158+AG159+AG160+AG161+AG162+AG163+AG164+AG165+AG166+AG167+AG168+AG169+AG170+AG171+AG172+AG173+AG174+AG175+AG176+AG177+AG178+AG179+AG180+AG181+AG182+AG183+AG184+AG185+AG186+AG187+AG188+AG189+AG190+AG191+AG192+AG193+AG194+AG195+AG196+AG197+AG198+AG199+AG200+AG201+AG202+AG203+AG204+AG205+AG206+AG207+AG208+AG209+AG210+AG211+AG212+AG213+AG214+AG215+AG216+AG217+AG218+AG219+AG220+AG221+AG222+AG223+AG224+AG225+AG226+AG227+AG228+AG229+AG230+AG231+AG232+AG233+AG234+AG235+AG236+AG237+AG238+AG239+AG240+AG241+AG242+AG243+AG244+AG245+AG246+AG247+AG248+AG249+AG250+AG251+AG252+AG253+AG254+AG255+AG256+AG257+AG258+AG259+AG260+AG261+AG262+AG263+AG264+AG265+AG266+AG267+AG268+AG269+AG270+AG271+AG272+AG273+AG274+AG275+AG276+AG277+AG278+AG279+AG280+AG281+AG282+AG283+AG284+AG285+AG286+AG287+AG288+AG289+AG290+AG291+AG292+AG293+AG294+AG295+AG296+AG297+AG298+AG299+AG300+AG301+AG302+AG303+AG304+AG305+AG306+AG307+AG308+AG309+AG310+AG311+AG312+AG313+AG314+AG315+AG316+AG317+AG318+AG319+AG320+AG321+AG322+AG323+AG324+AG325+AG326+AG327+AG328+AG329+AG330+AG331+AG332+AG333+AG334+AG335+AG336+AG337+AG338+AG339+AG340+AG341+AG342+AG343+AG344+AG345+AG346+AG347+AG348+AG349+AG350+AG351+AG352+AG353+AG354+AG355+AG356+AG357+AG358+AG359+AG360+AG361+AG362+AG363+AG364+AG365+AG366+AG367+AG368+AG369+AG370+AG371+AG372+AG373+AG374+AG375+AG376+AG377+AG378+AG379+AG380+AG381+AG382+AG383+AG384+AG385+AG386+AG387+AG388+AG389+AG390+AG391+AG392+AG393+AG394+AG395+AG396+AG397+AG398+AG399+AG400+AG401+AG402+AG403+AG404+AG405+AG406+AG407+AG408+AG409+AG410+AG411+AG412+AG413+AG414+AG415+AG416+AG417+AG418+AG419+AG420+AG421+AG422+AG423+AG424+AG425+AG426+AG427+AG428+AG429+AG430+AG431+AG432+AG433+AG434+AG435+AG436+AG437+AG438+AG439+AG440+AG441+AG442+AG443+AG444+AG445+AG446+AG447+AG448+AG449+AG450+AG451+AG452+AG453+AG454+AG455+AG456+AG457+AG458+AG459+AG460+AG461+AG462+AG463+AG464+AG465+AG466+AG467+AG468+AG469+AG470+AG471+AG472+AG473+AG474+AG475+AG476+AG477+AG478+AG479+AG480+AG481+AG482+AG483+AG484+AG485+AG486+AG487+AG488+AG489+AG490+AG491+AG492+AG493+AG494+AG495+AG496+AG497+AG498+AG499+AG500+AG501+AG502+AG503+AG504+AG505+AG506+AG507+AG508+AG509+AG510+AG511+AG512+AG513+AG514+AG515+AG516+AG517+AG518+AG519+AG520+AG521+AG522+AG523+AG524+AG525+AG526+AG527+AG528+AG529+AG530+AG531+AG532+AG533+AG534+AG535+AG536+AG537+AG538+AG539+AG540+AG541+AG542+AG543+AG544+AG545+AG546+AG547+AG548+AG549+AG550+AG551+AG552+AG553+AG554+AG555+AG556+AG557+AG558+AG559+AG560 -> 26900 | AO9: 1 | AP9: =U9*B9 -> 0 | AQ9: =U9*C9 -> 0 | AR9: =AQ9-AP9 -> 0 | AS9: =X9*B9 -> 2000 | AT9: ok
A10: 2 | B10: 1000 | C10: 1500 | D10: =C10-B10 -> 500 | E10: Tinte | F10: 9 | P10: 1 | T10: 3 | U10: =T10+R10+P10+N10+L10+J10+H10 -> 4 | X10: =F10+G10+I10+K10+M10+O10+Q10+S10-H10-J10-L10-N10-P10-R10-T10-V10-W10 -> 5 | Y10: =G10+I10+K10+M10+O10+Q10+S10 -> 0 | Z10: =Y10*B10 -> 0 | AA10: =H10*C10 -> 0 | AB10: =J10*C10 -> 0 | AC10: =L10*C10 -> 0 | AD10: =N10*C10 -> 0 | AE10: =P10*C10 -> 1500 | AF10: =R10*C10 -> 0 | AG10: =T10*C10 -> 4500 | AO10: 2 | AP10: =U10*B10 -> 4000 | AQ10: =U10*C10 -> 6000 | AR10: =AQ10-AP10 -> 2000 | AS10: =X10*B10 -> 5000
A11: 3 | B11: 1600 | C11: 2500 | D11: =C11-B11 -> 900 | E11: Juego Champu varios | F11: 0 | O11: 12 | T11: 1 | U11: =T11+R11+P11+N11+L11+J11+H11 -> 1 | X11: =F11+G11+I11+K11+M11+O11+Q11+S11-H11-J11-L11-N11-P11-R11-T11-V11-W11 -> 11 | Y11: =G11+I11+K11+M11+O11+Q11+S11 -> 12 | Z11: =Y11*B11 -> 19200 | AA11: =H11*C11 -> 0 | AB11: =J11*C11 -> 0 | AC11: =L11*C11 -> 0 | AD11: =N11*C11 -> 0 | AE11: =P11*C11 -> 0 | AF11: =R11*C11 -> 0 | AG11: =T11*C11 -> 2500 | AO11: 3 | AP11: =U11*B11 -> 1600 | AQ11: =U11*C11 -> 2500 | AR11: =AQ11-AP11 -> 900 | AS11: =X11*B11 -> 17600 | AT11: ok
A12: 4 | B12: 2200 | C12: 3200 | D12: =C12-B12 -> 1000 | E12: Juego Champu Miel | F12: 3 | J12: 2 | O12: 12 | U12: =T12+R12+P12+N12+L12+J12+H12 -> 2 | X12: =F12+G12+I12+K12+M12+O12+Q12+S12-H12-J12-L12-N12-P12-R12-T12-V12-W12 -> 13 | Y12: =G12+I12+K12+M12+O12+Q12+S12 -> 12 | Z12: =Y12*B12 -> 26400 | AA12: =H12*C12 -> 0 | AB12: =J12*C12 -> 6400 | AC12: =L12*C12 -> 0 | AD12: =N12*C12 -> 0 | AE12: =P12*C12 -> 0 | AF12: =R12*C12 -> 0 | AG12: =T12*C12 -> 0 | AH12: Total de la semana | AI12: =AH9+AI9+AJ9+AK9+AL9+AM9+AN9 -> 169300 | AO12: 4 | AP12: =U12*B12 -> 4400 | AQ12: =U12*C12 -> 6400 | AR12: =AQ12-AP12 -> 2000 | AS12: =X12*B12 -> 28600 | AT12: ok
A13: 5 | B13: 2200 | C13: 3000 | D13: =C13-B13 -> 800 | E13: Juego champu sin sal | F13: 1 | N13: 1 | U13: =T13+R13+P13+N13+L13+J13+H13 -> 1 | X13: =F13+G13+I13+K13+M13+O13+Q13+S13-H13-J13-L13-N13-P13-R13-T13-V13-W13 -> 0 | Y13: =G13+I13+K13+M13+O13+Q13+S13 -> 0 | Z13: =Y13*B13 -> 0 | AA13: =H13*C13 -> 0 | AB13: =J13*C13 -> 0 | AC13: =L13*C13 -> 0 | AD13: =N13*C13 -> 3000 | AE13: =P13*C13 -> 0 | AF13: =R13*C13 -> 0 | AG13: =T13*C13 -> 0 | AO13: 5 | AP13: =U13*B13 -> 2200 | AQ13: =U13*C13 -> 3000 | AR13: =AQ13-AP13 -> 800 | AS13: =X13*B13 -> 0
A14: 6 | B14: 2400 | C14: 3200 | D14: =C14-B14 -> 800 | E14: Juego Champu sin sal | F14: 0 | O14: 16 | R14: 3 | U14: =T14+R14+P14+N14+L14+J14+H14 -> 3 | X14: =F14+G14+I14+K14+M14+O14+Q14+S14-H14-J14-L14-N14-P14-R14-T14-V14-W14 -> 13 | Y14: =G14+I14+K14+M14+O14+Q14+S14 -> 16 | Z14: =Y14*B14 -> 38400 | AA14: =H14*C14 -> 0 | AB14: =J14*C14 -> 0 | AC14: =L14*C14 -> 0 | AD14: =N14*C14 -> 0 | AE14: =P14*C14 -> 0 | AF14: =R14*C14 -> 9600 | AG14: =T14*C14 -> 0 | AO14: 6 | AP14: =U14*B14 -> 7200 | AQ14: =U14*C14 -> 9600 | AR14: =AQ14-AP14 -> 2400 | AS14: =X14*B14 -> 31200 | AT14: ok
A15: 7 | B15: 2500 | C15: 3500 | D15: =C15-B15 -> 1000 | E15: Juego champu Argan | F15: 4 | L15: 1 | N15: 3 | U15: =T15+R15+P15+N15+L15+J15+H15 -> 4 | X15: =F15+G15+I15+K15+M15+O15+Q15+S15-H15-J15-L15-N15-P15-R15-T15-V15-W15 -> 0 | Y15: =G15+I15+K15+M15+O15+Q15+S15 -> 0 | Z15: =Y15*B15 -> 0 | AA15: =H15*C15 -> 0 | AB15: =J15*C15 -> 0 | AC15: =L15*C15 -> 3500 | AD15: =N15*C15 -> 10500 | AE15: =P15*C15 -> 0 | AF15: =R15*C15 -> 0 | AG15: =T15*C15 -> 0 | AO15: 7 | AP15: =U15*B15 -> 10000 | AQ15: =U15*C15 -> 14000 | AR15: =AQ15-AP15 -> 4000 | AS15: =X15*B15 -> 0
A16: 8 | B16: 1700 | C16: 2500 | D16: =C16-B16 -> 800 | E16: Jgo Champu nuevo | F16: 0 | U16: =T16+R16+P16+N16+L16+J16+H16 -> 0 | X16: =F16+G16+I16+K16+M16+O16+Q16+S16-H16-J16-L16-N16-P16-R16-T16-V16-W16 -> 0 | Y16: =G16+I16+K16+M16+O16+Q16+S16 -> 0 | Z16: =Y16*B16 -> 0 | AA16: =H16*C16 -> 0 | AB16: =J16*C16 -> 0 | AC16: =L16*C16 -> 0 | AD16: =N16*C16 -> 0 | AE16: =P16*C16 -> 0 | AF16: =R16*C16 -> 0 | AG16: =T16*C16 -> 0 | AO16: 9 | AP16: =U16*B16 -> 0 | AQ16: =U16*C16 -> 0 | AR16: =AQ16-AP16 -> 0 | AS16: =X16*B16 -> 0 | AT16: 1
A17: 9 | B17: 1300 | C17: 1800 | D17: =C17-B17 -> 500 | E17: Champu Dove | F17: 2 | U17: =T17+R17+P17+N17+L17+J17+H17 -> 0 | X17: =F17+G17+I17+K17+M17+O17+Q17+S17-H17-J17-L17-N17-P17-R17-T17-V17-W17 -> 2 | Y17: =G17+I17+K17+M17+O17+Q17+S17 -> 0 | Z17: =Y17*B17 -> 0 | AA17: =H17*C17 -> 0 | AB17: =J17*C17 -> 0 | AC17: =L17*C17 -> 0 | AD17: =N17*C17 -> 0 | AE17: =P17*C17 -> 0 | AF17: =R17*C17 -> 0 | AG17: =T17*C17 -> 0 | AO17: 10 | AP17: =U17*B17 -> 0 | AQ17: =U17*C17 -> 0 | AR17: =AQ17-AP17 -> 0 | AS17: =X17*B17 -> 2600 | AT17: ok
A18: 10 | B18: 1500 | C18: 2500 | D18: =C18-B18 -> 1000 | E18: Champu varios | F18: 0 | U18: =T18+R18+P18+N18+L18+J18+H18 -> 0 | X18: =F18+G18+I18+K18+M18+O18+Q18+S18-H18-J18-L18-N18-P18-R18-T18-V18-W18 -> 0 | Y18: =G18+I18+K18+M18+O18+Q18+S18 -> 0 | Z18: =Y18*B18 -> 0 | AA18: =H18*C18 -> 0 | AB18: =J18*C18 -> 0 | AC18: =L18*C18 -> 0 | AD18: =N18*C18 -> 0 | AE18: =P18*C18 -> 0 | AF18: =R18*C18 -> 0 | AG18: =T18*C18 -> 0 | AO18: 11 | AP18: =U18*B18 -> 0 | AQ18: =U18*C18 -> 0 | AR18: =AQ18-AP18 -> 0 | AS18: =X18*B18 -> 0
A19: 11 | B19: 1700 | C19: 2800 | D19: =C19-B19 -> 1100 | E19: Champu rosado | F19: 0 | U19: =T19+R19+P19+N19+L19+J19+H19 -> 0 | X19: =F19+G19+I19+K19+M19+O19+Q19+S19-H19-J19-L19-N19-P19-R19-T19-V19-W19 -> 0 | Y19: =G19+I19+K19+M19+O19+Q19+S19 -> 0 | Z19: =Y19*B19 -> 0 | AA19: =H19*C19 -> 0 | AB19: =J19*C19 -> 0 | AC19: =L19*C19 -> 0 | AD19: =N19*C19 -> 0 | AE19: =P19*C19 -> 0 | AF19: =R19*C19 -> 0 | AG19: =T19*C19 -> 0 | AO19: 12 | AP19: =U19*B19 -> 0 | AQ19: =U19*C19 -> 0 | AR19: =AQ19-AP19 -> 0 | AS19: =X19*B19 -> 0 | AT19: ok
A20: 12 | B20: 850 | C20: 1400 | D20: =C20-B20 -> 550 | E20: Acondicionador rosado | F20: 1 | L20: 1 | U20: =T20+R20+P20+N20+L20+J20+H20 -> 1 | X20: =F20+G20+I20+K20+M20+O20+Q20+S20-H20-J20-L20-N20-P20-R20-T20-V20-W20 -> 0 | Y20: =G20+I20+K20+M20+O20+Q20+S20 -> 0 | Z20: =Y20*B20 -> 0 | AA20: =H20*C20 -> 0 | AB20: =J20*C20 -> 0 | AC20: =L20*C20 -> 1400 | AD20: =N20*C20 -> 0 | AE20: =P20*C20 -> 0 | AF20: =R20*C20 -> 0 | AG20: =T20*C20 -> 0 | AO20: 13 | AP20: =U20*B20 -> 850 | AQ20: =U20*C20 -> 1400 | AR20: =AQ20-AP20 -> 550 | AS20: =X20*B20 -> 0 | AT20: ok
A21: 13 | B21: 700 | C21: 1000 | D21: =C21-B21 -> 300 | E21: Champu Doxa | F21: 0 | O21: 18 | T21: 1 | U21: =T21+R21+P21+N21+L21+J21+H21 -> 1 | X21: =F21+G21+I21+K21+M21+O21+Q21+S21-H21-J21-L21-N21-P21-R21-T21-V21-W21 -> 17 | Y21: =G21+I21+K21+M21+O21+Q21+S21 -> 18 | Z21: =Y21*B21 -> 12600 | AA21: =H21*C21 -> 0 | AB21: =J21*C21 -> 0 | AC21: =L21*C21 -> 0 | AD21: =N21*C21 -> 0 | AE21: =P21*C21 -> 0 | AF21: =R21*C21 -> 0 | AG21: =T21*C21 -> 1000 | AO21: 14 | AP21: =U21*B21 -> 700 | AQ21: =U21*C21 -> 1000 | AR21: =AQ21-AP21 -> 300 | AS21: =X21*B21 -> 11900 | AT21: ok
A22: 14 | B22: 2600 | C22: 3500 | D22: =C22-B22 -> 900 | E22: Tratamiento | F22: 0 | O22: 4 | T22: 1 | U22: =T22+R22+P22+N22+L22+J22+H22 -> 1 | X22: =F22+G22+I22+K22+M22+O22+Q22+S22-H22-J22-L22-N22-P22-R22-T22-V22-W22 -> 3 | Y22: =G22+I22+K22+M22+O22+Q22+S22 -> 4 | Z22: =Y22*B22 -> 10400 | AA22: =H22*C22 -> 0 | AB22: =J22*C22 -> 0 | AC22: =L22*C22 -> 0 | AD22: =N22*C22 -> 0 | AE22: =P22*C22 -> 0 | AF22: =R22*C22 -> 0 | AG22: =T22*C22 -> 3500 | AO22: 15 | AP22: =U22*B22 -> 2600 | AQ22: =U22*C22 -> 3500 | AR22: =AQ22-AP22 -> 900 | AS22: =X22*B22 -> 7800
A23: 15 | B23: 1050 | C23: 2000 | D23: 950 | E23: Tratamiento chico | F23: 1 | U23: =T23+R23+P23+N23+L23+J23+H23 -> 0 | X23: =F23+G23+I23+K23+M23+O23+Q23+S23-H23-J23-L23-N23-P23-R23-T23-V23-W23 -> 1 | Y23: =G23+I23+K23+M23+O23+Q23+S23 -> 0 | Z23: =Y23*B23 -> 0 | AA23: =H23*C23 -> 0 | AB23: =J23*C23 -> 0 | AC23: =L23*C23 -> 0 | AD23: =N23*C23 -> 0 | AE23: =P23*C23 -> 0 | AF23: =R23*C23 -> 0 | AG23: =T23*C23 -> 0 | AO23: 16 | AP23: =U23*B23 -> 0 | AQ23: =U23*C23 -> 0 | AR23: =AQ23-AP23 -> 0 | AS23: =X23*B23 -> 1050
A24: 16 | B24: 2500 | C24: 3600 | D24: =C24-B24 -> 1100 | E24: EVA | F24: 0 | U24: =T24+R24+P24+N24+L24+J24+H24 -> 0 | X24: =F24+G24+I24+K24+M24+O24+Q24+S24-H24-J24-L24-N24-P24-R24-T24-V24-W24 -> 0 | Y24: =G24+I24+K24+M24+O24+Q24+S24 -> 0 | Z24: =Y24*B24 -> 0 | AA24: =H24*C24 -> 0 | AB24: =J24*C24 -> 0 | AC24: =L24*C24 -> 0 | AD24: =N24*C24 -> 0 | AE24: =P24*C24 -> 0 | AF24: =R24*C24 -> 0 | AG24: =T24*C24 -> 0 | AO24: 17 | AP24: =U24*B24 -> 0 | AQ24: =U24*C24 -> 0 | AR24: =AQ24-AP24 -> 0 | AS24: =X24*B24 -> 0 | AT24: ok
A25: 17 | B25: 4100 | C25: 6000 | D25: =C25-B25 -> 1900 | E25: Impacto | F25: 0 | O25: 2 | U25: =T25+R25+P25+N25+L25+J25+H25 -> 0 | X25: =F25+G25+I25+K25+M25+O25+Q25+S25-H25-J25-L25-N25-P25-R25-T25-V25-W25 -> 2 | Y25: =G25+I25+K25+M25+O25+Q25+S25 -> 2 | Z25: =Y25*B25 -> 8200 | AA25: =H25*C25 -> 0 | AB25: =J25*C25 -> 0 | AC25: =L25*C25 -> 0 | AD25: =N25*C25 -> 0 | AE25: =P25*C25 -> 0 | AF25: =R25*C25 -> 0 | AG25: =T25*C25 -> 0 | AO25: 18 | AP25: =U25*B25 -> 0 | AQ25: =U25*C25 -> 0 | AR25: =AQ25-AP25 -> 0 | AS25: =X25*B25 -> 8200 | AT25: ok
A26: 18 | B26: 1300 | C26: 2200 | D26: =C26-B26 -> 900 | E26: Amoremio | F26: 0 | O26: 3 | U26: =T26+R26+P26+N26+L26+J26+H26 -> 0 | X26: =F26+G26+I26+K26+M26+O26+Q26+S26-H26-J26-L26-N26-P26-R26-T26-V26-W26 -> 3 | Y26: =G26+I26+K26+M26+O26+Q26+S26 -> 3 | Z26: =Y26*B26 -> 3900 | AA26: =H26*C26 -> 0 | AB26: =J26*C26 -> 0 | AC26: =L26*C26 -> 0 | AD26: =N26*C26 -> 0 | AE26: =P26*C26 -> 0 | AF26: =R26*C26 -> 0 | AG26: =T26*C26 -> 0 | AO26: 19 | AP26: =U26*B26 -> 0 | AQ26: =U26*C26 -> 0 | AR26: =AQ26-AP26 -> 0 | AS26: =X26*B26 -> 3900
A27: 19 | B27: 3900 | C27: 6000 | D27: =C27-B27 -> 2100 | E27: Camerata | F27: 0 | O27: 2 | U27: =T27+R27+P27+N27+L27+J27+H27 -> 0 | X27: =F27+G27+I27+K27+M27+O27+Q27+S27-H27-J27-L27-N27-P27-R27-T27-V27-W27 -> 2 | Y27: =G27+I27+K27+M27+O27+Q27+S27 -> 2 | Z27: =Y27*B27 -> 7800 | AA27: =H27*C27 -> 0 | AB27: =J27*C27 -> 0 | AC27: =L27*C27 -> 0 | AD27: =N27*C27 -> 0 | AE27: =P27*C27 -> 0 | AF27: =R27*C27 -> 0 | AG27: =T27*C27 -> 0 | AO27: 20 | AP27: =U27*B27 -> 0 | AQ27: =U27*C27 -> 0 | AR27: =AQ27-AP27 -> 0 | AS27: =X27*B27 -> 7800
A28: 20 | B28: 5100 | C28: 6500 | D28: =C28-B28 -> 1400 | E28: Alicia | F28: 0 | O28: 2 | U28: =T28+R28+P28+N28+L28+J28+H28 -> 0 | X28: =F28+G28+I28+K28+M28+O28+Q28+S28-H28-J28-L28-N28-P28-R28-T28-V28-W28 -> 2 | Y28: =G28+I28+K28+M28+O28+Q28+S28 -> 2 | Z28: =Y28*B28 -> 10200 | AA28: =H28*C28 -> 0 | AB28: =J28*C28 -> 0 | AC28: =L28*C28 -> 0 | AD28: =N28*C28 -> 0 | AE28: =P28*C28 -> 0 | AF28: =R28*C28 -> 0 | AG28: =T28*C28 -> 0 | AO28: 21 | AP28: =U28*B28 -> 0 | AQ28: =U28*C28 -> 0 | AR28: =AQ28-AP28 -> 0 | AS28: =X28*B28 -> 10200
A29: 21 | B29: 4200 | C29: 6000 | D29: =C29-B29 -> 1800 | E29: Mariposa absolut | F29: 1 | O29: 2 | P29: 1 | U29: =T29+R29+P29+N29+L29+J29+H29 -> 1 | X29: =F29+G29+I29+K29+M29+O29+Q29+S29-H29-J29-L29-N29-P29-R29-T29-V29-W29 -> 2 | Y29: =G29+I29+K29+M29+O29+Q29+S29 -> 2 | Z29: =Y29*B29 -> 8400 | AA29: =H29*C29 -> 0 | AB29: =J29*C29 -> 0 | AC29: =L29*C29 -> 0 | AD29: =N29*C29 -> 0 | AE29: =P29*C29 -> 6000 | AF29: =R29*C29 -> 0 | AG29: =T29*C29 -> 0 | AO29: 22 | AP29: =U29*B29 -> 4200 | AQ29: =U29*C29 -> 6000 | AR29: =AQ29-AP29 -> 1800 | AS29: =X29*B29 -> 8400
A30: 22 | B30: 3600 | C30: 5500 | D30: =C30-B30 -> 1900 | E30: Mariposa | F30: 2 | U30: =T30+R30+P30+N30+L30+J30+H30 -> 0 | X30: =F30+G30+I30+K30+M30+O30+Q30+S30-H30-J30-L30-N30-P30-R30-T30-V30-W30 -> 2 | Y30: =G30+I30+K30+M30+O30+Q30+S30 -> 0 | Z30: =Y30*B30 -> 0 | AA30: =H30*C30 -> 0 | AB30: =J30*C30 -> 0 | AC30: =L30*C30 -> 0 | AD30: =N30*C30 -> 0 | AE30: =P30*C30 -> 0 | AF30: =R30*C30 -> 0 | AG30: =T30*C30 -> 0 | AO30: 23 | AP30: =U30*B30 -> 0 | AQ30: =U30*C30 -> 0 | AR30: =AQ30-AP30 -> 0 | AS30: =X30*B30 -> 7200
A31: 23 | B31: 2600 | C31: 3800 | D31: =C31-B31 -> 1200 | E31: Blue Moon | F31: 0 | O31: 2 | U31: =T31+R31+P31+N31+L31+J31+H31 -> 0 | X31: =F31+G31+I31+K31+M31+O31+Q31+S31-H31-J31-L31-N31-P31-R31-T31-V31-W31 -> 2 | Y31: =G31+I31+K31+M31+O31+Q31+S31 -> 2 | Z31: =Y31*B31 -> 5200 | AA31: =H31*C31 -> 0 | AB31: =J31*C31 -> 0 | AC31: =L31*C31 -> 0 | AD31: =N31*C31 -> 0 | AE31: =P31*C31 -> 0 | AF31: =R31*C31 -> 0 | AG31: =T31*C31 -> 0 | AO31: 24 | AP31: =U31*B31 -> 0 | AQ31: =U31*C31 -> 0 | AR31: =AQ31-AP31 -> 0 | AS31: =X31*B31 -> 5200
A32: 24 | B32: 3800 | C32: 5700 | D32: =C32-B32 -> 1900 | E32: Veguero | F32: 1 | O32: 3 | U32: =T32+R32+P32+N32+L32+J32+H32 -> 0 | X32: =F32+G32+I32+K32+M32+O32+Q32+S32-H32-J32-L32-N32-P32-R32-T32-V32-W32 -> 4 | Y32: =G32+I32+K32+M32+O32+Q32+S32 -> 3 | Z32: =Y32*B32 -> 11400 | AA32: =H32*C32 -> 0 | AB32: =J32*C32 -> 0 | AC32: =L32*C32 -> 0 | AD32: =N32*C32 -> 0 | AE32: =P32*C32 -> 0 | AF32: =R32*C32 -> 0 | AG32: =T32*C32 -> 0 | AO32: 25 | AP32: =U32*B32 -> 0 | AQ32: =U32*C32 -> 0 | AR32: =AQ32-AP32 -> 0 | AS32: =X32*B32 -> 15200
A33: 25 | B33: 8500 | C33: 10000 | D33: =C33-B33 -> 1500 | E33: Habana 500 | F33: 2 | U33: =T33+R33+P33+N33+L33+J33+H33 -> 0 | X33: =F33+G33+I33+K33+M33+O33+Q33+S33-H33-J33-L33-N33-P33-R33-T33-V33-W33 -> 2 | Y33: =G33+I33+K33+M33+O33+Q33+S33 -> 0 | Z33: =Y33*B33 -> 0 | AA33: =H33*C33 -> 0 | AB33: =J33*C33 -> 0 | AC33: =L33*C33 -> 0 | AD33: =N33*C33 -> 0 | AE33: =P33*C33 -> 0 | AF33: =R33*C33 -> 0 | AG33: =T33*C33 -> 0 | AO33: 26 | AP33: =U33*B33 -> 0 | AQ33: =U33*C33 -> 0 | AR33: =AQ33-AP33 -> 0 | AS33: =X33*B33 -> 17000
A34: 26 | B34: 2000 | C34: 3500 | D34: =C34-B34 -> 1500 | E34: Perfume cuevita | F34: 4 | L34: 1 | O34: 6 | U34: =T34+R34+P34+N34+L34+J34+H34 -> 1 | X34: =F34+G34+I34+K34+M34+O34+Q34+S34-H34-J34-L34-N34-P34-R34-T34-V34-W34 -> 9 | Y34: =G34+I34+K34+M34+O34+Q34+S34 -> 6 | Z34: =Y34*B34 -> 12000 | AA34: =H34*C34 -> 0 | AB34: =J34*C34 -> 0 | AC34: =L34*C34 -> 3500 | AD34: =N34*C34 -> 0 | AE34: =P34*C34 -> 0 | AF34: =R34*C34 -> 0 | AG34: =T34*C34 -> 0 | AO34: 27 | AP34: =U34*B34 -> 2000 | AQ34: =U34*C34 -> 3500 | AR34: =AQ34-AP34 -> 1500 | AS34: =X34*B34 -> 18000
A35: 27 | B35: 2800 | C35: 4000 | D35: =C35-B35 -> 1200 | E35: Nao | F35: 1 | O35: 2 | P35: 1 | U35: =T35+R35+P35+N35+L35+J35+H35 -> 1 | X35: =F35+G35+I35+K35+M35+O35+Q35+S35-H35-J35-L35-N35-P35-R35-T35-V35-W35 -> 2 | Y35: =G35+I35+K35+M35+O35+Q35+S35 -> 2 | Z35: =Y35*B35 -> 5600 | AA35: =H35*C35 -> 0 | AB35: =J35*C35 -> 0 | AC35: =L35*C35 -> 0 | AD35: =N35*C35 -> 0 | AE35: =P35*C35 -> 4000 | AF35: =R35*C35 -> 0 | AG35: =T35*C35 -> 0 | AO35: 28 | AP35: =U35*B35 -> 2800 | AQ35: =U35*C35 -> 4000 | AR35: =AQ35-AP35 -> 1200 | AS35: =X35*B35 -> 5600
A36: 28 | B36: 1250 | C36: 1700 | D36: =C36-B36 -> 450 | E36: Perfume No. | F36: 8 | L36: 1 | P36: 2 | R36: 1 | T36: 1 | U36: =T36+R36+P36+N36+L36+J36+H36 -> 5 | X36: =F36+G36+I36+K36+M36+O36+Q36+S36-H36-J36-L36-N36-P36-R36-T36-V36-W36 -> 3 | Y36: =G36+I36+K36+M36+O36+Q36+S36 -> 0 | Z36: =Y36*B36 -> 0 | AA36: =H36*C36 -> 0 | AB36: =J36*C36 -> 0 | AC36: =L36*C36 -> 1700 | AD36: =N36*C36 -> 0 | AE36: =P36*C36 -> 3400 | AF36: =R36*C36 -> 1700 | AG36: =T36*C36 -> 1700 | AO36: 29 | AP36: =U36*B36 -> 6250 | AQ36: =U36*C36 -> 8500 | AR36: =AQ36-AP36 -> 2250 | AS36: =X36*B36 -> 3750
A37: 29 | B37: 2000 | C37: 3500 | D37: =C37-B37 -> 1500 | E37: Perfume cuevita | F37: 7 | U37: =T37+R37+P37+N37+L37+J37+H37 -> 0 | X37: =F37+G37+I37+K37+M37+O37+Q37+S37-H37-J37-L37-N37-P37-R37-T37-V37-W37 -> 7 | Y37: =G37+I37+K37+M37+O37+Q37+S37 -> 0 | Z37: =Y37*B37 -> 0 | AA37: =H37*C37 -> 0 | AB37: =J37*C37 -> 0 | AC37: =L37*C37 -> 0 | AD37: =N37*C37 -> 0 | AE37: =P37*C37 -> 0 | AF37: =R37*C37 -> 0 | AG37: =T37*C37 -> 0 | AO37: 30 | AP37: =U37*B37 -> 0 | AQ37: =U37*C37 -> 0 | AR37: =AQ37-AP37 -> 0 | AS37: =X37*B37 -> 14000
A38: 30 | B38: 2300 | C38: 3500 | D38: =C38-B38 -> 1200 | E38: Elements | F38: 3 | N38: 2 | O38: 3 | U38: =T38+R38+P38+N38+L38+J38+H38 -> 2 | X38: =F38+G38+I38+K38+M38+O38+Q38+S38-H38-J38-L38-N38-P38-R38-T38-V38-W38 -> 4 | Y38: =G38+I38+K38+M38+O38+Q38+S38 -> 3 | Z38: =Y38*B38 -> 6900 | AA38: =H38*C38 -> 0 | AB38: =J38*C38 -> 0 | AC38: =L38*C38 -> 0 | AD38: =N38*C38 -> 7000 | AE38: =P38*C38 -> 0 | AF38: =R38*C38 -> 0 | AG38: =T38*C38 -> 0 | AO38: 31 | AP38: =U38*B38 -> 4600 | AQ38: =U38*C38 -> 7000 | AR38: =AQ38-AP38 -> 2400 | AS38: =X38*B38 -> 9200
A39: 31 | B39: 2800 | C39: 3800 | D39: =C39-B39 -> 1000 | E39: Complice | F39: 0 | U39: =T39+R39+P39+N39+L39+J39+H39 -> 0 | X39: =F39+G39+I39+K39+M39+O39+Q39+S39-H39-J39-L39-N39-P39-R39-T39-V39-W39 -> 0 | Y39: =G39+I39+K39+M39+O39+Q39+S39 -> 0 | Z39: =Y39*B39 -> 0 | AA39: =H39*C39 -> 0 | AB39: =J39*C39 -> 0 | AC39: =L39*C39 -> 0 | AD39: =N39*C39 -> 0 | AE39: =P39*C39 -> 0 | AF39: =R39*C39 -> 0 | AG39: =T39*C39 -> 0 | AO39: 32 | AP39: =U39*B39 -> 0 | AQ39: =U39*C39 -> 0 | AR39: =AQ39-AP39 -> 0 | AS39: =X39*B39 -> 0
A40: 32 | B40: 3300 | C40: 5000 | D40: =C40-B40 -> 1700 | E40: S/C | F40: 2 | J40: 1 | U40: =T40+R40+P40+N40+L40+J40+H40 -> 1 | X40: =F40+G40+I40+K40+M40+O40+Q40+S40-H40-J40-L40-N40-P40-R40-T40-V40-W40 -> 1 | Y40: =G40+I40+K40+M40+O40+Q40+S40 -> 0 | Z40: =Y40*B40 -> 0 | AA40: =H40*C40 -> 0 | AB40: =J40*C40 -> 5000 | AC40: =L40*C40 -> 0 | AD40: =N40*C40 -> 0 | AE40: =P40*C40 -> 0 | AF40: =R40*C40 -> 0 | AG40: =T40*C40 -> 0 | AO40: 33 | AP40: =U40*B40 -> 3300 | AQ40: =U40*C40 -> 5000 | AR40: =AQ40-AP40 -> 1700 | AS40: =X40*B40 -> 3300
A41: 33 | B41: 3000 | C41: 4000 | D41: =C41-B41 -> 1000 | E41: Blue Marlin | F41: 2 | N41: 1 | O41: 2 | R41: 1 | U41: =T41+R41+P41+N41+L41+J41+H41 -> 2 | X41: =F41+G41+I41+K41+M41+O41+Q41+S41-H41-J41-L41-N41-P41-R41-T41-V41-W41 -> 2 | Y41: =G41+I41+K41+M41+O41+Q41+S41 -> 2 | Z41: =Y41*B41 -> 6000 | AA41: =H41*C41 -> 0 | AB41: =J41*C41 -> 0 | AC41: =L41*C41 -> 0 | AD41: =N41*C41 -> 4000 | AE41: =P41*C41 -> 0 | AF41: =R41*C41 -> 4000 | AG41: =T41*C41 -> 0 | AO41: 34 | AP41: =U41*B41 -> 6000 | AQ41: =U41*C41 -> 8000 | AR41: =AQ41-AP41 -> 2000 | AS41: =X41*B41 -> 6000
A42: 34 | B42: 4100 | C42: 6000 | D42: =C42-B42 -> 1900 | E42: MARIPOSA | F42: 0 | O42: 4 | R42: 1 | U42: =T42+R42+P42+N42+L42+J42+H42 -> 1 | X42: =F42+G42+I42+K42+M42+O42+Q42+S42-H42-J42-L42-N42-P42-R42-T42-V42-W42 -> 3 | Y42: =G42+I42+K42+M42+O42+Q42+S42 -> 4 | Z42: =Y42*B42 -> 16400 | AA42: =H42*C42 -> 0 | AB42: =J42*C42 -> 0 | AC42: =L42*C42 -> 0 | AD42: =N42*C42 -> 0 | AE42: =P42*C42 -> 0 | AF42: =R42*C42 -> 6000 | AG42: =T42*C42 -> 0 | AO42: 35 | AP42: =U42*B42 -> 4100 | AQ42: =U42*C42 -> 6000 | AR42: =AQ42-AP42 -> 1900 | AS42: =X42*B42 -> 12300
A43: 35 | B43: 2600 | C43: 3600 | D43: =C43-B43 -> 1000 | E43: Revelde | F43: 1 | O43: 2 | P43: 1 | U43: =T43+R43+P43+N43+L43+J43+H43 -> 1 | X43: =F43+G43+I43+K43+M43+O43+Q43+S43-H43-J43-L43-N43-P43-R43-T43-V43-W43 -> 2 | Y43: =G43+I43+K43+M43+O43+Q43+S43 -> 2 | Z43: =Y43*B43 -> 5200 | AA43: =H43*C43 -> 0 | AB43: =J43*C43 -> 0 | AC43: =L43*C43 -> 0 | AD43: =N43*C43 -> 0 | AE43: =P43*C43 -> 3600 | AF43: =R43*C43 -> 0 | AG43: =T43*C43 -> 0 | AO43: 36 | AP43: =U43*B43 -> 2600 | AQ43: =U43*C43 -> 3600 | AR43: =AQ43-AP43 -> 1000 | AS43: =X43*B43 -> 5200
A44: 36 | B44: 1600 | C44: 3500 | D44: =C44-B44 -> 1900 | E44: Perfume Arabe | F44: 2 | U44: =T44+R44+P44+N44+L44+J44+H44 -> 0 | X44: =F44+G44+I44+K44+M44+O44+Q44+S44-H44-J44-L44-N44-P44-R44-T44-V44-W44 -> 2 | Y44: =G44+I44+K44+M44+O44+Q44+S44 -> 0 | Z44: =Y44*B44 -> 0 | AA44: =H44*C44 -> 0 | AB44: =J44*C44 -> 0 | AC44: =L44*C44 -> 0 | AD44: =N44*C44 -> 0 | AE44: =P44*C44 -> 0 | AF44: =R44*C44 -> 0 | AG44: =T44*C44 -> 0 | AO44: 37 | AP44: =U44*B44 -> 0 | AQ44: =U44*C44 -> 0 | AR44: =AQ44-AP44 -> 0 | AS44: =X44*B44 -> 3200
A45: 37 | B45: 2600 | C45: 3500 | D45: =C45-B45 -> 900 | E45: Alas de mariposa | F45: 1 | T45: 1 | U45: =T45+R45+P45+N45+L45+J45+H45 -> 1 | X45: =F45+G45+I45+K45+M45+O45+Q45+S45-H45-J45-L45-N45-P45-R45-T45-V45-W45 -> 0 | Y45: =G45+I45+K45+M45+O45+Q45+S45 -> 0 | Z45: =Y45*B45 -> 0 | AA45: =H45*C45 -> 0 | AB45: =J45*C45 -> 0 | AC45: =L45*C45 -> 0 | AD45: =N45*C45 -> 0 | AE45: =P45*C45 -> 0 | AF45: =R45*C45 -> 0 | AG45: =T45*C45 -> 3500 | AO45: 38 | AP45: =U45*B45 -> 2600 | AQ45: =U45*C45 -> 3500 | AR45: =AQ45-AP45 -> 900 | AS45: =X45*B45 -> 0
A46: 38 | B46: 1100 | C46: 2000 | D46: =C46-B46 -> 900 | E46: Colonia V V | F46: 0 | U46: =T46+R46+P46+N46+L46+J46+H46 -> 0 | X46: =F46+G46+I46+K46+M46+O46+Q46+S46-H46-J46-L46-N46-P46-R46-T46-V46-W46 -> 0 | Y46: =G46+I46+K46+M46+O46+Q46+S46 -> 0 | Z46: =Y46*B46 -> 0 | AA46: =H46*C46 -> 0 | AB46: =J46*C46 -> 0 | AC46: =L46*C46 -> 0 | AD46: =N46*C46 -> 0 | AE46: =P46*C46 -> 0 | AF46: =R46*C46 -> 0 | AG46: =T46*C46 -> 0 | AO46: 39 | AP46: =U46*B46 -> 0 | AQ46: =U46*C46 -> 0 | AR46: =AQ46-AP46 -> 0 | AS46: =X46*B46 -> 0
A47: 39 | B47: 850 | C47: 1300 | D47: =C47-B47 -> 450 | E47: Mini colonia | F47: 0 | U47: =T47+R47+P47+N47+L47+J47+H47 -> 0 | X47: =F47+G47+I47+K47+M47+O47+Q47+S47-H47-J47-L47-N47-P47-R47-T47-V47-W47 -> 0 | Y47: =G47+I47+K47+M47+O47+Q47+S47 -> 0 | Z47: =Y47*B47 -> 0 | AA47: =H47*C47 -> 0 | AB47: =J47*C47 -> 0 | AC47: =L47*C47 -> 0 | AD47: =N47*C47 -> 0 | AE47: =P47*C47 -> 0 | AF47: =R47*C47 -> 0 | AG47: =T47*C47 -> 0 | AO47: 40 | AP47: =U47*B47 -> 0 | AQ47: =U47*C47 -> 0 | AR47: =AQ47-AP47 -> 0 | AS47: =X47*B47 -> 0
A48: 40 | B48: 850 | C48: 1200 | D48: =C48-B48 -> 350 | E48: Mini colonia | F48: 0 | U48: =T48+R48+P48+N48+L48+J48+H48 -> 0 | X48: =F48+G48+I48+K48+M48+O48+Q48+S48-H48-J48-L48-N48-P48-R48-T48-V48-W48 -> 0 | Y48: =G48+I48+K48+M48+O48+Q48+S48 -> 0 | Z48: =Y48*B48 -> 0 | AA48: =H48*C48 -> 0 | AB48: =J48*C48 -> 0 | AC48: =L48*C48 -> 0 | AD48: =N48*C48 -> 0 | AE48: =P48*C48 -> 0 | AF48: =R48*C48 -> 0 | AG48: =T48*C48 -> 0 | AO48: 41 | AP48: =U48*B48 -> 0 | AQ48: =U48*C48 -> 0 | AR48: =AQ48-AP48 -> 0 | AS48: =X48*B48 -> 0
A49: 41 | B49: 1250 | C49: 2300 | D49: =C49-B49 -> 1050 | E49: Colonia Love | F49: 6 | O49: 12 | T49: 1 | U49: =T49+R49+P49+N49+L49+J49+H49 -> 1 | X49: =F49+G49+I49+K49+M49+O49+Q49+S49-H49-J49-L49-N49-P49-R49-T49-V49-W49 -> 17 | Y49: =G49+I49+K49+M49+O49+Q49+S49 -> 12 | Z49: =Y49*B49 -> 15000 | AA49: =H49*C49 -> 0 | AB49: =J49*C49 -> 0 | AC49: =L49*C49 -> 0 | AD49: =N49*C49 -> 0 | AE49: =P49*C49 -> 0 | AF49: =R49*C49 -> 0 | AG49: =T49*C49 -> 2300 | AO49: 42 | AP49: =U49*B49 -> 1250 | AQ49: =U49*C49 -> 2300 | AR49: =AQ49-AP49 -> 1050 | AS49: =X49*B49 -> 21250
A50: 42 | B50: 1250 | C50: 2200 | D50: =C50-B50 -> 950 | E50: Colonia Bella | F50: 0 | U50: =T50+R50+P50+N50+L50+J50+H50 -> 0 | X50: =F50+G50+I50+K50+M50+O50+Q50+S50-H50-J50-L50-N50-P50-R50-T50-V50-W50 -> 0 | Y50: =G50+I50+K50+M50+O50+Q50+S50 -> 0 | Z50: =Y50*B50 -> 0 | AA50: =H50*C50 -> 0 | AB50: =J50*C50 -> 0 | AC50: =L50*C50 -> 0 | AD50: =N50*C50 -> 0 | AE50: =P50*C50 -> 0 | AF50: =R50*C50 -> 0 | AG50: =T50*C50 -> 0 | AO50: 43 | AP50: =U50*B50 -> 0 | AQ50: =U50*C50 -> 0 | AR50: =AQ50-AP50 -> 0 | AS50: =X50*B50 -> 0
A51: 43 | B51: 1500 | C51: 2000 | D51: =C51-B51 -> 500 | E51: Colonia Gorda | F51: 0 | O51: 12 | R51: 1 | T51: 1 | U51: =T51+R51+P51+N51+L51+J51+H51 -> 2 | X51: =F51+G51+I51+K51+M51+O51+Q51+S51-H51-J51-L51-N51-P51-R51-T51-V51-W51 -> 10 | Y51: =G51+I51+K51+M51+O51+Q51+S51 -> 12 | Z51: =Y51*B51 -> 18000 | AA51: =H51*C51 -> 0 | AB51: =J51*C51 -> 0 | AC51: =L51*C51 -> 0 | AD51: =N51*C51 -> 0 | AE51: =P51*C51 -> 0 | AF51: =R51*C51 -> 2000 | AG51: =T51*C51 -> 2000 | AO51: 44 | AP51: =U51*B51 -> 3000 | AQ51: =U51*C51 -> 4000 | AR51: =AQ51-AP51 -> 1000 | AS51: =X51*B51 -> 15000
A52: 44 | B52: 1150 | C52: 1500 | D52: =C52-B52 -> 350 | E52: Colonia Bonabel | F52: 3 | P52: 1 | U52: =T52+R52+P52+N52+L52+J52+H52 -> 1 | X52: =F52+G52+I52+K52+M52+O52+Q52+S52-H52-J52-L52-N52-P52-R52-T52-V52-W52 -> 2 | Y52: =G52+I52+K52+M52+O52+Q52+S52 -> 0 | Z52: =Y52*B52 -> 0 | AA52: =H52*C52 -> 0 | AB52: =J52*C52 -> 0 | AC52: =L52*C52 -> 0 | AD52: =N52*C52 -> 0 | AE52: =P52*C52 -> 1500 | AF52: =R52*C52 -> 0 | AG52: =T52*C52 -> 0 | AO52: 45 | AP52: =U52*B52 -> 1150 | AQ52: =U52*C52 -> 1500 | AR52: =AQ52-AP52 -> 350 | AS52: =X52*B52 -> 2300
A53: 45 | B53: 580 | C53: 850 | D53: =C53-B53 -> 270 | E53: Toallitas humeda | F53: 2 | L53: 2 | O53: 24 | T53: 1 | U53: =T53+R53+P53+N53+L53+J53+H53 -> 3 | X53: =F53+G53+I53+K53+M53+O53+Q53+S53-H53-J53-L53-N53-P53-R53-T53-V53-W53 -> 23 | Y53: =G53+I53+K53+M53+O53+Q53+S53 -> 24 | Z53: =Y53*B53 -> 13920 | AA53: =H53*C53 -> 0 | AB53: =J53*C53 -> 0 | AC53: =L53*C53 -> 1700 | AD53: =N53*C53 -> 0 | AE53: =P53*C53 -> 0 | AF53: =R53*C53 -> 0 | AG53: =T53*C53 -> 850 | AO53: 46 | AP53: =U53*B53 -> 1740 | AQ53: =U53*C53 -> 2550 | AR53: =AQ53-AP53 -> 810 | AS53: =X53*B53 -> 13340
